Workbook

Sheet SOW, Feedbacks-Bug & CR_Items
A1: Area | B1: Feature | C1: Functionality | D1: Module | E1: Phase | F1: Status | G1: Remarks | H1: Requested Date | I1: ETA | J1: Resource | K1: Jira ID
A2: FRAMEWORK: Frontend | B2: Project setup | C2: Basic project / Development environment setup | D2: Framework | E2: Milestone 1 | F2: Delivered | H2: 45717 | K2: IIRM-17
A3: FRAMEWORK: Frontend | B3: UI Approach Design System | C3: Building Design System | D3: Framework | E3: Milestone 1 | F3: Delivered | H3: 45717 | K3: IIRM-734
A4: FRAMEWORK: Frontend | B4: Core Infrastructure | C4: Core Infra | D4: Framework | E4: Milestone 1 | F4: Delivered | H4: 45717
A5: FRAMEWORK: Frontend | B5: Build UI components | C5: This includes all the UI componnets to compose the application and module definitions: Form, Toast, Filter, Cards, Visualisation, Grid, Menu, Header, Footer, Maps Integration | D5: Framework | E5: Milestone 1 | F5: Delivered | H5: 45717 | K5: IIRM-836
A6: FRAMEWORK: Frontend | B6: UI Approach Style Establishment | C6: UI Style Establishment | D6: Framework | E6: Milestone 1 | F6: Delivered | H6: 45717 | K6: IIRM-838
A7: FRAMEWORK: Frontend | B7: Service Workers Implementation | D7: Framework | E7: Milestone 1 | F7: Delivered | H7: 45717 | K7: IIRM-19
A8: FRAMEWORK: Frontend | B8: Core System | D8: Framework | E8: Milestone 1 | F8: Delivered | H8: 45717 | K8: IIRM-80
A9: FRAMEWORK: Frontend | B9: ACL & RBAC Control Framework | D9: Framework | E9: Milestone 1 | F9: Delivered | H9: 45717 | K9: IIRM-18
A10: FRAMEWORK: Frontend | B10: Micro Frontend Setup | D10: Framework | E10: Milestone 1 | F10: Delivered | H10: 45717 | K10: IIRM-15
A11: FRAMEWORK: Frontend | B11: Landing Page | D11: Framework | E11: Milestone 1 | F11: Delivered | H11: 45717
A12: FRAMEWORK: Services - Basic Modules | B12: Access Control Management | D12: Framework | E12: Milestone 1 | F12: Delivered | H12: 45717 | K12: IIRM-1528
A13: FRAMEWORK: Services - Larger Modules | B13: Auth Module (Simple Auth) | D13: Framework | E13: Milestone 1 | F13: Delivered | H13: 45717 | K13: IIRM-62
A14: FRAMEWORK: Services - Larger Modules | B14: Micro Service Framework Setup | D14: Framework | E14: Milestone 1 | F14: Delivered | H14: 45717 | K14: IIRM-16, IIRM-834
A15: iWORK: Services - Basic Modules | B15: Employee Mgmt | D15: iWork | E15: Milestone 1 | F15: Delivered | G15: User deletion need to be handled | H15: 45717 | I15: 46185
A16: iWORK: Common Components | B16: Common - Audit Trail Mgmt - Becomes critical in this phase iteself | D16: iWork | E16: Milestone 1 | F16: Delivered | H16: 45717
A17: iWORK: Frontend | B17: Add/View/Edit Opportunity | C17: Add Medium size form with 1->N list of Claims; Multiple drop downs Large View with several widgets, Simple Edit | D17: iWork | E17: Milestone 1 | F17: Delivered | H17: 45717 | K17: IIRM-740
A18: iWORK: Frontend | B18: Manage TPA/Insurer | C18: Basic Add, View with edit of basic data, with lists of policies/companies | D18: iWork | E18: Milestone 1 | F18: Delivered | H18: 45717 | K18: IIRM-741, IIRM-742
A19: iWORK: Frontend | B19: Core Infra | C19: Infrastructure | D19: iWork | E19: Milestone 1 | F19: Delivered | H19: 45717
A20: iWORK: Frontend | B20: Add/View/Edit Company | C20: Large form with basic format based validations, some mandatory fields, multiple addresses, couple of Rich Text Editor fields; Some multi-line fields (e.g., GST), uploads; Duplicate detection on Company name, GST/PAN etc. Simple edit like Add; View is multiple widgets (Contacts, Opportunities, Policies, Claims, SLAs, Document list) | D20: iWork | E20: Milestone 1 | F20: Delivered | H20: 45717
A21: iWORK: Frontend | B21: Insurer/TPA Hub | C21: List with Filter/Search | D21: iWork | E21: Milestone 1 | F21: Delivered | H21: 45717
A22: iWORK: Frontend | B22: Add/View/Edit Contact | C22: Simple edit like Add Contacts should maintain Company history although only 1 Company active with 1 contact; Medium size form with fields, linked in connect | D22: iWork | E22: Milestone 1 | F22: Delivered | H22: 45717 | K22: IIRM-1556
A23: iWORK: Frontend | B23: Company (Prospect) Hub | C23: Top 10/Latest companies, with search/filter, Table of basic attributes with GPS etc. | D23: iWork | E23: Milestone 1 | F23: Delivered | H23: 45717 | K23: IIRM-1560
A24: iWORK: Frontend | B24: Contact Hub | C24: Top 10/Latest Contacts, with search/filter, list with basic attributes | D24: iWork | E24: Milestone 1 | F24: Delivered | H24: 45717
A25: iWORK: Frontend | B25: Opportunity Hub | C25: Top Opportunities with search/filter, List of opportunities with high level summaries | D25: iWork | E25: Milestone 1 | F25: Delivered | H25: 45717 | K25: IIRM-811
A26: iWORK: Services - Basic Modules | B26: Contact /Company/Insurer/TPA Mgmt | D26: iWork | E26: Milestone 1 | F26: Delivered | H26: 45717
A27: iWORK: Services - Basic Modules | B27: Task Mgmt | D27: iWork | E27: Milestone 1 | F27: Delivered | H27: 45717 | K27: IIRM-738
A28: iWORK: Services - Basic Modules | B28: Meeting Mgmt | D28: iWork | E28: Milestone 1 | F28: Delivered | H28: 45717 | K28: IIRM-738
A29: iWORK: Services - Basic Modules | B29: RBAC and ACL setup for Iwork Module | D29: iWork | E29: Milestone 1 | F29: Delivered | H29: 45717 | K29: IIRM-18
A30: iWORK: Services - Basic Modules | B30: Opportunity Mgmt | D30: iWork | E30: Milestone 1 | F30: Delivered | H30: 45717 | K30: IIRM-740
A31: FRAMEWORK: Frontend | B31: Master Data Management | D31: Framework | E31: Milestone 2 | F31: Delivered | H31: 45763 | I31: 46169 | K31: IIRM-745
A32: FRAMEWORK: Frontend | B32: User Management | C32: 22-May: Other than iWork employee | D32: Framework | E32: Milestone 2 | F32: Delivered | G32: Pending: User deletion | H32: 45763 | I32: 46185 | K32: IIRM-744
A33: FRAMEWORK: Services - Basic Modules | B33: User Management | C33: 22-May: Other than iWork employee | D33: Framework | E33: Milestone 2 | F33: Delivered | G33: Pending: User deletion | H33: 45763 | I33: 46185 | K33: IIRM-744
A34: FRAMEWORK: Services - Larger Modules | B34: Data Security Considerations | D34: Framework | E34: Milestone 2 | F34: Delivered | G34: Duplicate of Covers in DPDP items | H34: 45763 | I34: 46203 | K34: IIRM-749
A35: FRAMEWORK: Frontend | B35: Visualization framework | C35: Charts and KPIs | D35: Framework | E35: Milestone 2 | F35: Delivered | H35: 45763 | K35: IIRM-743
A36: FRAMEWORK: Frontend | B36: Document Management | C36: Create, Upload, Seach, Download | D36: Framework | E36: Milestone 2 | F36: Delivered | H36: 45763 | K36: IIRM-750
A37: FRAMEWORK: Frontend | B37: Caching of API Data | D37: Framework | E37: Milestone 2 | F37: Delivered | H37: 45763
A38: FRAMEWORK: Services - Basic Modules | B38: Audit Data Capturing | D38: Framework | E38: Milestone 2 | F38: Delivered | H38: 45763 | K38: IIRM-4613
A39: FRAMEWORK: Services - Larger Modules | B39: CMS | D39: Framework | E39: Milestone 2 | F39: Delivered | G39: Used in IBP | H39: 45763 | K39: IIRM-750
A40: FRAMEWORK: Services - Basic Modules | B40: Notification and Communication Management | D40: Framework | E40: Milestone 2 | F40: Delivered | H40: 45763 | K40: IIRM-746
A41: FRAMEWORK: Services - Basic Modules | B41: Usage Tracking System (Reports) | C41: 23-May: Handle as a part of Reports | D41: Framework | E41: Milestone 2 | F41: Delivered | H41: 45763
A42: iWORK: Frontend | B42: Common Data Mapping Component | C42: Map input fields to output fields & Order | D42: iWork | E42: Milestone 2 | F42: Delivered | G42: Pending: Additional/Dynamic columns | H42: 45763 | I42: 46182
A43: iWORK: AI Components | B43: AI - (Non-OCR) Digital Document Processing for Content recognition (Company/Opportunity/Contact Creation from Previous Policy Document, Bizcard document) | D43: iWork | E43: Milestone 2 | F43: Delivered | H43: 45763
A44: iWORK: AI Components | B44: AI - OCR for Content Collection | D44: iWork | E44: Milestone 2 | F44: Delivered | H44: 45763
A45: iWORK: AI Components | B45: AI - Company Information by AI Search | D45: iWork | E45: Milestone 2 | F45: Delivered | H45: 45763
A46: iWORK: Common Components | B46: Common, Contexual Upload Component | D46: iWork | E46: Milestone 2 | F46: Delivered | H46: 45763
A47: iWORK: Common Components | B47: Common, Contexual Read and Spread Component (Utility) | D47: iWork | E47: Milestone 2 | F47: Delivered | H47: 45763
A48: iWORK: Frontend | B48: Manage Stage Planning/Performance/Approval | C48: Add iWork Stages (table) - Dates with each iWork Stage and who are the team members assigned to each Stage; Once all iWork stages are complete, ISG Team activities must be planned ISG Team can approve/reject each iWork Stage. Approving RFP Stage approves all iWork stages Completion of each iWork Stage (Activity) & ISG Stage - Comments, Attach Document, Date recorded, submit | D48: iWork | E48: Milestone 2 | F48: Delivered | H48: 45763 | K48: IIRM-752
A49: iWORK: Frontend | B49: Smart Add Component | C49: Allow Upload of Document/Image, select what to create (Company/Contact/Opportunity) | D49: iWork | E49: Milestone 2 | F49: Delivered | H49: 45763 | K49: IIRM-754
A50: iWORK: Frontend | B50: Dashboard - Drilldowns | C50: Drill down from the Tables (Targets vs. Actuals, Pending Activities, Followups, AR Report, Schedule) | D50: iWork | E50: Milestone 2 | F50: Delivered | H50: 45763 | K50: IIRM-751
A51: iWORK: Frontend | B51: Sales Team Hierarchy | C51: Hierarchy / Org chart tied to Platform Users | D51: iWork | E51: Milestone 2 | F51: Delivered | H51: 45763 | K51: IIRM-753
A52: iWORK: Frontend | B52: View Policy | C52: Long View, multiple widgets/entities, endorsements (each month), Claims, etc. | D52: iWork | E52: Milestone 2 | F52: Delivered | H52: 45763
A53: iWORK: Frontend | B53: Dashboard | C53: Multiple KPI Cards: Business Performance, Svc Performance, Table of targets vs. actuals vs. lost, Sales Funnel, Renewal Funnel, Servce Funnel, AR from Insurers, Pending Activities(iWork Stages) Widget, Followups widget, Meetings widget Filters available (Geo, Branch, Team/Team Member, Dates), Approvals, iWork Stages, Tasks, Meetings | D53: iWork | E53: Milestone 2 | F53: Delivered | H53: 45763
A54: iWORK: Frontend | B54: Dashboard - Pending tasks, approvals | C54: Pending tasks/approvals, | D54: iWork | E54: Milestone 2 | F54: Delivered | H54: 45763
A55: iWORK: Frontend | B55: Reports - Biz Done | C55: Report View, Download, List of earlier snaps of the report, Search and Filter | D55: iWork | E55: Milestone 2 | F55: Delivered | H55: 45763
A56: iWORK: Services - Basic Modules | B56: Core Infrastructure | C56: Core Infra | D56: iWork | E56: Milestone 2 | F56: Delivered | H56: 45763
A57: iWORK: Services - Basic Modules | B57: Organisation, Branch, Employee, & Hierarchy Mgmt | D57: iWork | E57: Milestone 2 | F57: Delivered | H57: 45763
A58: iWORK: Services - Basic Modules | B58: Dashboard (Place Holder) | D58: iWork | E58: Milestone 2 | F58: Delivered | H58: 45763
A59: iWORK: Services - Basic Modules | B59: Planning, Perform and Approval Mgmt | D59: iWork | E59: Milestone 2 | F59: Delivered | H59: 45763
A60: iWORK: Services - Basic Modules | B60: Policy Mgmt | D60: iWork | E60: Milestone 2 | F60: Delivered | H60: 45763
A61: iWORK: Services - Basic Modules | B61: Master Data Mgmt {Common, Contexual Master Data Mgmt} | D61: iWork | E61: Milestone 2 | F61: Delivered | H61: 45763 | K61: IIRM-745
A62: iWORK: Services - Basic Modules | B62: Cut Off Mgmt | D62: iWork | E62: Milestone 2 | F62: Pre-PROD | H62: 45763 | I62: 46237 | J62: Karan
A63: FRAMEWORK: Services - Larger Modules | B63: Document Generation | D63: Framework | E63: Milestone 3 | F63: Delivered | H63: 45793 | K63: IIRM-760
A64: iWORK: Services - Basic Modules | B64: Cover Mgmt | D64: iWork | E64: Milestone 3 | F64: Delivered | H64: 45793 | I64: 46183 | J64: Karan
A65: iWORK: Frontend | B65: Manage Policy (Endorsements) | C65: Add Endorsement - basic form with uploads of excel/document Validations of endorsement format - Map customer fields to internal fields Map internal fields to TPA fields (occasional per TPA) View/Update Endorsement, List View, Endorsement Performance | D65: iWork | E65: Milestone 3 | F65: Delivered | H65: 45793 | K65: IIRM-757
A66: iWORK: Services - Basic Modules | B66: Stage Mgmt (Activity/Transaction/Quote) | D66: iWork | E66: Milestone 3 | F66: Delivered | H66: 45793
A67: iWORK: Services - Basic Modules | B67: Asset/Member Data Mgmt | D67: iWork | E67: Milestone 3 | F67: Delivered | H67: 45793 | K67: IIRM-759
A68: iWORK: Services - Basic Modules | B68: Endorsement Mgmt | D68: iWork | E68: Milestone 3 | F68: Delivered | H68: 45793 | K68: IIRM-757
A69: iWORK: Frontend | B69: MIR Entry Mgmt | C69: Entry Form, Print to Document, List of Earlier MIRs, Search on MIRs | D69: iWork | E69: Milestone 3 | F69: Delivered | H69: 45793 | I69: 46225 | J69: Sunil | K69: IIRM-758
A70: iWORK: Services - Basic Modules | B70: MIR Entry Mgmt | C70: Module to manage MIR {Monthly Infomatiom Report} | D70: iWork | E70: Milestone 3 | F70: Delivered | H70: 45793 | I70: 46225 | J70: Sunil | K70: IIRM-758
A71: Production - Bug | B71: Enrolment Journey - Component - Notes | C71: Policy Level - Component Notes from Stapi | D71: IBP | E71: Milestone 6 | F71: Yet to start | G71: Kriti raised | H71: 46232 | I71: 46238
A72: FRAMEWORK: Services - Basic Modules | B72: Configuration Management | D72: Framework | E72: Milestone 4 | F72: Delivered | H72: 45818 | K72: IIRM-762
A73: FRAMEWORK: Services - Basic Modules | B73: Feature Flag Control Management | D73: Framework | E73: Milestone 4 | F73: Delivered | H73: 45818
A74: FRAMEWORK: Services - Larger Modules | B74: Localistation Management | D74: Framework | E74: Milestone 4 | F74: Delivered | H74: 45818 | K74: IIRM-764
A75: FRAMEWORK: Services - Larger Modules | B75: Caching Implementation | D75: Framework | E75: Milestone 4 | F75: Delivered | H75: 45818
A76: FRAMEWORK: Frontend | B76: Notifications Management | C76: Different email notification - Madhav excel. 1. Renewal Reminders - ASAP 2. Instalment Reminders 3. Others | D76: Framework | E76: Milestone 4 | F76: Pre-PROD | H76: 45818 | I76: 46237 | J76: Pushyami | K76: IIRM-761, IIRM-4740
A77: FRAMEWORK: Services - Larger Modules | B77: Workflow Management | C77: 23-May: Integrate the 3'rd party libraries | D77: Framework | E77: Milestone 4 | F77: Not in scope | G77: 23-Jul-2026: As per Gopal as this system custom and most of the data is driven from Master creating/plug any 3'rd Party will make complex. | H77: 45818 | K77: IIRM-766
A78: iWORK: Services - Basic Modules | B78: Archived Oppurtunity, Policy Mgmt {Archived Biz Data and Retrieval on need} - DPDP | D78: DPDP | E78: Milestone 4 | F78: Yet to start | G78: Duplicate of Archival from NFR & DPDP | H78: 45818 | I78: 46241 | J78: Rama
A79: iWORK: Frontend | B79: Reports | C79: Generic template for all the reports, Bizdone Report, Missing entries from commission statement against policies | D79: iWork | E79: Milestone 5 | F79: Delivered - Deficit | G79: Linked with Reconciliation Management & Commission | H79: 45869 | I79: 46239
A80: FRAMEWORK: Services - Larger Modules | B80: Rule Definition Management | C80: 23-May: Integrate the 3'rd party libraries | D80: Framework | E80: Milestone 4 | F80: Not in scope | G80: 23-Jul-2026: As per Gopal as this system custom and most of the data is driven from Master creating/plug any 3'rd Party will make complex. | H80: 45818 | K80: IIRM-765
A81: IBP: Services - Larger Modules | B81: IBP - User Management | C81: IBP: HR Portal - Company-Scoped Employee Access for Client HR (Ex. TeamLease's Customer) | D81: IBP | E81: Milestone 4 | F81: Delivered | H81: 45818 | I81: 46168 | K81: IIRM-10375
A82: IBP: Services - Larger Modules | B82: IBP - Portal Setup | C82: Post policy creation, create default IBP Portal Config for all the company-policy(ies) | D82: IBP | E82: Milestone 4 | F82: Delivered | H82: 45818 | I82: 46192 | J82: Manjusha | K82: IIRM-794
A83: IBP: SERVICES - Basic Modules | B83: Personal Profile Mgmt | C83: Profile settings | D83: IBP | E83: Milestone 4 | F83: Delivered | G83: Pending:Add Dependents | H83: 45818 | I83: 46183 | J83: Manjusha
A84: IBP: FRONTEND | B84: HR Portal View | C84: Employee Search, Resend Email, Delete Employees, Extend Enrollment Windows, Reports, Bulk Email | D84: IBP | E84: Milestone 4 | F84: Delivered | H84: 45818 | I84: 46184 | J84: Abhilash | K84: IIRM-776
A85: IBP: Common Components | B85: Simple Auth | C85: Username and Password based authentication and RBAC on simple-auth users. Auth rules needs configuration capability. IBP - HR User Management | D85: IBP | E85: Milestone 4 | F85: Delivered | H85: 45818 | I85: 46185 | J85: Abhilash
A86: IBP: FRONTEND | B86: My Documents | C86: Document Hub - Covers Policies, Prescriptions, Reports | D86: IBP | E86: Milestone 4 | F86: Delivered | G86: Pending: Design | H86: 45818 | I86: 46185 | J86: Manjusha
A87: IBP: SERVICES - Basic Modules | B87: Document Mgmt for End User | C87: Insurance, Health Reports and Prescriptions {No automatic pull from Partners} | D87: IBP | E87: Milestone 4 | F87: Delivered | G87: Pending: Design | H87: 45818 | I87: 46185 | J87: Manjusha
A88: Framework: NFR | B88: NFR_Usability | C88: NFR-USA-018: The session management should be configurable from UI 23-May: Configure from UI & store in DB; When changed then restart server | D88: IBP | E88: Milestone 4 | F88: Delivered | H88: 45818 | I88: 46188 | J88: Manjusha | K88: IIRM-9912
A89: IBP: FRONTEND | B89: Policy Document | C89: IBP-Risk Watch: Show the each policy document | D89: IBP | E89: Milestone 4 | F89: Delivered | H89: 45818 | I89: 46192 | J89: Tharun
A90: Framework: NFR | B90: NFR_Usability | C90: NFR-USA-015: The system must show personalized welcome messages and profile information based on locale. | D90: IBP | E90: Milestone 4 | F90: Delivered | H90: 45818 | K90: IIRM-4477
A91: Framework: NFR | B91: NFR_Usability | C91: NFR-USA-016: Notification banners must be dismissible and configurable based on role. | D91: IBP | E91: Milestone 4 | F91: Delivered | G91: No notifications in IBP | H91: 45818 | K91: IIRM-4478
A92: IBP: Common Components | B92: Whitelabelling Support | D92: IBP | E92: Milestone 4 | F92: Delivered | H92: 45818 | K92: IIRM-775
A93: IBP: FRONTEND | B93: Company Plans | C93: 6 Policies - GMC, GPA, GTL, Parental Plicy, Top-ups, OPD Policy (Summary view of policies) | D93: IBP | E93: Milestone 4 | F93: Delivered | H93: 45818 | K93: IIRM-774
A94: IBP: FRONTEND | B94: IBP Landing Page - Basic | C94: Basic Landing Page with only company plans and summart | D94: IBP | E94: Milestone 4 | F94: Delivered | H94: 45818 | K94: IIRM-771
A95: IBP: FRONTEND | B95: Contact Matrix View | C95: Contact Matrix View for end user | D95: IBP | E95: Milestone 4 | F95: Delivered | H95: 45818 | K95: IIRM-8036
A96: IBP: FRONTEND | B96: Core Infrastructure | C96: Core Infra | D96: IBP | E96: Milestone 4 | F96: Delivered | H96: 45818
A97: IBP: FRONTEND | B97: Per-policy Enrolment | C97: Enrolment and addon policy selection | D97: IBP | E97: Milestone 4 | F97: Delivered | H97: 45818
A98: IBP: FRONTEND | B98: My Insurance | C98: Part-1: Hub of all plans I have as an employee - Company provided. Mostly a navigational page | D98: IBP | E98: Milestone 4 | F98: Delivered | H98: 45818
A99: IBP: Services - Basic Modules | B99: Basic Landing Page Services | C99: Company provided plans only | D99: IBP | E99: Milestone 4 | F99: Delivered | H99: 45818
A100: IBP: Services - Larger Modules | B100: Group Policy Mgmt - Enrollment | C100: Enrollment (Adding Dependents, Choosing Options available). Submit the enrollment to Insurer or TPA 6 Types of Policies to be considered | D100: IBP | E100: Milestone 4 | F100: Delivered | G100: Need Confirmation: If scope has, Insurer & TPA integrations, then they are pending | H100: 45818 | K100: IIRM-773
...

Sheet ① Executive Summary
A1: PROJECT DELIVERY PLAN
A4: iWork · IBP · Framework (IIRM SOW) | Status Overview & Forward Roadmap · As of 31-Jul-2026
A6: OVERALL COMPLETION | H6: REMAINING WORK
A7: =ROUND(COUNTIF(Helper!$E:$E,"Delivered")/(COUNTIF(Helper!$E:$E,"Delivered")+COUNTIF(Helper!$E:$E,"Pending")),3) -> 0.782 | D7: =COUNTIF(Helper!$E:$E,"Delivered")&" of "&(COUNTIF(Helper!$E:$E,"Delivered")+COUNTIF(Helper!$E:$E,"Pending"))&" scope items delivered" -> 277 of 354 scope items delivered | H7: =COUNTIF(Helper!$E:$E,"Pending") -> 77 | J7: items still to deliver across all modules — planned week by week in the weekly sheets
A11: SOW SCOPE — ORIGINAL vs CURRENT ITEMS
A12: Static comparison vs the 'SOW - Actual Items' reference sheet (original contracted scope). Matched by Module + Feature name. Recomputed on each re-run of the script.
A14: Original SOW items | G14: 158
A15: Currently tracked (all items) | G15: 354
A16: — new: DPDP / NFR / Change Requests | G16: 77
A17: — new: organic growth (existing modules) | G17: 127
A18: Net growth vs original SOW (158 → 354) | G18: +196
A19: ⚠ 2 original SOW item(s) still need review — no matching row in the tracker and no mapping note yet.
A20: 🔗 15 item(s) already mapped by hand to a renamed/restructured tracker row — see notes in 'SOW - Actual Items'.
A23: WEEKLY INTAKE — items requested (by Requested Date)
A24: Period | B24: Added | C24: Delivered | D24: Pending | E24: % Closed
A25: Before 01-Jun-2026 | B25: =COUNTIFS(Helper!$F:$F,"<"&DATE(2026,6,1)) -> 209 | C25: =COUNTIFS(Helper!$F:$F,"<"&DATE(2026,6,1),Helper!$E:$E,"Delivered") -> 158 | D25: =COUNTIFS(Helper!$F:$F,"<"&DATE(2026,6,1),Helper!$E:$E,"Pending") -> 51 | E25: =IFERROR(C25/B25,0) -> 0.75598086
A26: Week of 01 Jun 2026 | B26: =COUNTIFS(Helper!$F:$F,">="&DATE(2026,6,1),Helper!$F:$F,"<="&DATE(2026,6,7)) -> 5 | C26: =COUNTIFS(Helper!$F:$F,">="&DATE(2026,6,1),Helper!$F:$F,"<="&DATE(2026,6,7),Helper!$E:$E,"Delivered") -> 4 | D26: =COUNTIFS(Helper!$F:$F,">="&DATE(2026,6,1),Helper!$F:$F,"<="&DATE(2026,6,7),Helper!$E:$E,"Pending") -> 1 | E26: =IFERROR(C26/B26,0) -> 0.8
A27: Week of 08 Jun 2026 | B27: =COUNTIFS(Helper!$F:$F,">="&DATE(2026,6,8),Helper!$F:$F,"<="&DATE(2026,6,14)) -> 43 | C27: =COUNTIFS(Helper!$F:$F,">="&DATE(2026,6,8),Helper!$F:$F,"<="&DATE(2026,6,14),Helper!$E:$E,"Delivered") -> 42 | D27: =COUNTIFS(Helper!$F:$F,">="&DATE(2026,6,8),Helper!$F:$F,"<="&DATE(2026,6,14),Helper!$E:$E,"Pending") -> 1 | E27: =IFERROR(C27/B27,0) -> 0.97674419
A28: Week of 15 Jun 2026 | B28: =COUNTIFS(Helper!$F:$F,">="&DATE(2026,6,15),Helper!$F:$F,"<="&DATE(2026,6,21)) -> 12 | C28: =COUNTIFS(Helper!$F:$F,">="&DATE(2026,6,15),Helper!$F:$F,"<="&DATE(2026,6,21),Helper!$E:$E,"Delivered") -> 5 | D28: =COUNTIFS(Helper!$F:$F,">="&DATE(2026,6,15),Helper!$F:$F,"<="&DATE(2026,6,21),Helper!$E:$E,"Pending") -> 7 | E28: =IFERROR(C28/B28,0) -> 0.41666667
A29: Week of 22 Jun 2026 | B29: =COUNTIFS(Helper!$F:$F,">="&DATE(2026,6,22),Helper!$F:$F,"<="&DATE(2026,6,28)) -> 21 | C29: =COUNTIFS(Helper!$F:$F,">="&DATE(2026,6,22),Helper!$F:$F,"<="&DATE(2026,6,28),Helper!$E:$E,"Delivered") -> 15 | D29: =COUNTIFS(Helper!$F:$F,">="&DATE(2026,6,22),Helper!$F:$F,"<="&DATE(2026,6,28),Helper!$E:$E,"Pending") -> 6 | E29: =IFERROR(C29/B29,0) -> 0.71428571
A30: Week of 29 Jun 2026 | B30: =COUNTIFS(Helper!$F:$F,">="&DATE(2026,6,29),Helper!$F:$F,"<="&DATE(2026,7,5)) -> 5 | C30: =COUNTIFS(Helper!$F:$F,">="&DATE(2026,6,29),Helper!$F:$F,"<="&DATE(2026,7,5),Helper!$E:$E,"Delivered") -> 2 | D30: =COUNTIFS(Helper!$F:$F,">="&DATE(2026,6,29),Helper!$F:$F,"<="&DATE(2026,7,5),Helper!$E:$E,"Pending") -> 3 | E30: =IFERROR(C30/B30,0) -> 0.4
A31: Week of 06 Jul 2026 | B31: =COUNTIFS(Helper!$F:$F,">="&DATE(2026,7,6),Helper!$F:$F,"<="&DATE(2026,7,12)) -> 8 | C31: =COUNTIFS(Helper!$F:$F,">="&DATE(2026,7,6),Helper!$F:$F,"<="&DATE(2026,7,12),Helper!$E:$E,"Delivered") -> 7 | D31: =COUNTIFS(Helper!$F:$F,">="&DATE(2026,7,6),Helper!$F:$F,"<="&DATE(2026,7,12),Helper!$E:$E,"Pending") -> 1 | E31: =IFERROR(C31/B31,0) -> 0.875
A32: Week of 13 Jul 2026 | B32: =COUNTIFS(Helper!$F:$F,">="&DATE(2026,7,13),Helper!$F:$F,"<="&DATE(2026,7,19)) -> 21 | C32: =COUNTIFS(Helper!$F:$F,">="&DATE(2026,7,13),Helper!$F:$F,"<="&DATE(2026,7,19),Helper!$E:$E,"Delivered") -> 19 | D32: =COUNTIFS(Helper!$F:$F,">="&DATE(2026,7,13),Helper!$F:$F,"<="&DATE(2026,7,19),Helper!$E:$E,"Pending") -> 2 | E32: =IFERROR(C32/B32,0) -> 0.9047619
A33: Week of 20 Jul 2026 — last week | B33: =COUNTIFS(Helper!$F:$F,">="&DATE(2026,7,20),Helper!$F:$F,"<="&DATE(2026,7,26)) -> 20 | C33: =COUNTIFS(Helper!$F:$F,">="&DATE(2026,7,20),Helper!$F:$F,"<="&DATE(2026,7,26),Helper!$E:$E,"Delivered") -> 17 | D33: =COUNTIFS(Helper!$F:$F,">="&DATE(2026,7,20),Helper!$F:$F,"<="&DATE(2026,7,26),Helper!$E:$E,"Pending") -> 3 | E33: =IFERROR(C33/B33,0) -> 0.85
A34: Week of 27 Jul 2026 — this week | B34: =COUNTIFS(Helper!$F:$F,">="&DATE(2026,7,27),Helper!$F:$F,"<="&DATE(2026,8,2)) -> 10 | C34: =COUNTIFS(Helper!$F:$F,">="&DATE(2026,7,27),Helper!$F:$F,"<="&DATE(2026,8,2),Helper!$E:$E,"Delivered") -> 8 | D34: =COUNTIFS(Helper!$F:$F,">="&DATE(2026,7,27),Helper!$F:$F,"<="&DATE(2026,8,2),Helper!$E:$E,"Pending") -> 2 | E34: =IFERROR(C34/B34,0) -> 0.8
A35: Requested ahead (after 02 Aug) | B35: =COUNTIFS(Helper!$F:$F,">"&DATE(2026,8,2)) -> 0 | C35: =COUNTIFS(Helper!$F:$F,">"&DATE(2026,8,2),Helper!$E:$E,"Delivered") -> 0 | D35: =COUNTIFS(Helper!$F:$F,">"&DATE(2026,8,2),Helper!$E:$E,"Pending") -> 0 | E35: =IFERROR(C35/B35,0) -> 0
A36: No Requested Date | B36: =COUNTA(Helper!$C$2:$C$5000)-COUNT(Helper!$F$2:$F$5000) -> 0 | C36: =COUNTIFS(Helper!$F:$F,"",Helper!$E:$E,"Delivered") -> 0 | D36: =COUNTIFS(Helper!$F:$F,"",Helper!$E:$E,"Pending") -> 0 | E36: =IFERROR(C36/B36,0) -> 0
A37: TOTAL | B37: =SUM(B25:B36) -> 354 | C37: =SUM(C25:C36) -> 277 | D37: =SUM(D25:D36) -> 77 | E37: =IFERROR(C37/B37,0) -> 0.78248588
A39: STATUS BREAKDOWN (all items)
A40: =COUNTIF(Helper!$D:$D,"Delivered") -> 276 | D40: =COUNTIF(Helper!$D:$D,"Dev Complete") -> 1 | G40: =COUNTIF(Helper!$D:$D,"In Development") -> 13 | J40: =COUNTIF(Helper!$D:$D,"In QA") -> 1
A41: Delivered | D41: Dev Complete | G41: In Development | J41: In QA
A42: =COUNTIF(Helper!$D:$D,"Pre-PROD / UAT") -> 18 | D42: =COUNTIF(Helper!$D:$D,"Not Started") -> 42 | G42: =COUNTIF(Helper!$D:$D,"Partial Delivery") -> 3 | J42: =COUNTIF(Helper!$D:$D,"N/A") -> 0
A43: Pre-PROD / UAT | D43: Not Started | G43: Partial Delivery | J43: N/A
A45: PROGRESS BY MODULE
A46: Module | B46: Type | C46: Total | D46: Delivered | E46: Pending | F46: N/A | G46: % Complete | H46: Progress
A47: iWork (Backlog) | B47: Backlog | C47: =COUNTIF(Helper!$A:$A,"iWork") -> 148 | D47: =COUNTIFS(Helper!$A:$A,"iWork",Helper!$E:$E,"Delivered") -> 133 | E47: =COUNTIFS(Helper!$A:$A,"iWork",Helper!$E:$E,"Pending") -> 15 | F47: =COUNTIFS(Helper!$A:$A,"iWork",Helper!$E:$E,"N/A") -> 0 | G47: =IFERROR(D47/(D47+E47),0) -> 0.89864865 | H47: =G47 -> 0.89864865
A48: iWork (Change Requests) | B48: Change Request | C48: =COUNTIF(Helper!$A:$A,"iWork - CR") -> 42 | D48: =COUNTIFS(Helper!$A:$A,"iWork - CR",Helper!$E:$E,"Delivered") -> 35 | E48: =COUNTIFS(Helper!$A:$A,"iWork - CR",Helper!$E:$E,"Pending") -> 7 | F48: =COUNTIFS(Helper!$A:$A,"iWork - CR",Helper!$E:$E,"N/A") -> 0 | G48: =IFERROR(D48/(D48+E48),0) -> 0.83333333 | H48: =G48 -> 0.83333333
A49: IBP (Backlog) | B49: Backlog | C49: =COUNTIF(Helper!$A:$A,"IBP") -> 69 | D49: =COUNTIFS(Helper!$A:$A,"IBP",Helper!$E:$E,"Delivered") -> 49 | E49: =COUNTIFS(Helper!$A:$A,"IBP",Helper!$E:$E,"Pending") -> 20 | F49: =COUNTIFS(Helper!$A:$A,"IBP",Helper!$E:$E,"N/A") -> 0 | G49: =IFERROR(D49/(D49+E49),0) -> 0.71014493 | H49: =G49 -> 0.71014493
A50: IBP (Change Requests) | B50: Change Request | C50: =COUNTIF(Helper!$A:$A,"IBP - CR") -> 3 | D50: =COUNTIFS(Helper!$A:$A,"IBP - CR",Helper!$E:$E,"Delivered") -> 2 | E50: =COUNTIFS(Helper!$A:$A,"IBP - CR",Helper!$E:$E,"Pending") -> 1 | F50: =COUNTIFS(Helper!$A:$A,"IBP - CR",Helper!$E:$E,"N/A") -> 0 | G50: =IFERROR(D50/(D50+E50),0) -> 0.66666667 | H50: =G50 -> 0.66666667
A51: IBP / iWork (Shared) | B51: Backlog | C51: =COUNTIF(Helper!$A:$A,"IBP/iWork") -> 26 | D51: =COUNTIFS(Helper!$A:$A,"IBP/iWork",Helper!$E:$E,"Delivered") -> 16 | E51: =COUNTIFS(Helper!$A:$A,"IBP/iWork",Helper!$E:$E,"Pending") -> 10 | F51: =COUNTIFS(Helper!$A:$A,"IBP/iWork",Helper!$E:$E,"N/A") -> 0 | G51: =IFERROR(D51/(D51+E51),0) -> 0.61538462 | H51: =G51 -> 0.61538462
A52: IBP / iWork (Shared CRs) | B52: Change Request | C52: =COUNTIF(Helper!$A:$A,"IBP/iWork - CR") -> 9 | D52: =COUNTIFS(Helper!$A:$A,"IBP/iWork - CR",Helper!$E:$E,"Delivered") -> 3 | E52: =COUNTIFS(Helper!$A:$A,"IBP/iWork - CR",Helper!$E:$E,"Pending") -> 6 | F52: =COUNTIFS(Helper!$A:$A,"IBP/iWork - CR",Helper!$E:$E,"N/A") -> 0 | G52: =IFERROR(D52/(D52+E52),0) -> 0.33333333 | H52: =G52 -> 0.33333333
A53: Framework | B53: Backlog | C53: =COUNTIF(Helper!$A:$A,"Framework") -> 34 | D53: =COUNTIFS(Helper!$A:$A,"Framework",Helper!$E:$E,"Delivered") -> 31 | E53: =COUNTIFS(Helper!$A:$A,"Framework",Helper!$E:$E,"Pending") -> 3 | F53: =COUNTIFS(Helper!$A:$A,"Framework",Helper!$E:$E,"N/A") -> 0 | G53: =IFERROR(D53/(D53+E53),0) -> 0.91176471 | H53: =G53 -> 0.91176471
A54: DPDP | B54: Backlog | C54: =COUNTIF(Helper!$A:$A,"DPDP") -> 19 | D54: =COUNTIFS(Helper!$A:$A,"DPDP",Helper!$E:$E,"Delivered") -> 7 | E54: =COUNTIFS(Helper!$A:$A,"DPDP",Helper!$E:$E,"Pending") -> 12 | F54: =COUNTIFS(Helper!$A:$A,"DPDP",Helper!$E:$E,"N/A") -> 0 | G54: =IFERROR(D54/(D54+E54),0) -> 0.36842105 | H54: =G54 -> 0.36842105
A55: NFR | B55: Backlog | C55: =COUNTIF(Helper!$A:$A,"NFR") -> 4 | D55: =COUNTIFS(Helper!$A:$A,"NFR",Helper!$E:$E,"Delivered") -> 1 | E55: =COUNTIFS(Helper!$A:$A,"NFR",Helper!$E:$E,"Pending") -> 3 | F55: =COUNTIFS(Helper!$A:$A,"NFR",Helper!$E:$E,"N/A") -> 0 | G55: =IFERROR(D55/(D55+E55),0) -> 0.25 | H55: =G55 -> 0.25
A56: TOTAL | B56: All | C56: =COUNTA(Helper!$A$2:$A$5000) -> 354 | D56: =COUNTIF(Helper!$E:$E,"Delivered") -> 277 | E56: =COUNTIF(Helper!$E:$E,"Pending") -> 77 | F56: =COUNTIF(Helper!$E:$E,"N/A") -> 0 | G56: =IFERROR(D56/(D56+E56),0) -> 0.78248588 | H56: =G56 -> 0.78248588
A58: PENDING BY MILESTONE & MODULE
A59: Milestone | B59: iWork | C59: iWork - CR | D59: IBP | E59: IBP - CR | F59: IBP/iWork | G59: IBP/iWork - CR | H59: Framework | I59: DPDP | J59: NFR | K59: TOTAL PENDING
A60: Milestone 1 | B60: =COUNTIFS(Helper!$B:$B,"Milestone 1",Helper!$A:$A,"iWork",Helper!$E:$E,"Pending") -> 0 | C60: =COUNTIFS(Helper!$B:$B,"Milestone 1",Helper!$A:$A,"iWork - CR",Helper!$E:$E,"Pending") -> 0 | D60: =COUNTIFS(Helper!$B:$B,"Milestone 1",Helper!$A:$A,"IBP",Helper!$E:$E,"Pending") -> 0 | E60: =COUNTIFS(Helper!$B:$B,"Milestone 1",Helper!$A:$A,"IBP - CR",Helper!$E:$E,"Pending") -> 0 | F60: =COUNTIFS(Helper!$B:$B,"Milestone 1",Helper!$A:$A,"IBP/iWork",Helper!$E:$E,"Pending") -> 0 | G60: =COUNTIFS(Helper!$B:$B,"Milestone 1",Helper!$A:$A,"IBP/iWork - CR",Helper!$E:$E,"Pending") -> 0 | H60: =COUNTIFS(Helper!$B:$B,"Milestone 1",Helper!$A:$A,"Framework",Helper!$E:$E,"Pending") -> 0 | I60: =COUNTIFS(Helper!$B:$B,"Milestone 1",Helper!$A:$A,"DPDP",Helper!$E:$E,"Pending") -> 0 | J60: =COUNTIFS(Helper!$B:$B,"Milestone 1",Helper!$A:$A,"NFR",Helper!$E:$E,"Pending") -> 0 | K60: =SUM(B60:J60) -> 0
A61: Milestone 2 | B61: =COUNTIFS(Helper!$B:$B,"Milestone 2",Helper!$A:$A,"iWork",Helper!$E:$E,"Pending") -> 1 | C61: =COUNTIFS(Helper!$B:$B,"Milestone 2",Helper!$A:$A,"iWork - CR",Helper!$E:$E,"Pending") -> 0 | D61: =COUNTIFS(Helper!$B:$B,"Milestone 2",Helper!$A:$A,"IBP",Helper!$E:$E,"Pending") -> 0 | E61: =COUNTIFS(Helper!$B:$B,"Milestone 2",Helper!$A:$A,"IBP - CR",Helper!$E:$E,"Pending") -> 0 | F61: =COUNTIFS(Helper!$B:$B,"Milestone 2",Helper!$A:$A,"IBP/iWork",Helper!$E:$E,"Pending") -> 0 | G61: =COUNTIFS(Helper!$B:$B,"Milestone 2",Helper!$A:$A,"IBP/iWork - CR",Helper!$E:$E,"Pending") -> 0 | H61: =COUNTIFS(Helper!$B:$B,"Milestone 2",Helper!$A:$A,"Framework",Helper!$E:$E,"Pending") -> 0 | I61: =COUNTIFS(Helper!$B:$B,"Milestone 2",Helper!$A:$A,"DPDP",Helper!$E:$E,"Pending") -> 0 | J61: =COUNTIFS(Helper!$B:$B,"Milestone 2",Helper!$A:$A,"NFR",Helper!$E:$E,"Pending") -> 0 | K61: =SUM(B61:J61) -> 1
A62: Milestone 3 | B62: =COUNTIFS(Helper!$B:$B,"Milestone 3",Helper!$A:$A,"iWork",Helper!$E:$E,"Pending") -> 0 | C62: =COUNTIFS(Helper!$B:$B,"Milestone 3",Helper!$A:$A,"iWork - CR",Helper!$E:$E,"Pending") -> 0 | D62: =COUNTIFS(Helper!$B:$B,"Milestone 3",Helper!$A:$A,"IBP",Helper!$E:$E,"Pending") -> 0 | E62: =COUNTIFS(Helper!$B:$B,"Milestone 3",Helper!$A:$A,"IBP - CR",Helper!$E:$E,"Pending") -> 0 | F62: =COUNTIFS(Helper!$B:$B,"Milestone 3",Helper!$A:$A,"IBP/iWork",Helper!$E:$E,"Pending") -> 0 | G62: =COUNTIFS(Helper!$B:$B,"Milestone 3",Helper!$A:$A,"IBP/iWork - CR",Helper!$E:$E,"Pending") -> 0 | H62: =COUNTIFS(Helper!$B:$B,"Milestone 3",Helper!$A:$A,"Framework",Helper!$E:$E,"Pending") -> 0 | I62: =COUNTIFS(Helper!$B:$B,"Milestone 3",Helper!$A:$A,"DPDP",Helper!$E:$E,"Pending") -> 0 | J62: =COUNTIFS(Helper!$B:$B,"Milestone 3",Helper!$A:$A,"NFR",Helper!$E:$E,"Pending") -> 0 | K62: =SUM(B62:J62) -> 0
A63: Milestone 4 | B63: =COUNTIFS(Helper!$B:$B,"Milestone 4",Helper!$A:$A,"iWork",Helper!$E:$E,"Pending") -> 1 | C63: =COUNTIFS(Helper!$B:$B,"Milestone 4",Helper!$A:$A,"iWork - CR",Helper!$E:$E,"Pending") -> 0 | D63: =COUNTIFS(Helper!$B:$B,"Milestone 4",Helper!$A:$A,"IBP",Helper!$E:$E,"Pending") -> 1 | E63: =COUNTIFS(Helper!$B:$B,"Milestone 4",Helper!$A:$A,"IBP - CR",Helper!$E:$E,"Pending") -> 0 | F63: =COUNTIFS(Helper!$B:$B,"Milestone 4",Helper!$A:$A,"IBP/iWork",Helper!$E:$E,"Pending") -> 3 | G63: =COUNTIFS(Helper!$B:$B,"Milestone 4",Helper!$A:$A,"IBP/iWork - CR",Helper!$E:$E,"Pending") -> 0 | H63: =COUNTIFS(Helper!$B:$B,"Milestone 4",Helper!$A:$A,"Framework",Helper!$E:$E,"Pending") -> 3 | I63: =COUNTIFS(Helper!$B:$B,"Milestone 4",Helper!$A:$A,"DPDP",Helper!$E:$E,"Pending") -> 1 | J63: =COUNTIFS(Helper!$B:$B,"Milestone 4",Helper!$A:$A,"NFR",Helper!$E:$E,"Pending") -> 1 | K63: =SUM(B63:J63) -> 10
A64: Milestone 5 | B64: =COUNTIFS(Helper!$B:$B,"Milestone 5",Helper!$A:$A,"iWork",Helper!$E:$E,"Pending") -> 4 | C64: =COUNTIFS(Helper!$B:$B,"Milestone 5",Helper!$A:$A,"iWork - CR",Helper!$E:$E,"Pending") -> 0 | D64: =COUNTIFS(Helper!$B:$B,"Milestone 5",Helper!$A:$A,"IBP",Helper!$E:$E,"Pending") -> 16 | E64: =COUNTIFS(Helper!$B:$B,"Milestone 5",Helper!$A:$A,"IBP - CR",Helper!$E:$E,"Pending") -> 0 | F64: =COUNTIFS(Helper!$B:$B,"Milestone 5",Helper!$A:$A,"IBP/iWork",Helper!$E:$E,"Pending") -> 3 | G64: =COUNTIFS(Helper!$B:$B,"Milestone 5",Helper!$A:$A,"IBP/iWork - CR",Helper!$E:$E,"Pending") -> 0 | H64: =COUNTIFS(Helper!$B:$B,"Milestone 5",Helper!$A:$A,"Framework",Helper!$E:$E,"Pending") -> 0 | I64: =COUNTIFS(Helper!$B:$B,"Milestone 5",Helper!$A:$A,"DPDP",Helper!$E:$E,"Pending") -> 11 | J64: =COUNTIFS(Helper!$B:$B,"Milestone 5",Helper!$A:$A,"NFR",Helper!$E:$E,"Pending") -> 2 | K64: =SUM(B64:J64) -> 36
A65: Milestone 6 | B65: =COUNTIFS(Helper!$B:$B,"Milestone 6",Helper!$A:$A,"iWork",Helper!$E:$E,"Pending") -> 9 | C65: =COUNTIFS(Helper!$B:$B,"Milestone 6",Helper!$A:$A,"iWork - CR",Helper!$E:$E,"Pending") -> 7 | D65: =COUNTIFS(Helper!$B:$B,"Milestone 6",Helper!$A:$A,"IBP",Helper!$E:$E,"Pending") -> 3 | E65: =COUNTIFS(Helper!$B:$B,"Milestone 6",Helper!$A:$A,"IBP - CR",Helper!$E:$E,"Pending") -> 1 | F65: =COUNTIFS(Helper!$B:$B,"Milestone 6",Helper!$A:$A,"IBP/iWork",Helper!$E:$E,"Pending") -> 4 | G65: =COUNTIFS(Helper!$B:$B,"Milestone 6",Helper!$A:$A,"IBP/iWork - CR",Helper!$E:$E,"Pending") -> 6 | H65: =COUNTIFS(Helper!$B:$B,"Milestone 6",Helper!$A:$A,"Framework",Helper!$E:$E,"Pending") -> 0 | I65: =COUNTIFS(Helper!$B:$B,"Milestone 6",Helper!$A:$A,"DPDP",Helper!$E:$E,"Pending") -> 0 | J65: =COUNTIFS(Helper!$B:$B,"Milestone 6",Helper!$A:$A,"NFR",Helper!$E:$E,"Pending") -> 0 | K65: =SUM(B65:J65) -> 30
A66: TOTAL | B66: =SUM(B60:B65) -> 15 | C66: =SUM(C60:C65) -> 7 | D66: =SUM(D60:D65) -> 20 | E66: =SUM(E60:E65) -> 1 | F66: =SUM(F60:F65) -> 10 | G66: =SUM(G60:G65) -> 6 | H66: =SUM(H60:H65) -> 3 | I66: =SUM(I60:I65) -> 12 | ... K66: =SUM(K60:K65) -> 77
A68: ITEMS BY MILESTONE & STATUS
A69: Milestone | B69: Delivered | C69: Dev Complete | D69: In Development | E69: In QA | F69: Pre-PROD / UAT | G69: Not Started | H69: Partial Delivery | I69: TOTAL
A70: Milestone 1 | B70: =COUNTIFS(Helper!$B:$B,"Milestone 1",Helper!$D:$D,"Delivered") -> 29 | C70: =COUNTIFS(Helper!$B:$B,"Milestone 1",Helper!$D:$D,"Dev Complete") -> 0 | D70: =COUNTIFS(Helper!$B:$B,"Milestone 1",Helper!$D:$D,"In Development") -> 0 | E70: =COUNTIFS(Helper!$B:$B,"Milestone 1",Helper!$D:$D,"In QA") -> 0 | F70: =COUNTIFS(Helper!$B:$B,"Milestone 1",Helper!$D:$D,"Pre-PROD / UAT") -> 0 | G70: =COUNTIFS(Helper!$B:$B,"Milestone 1",Helper!$D:$D,"Not Started") -> 0 | H70: =COUNTIFS(Helper!$B:$B,"Milestone 1",Helper!$D:$D,"Partial Delivery") -> 0 | I70: =SUM(B70:H70) -> 29
A71: Milestone 2 | B71: =COUNTIFS(Helper!$B:$B,"Milestone 2",Helper!$D:$D,"Delivered") -> 31 | C71: =COUNTIFS(Helper!$B:$B,"Milestone 2",Helper!$D:$D,"Dev Complete") -> 0 | D71: =COUNTIFS(Helper!$B:$B,"Milestone 2",Helper!$D:$D,"In Development") -> 0 | E71: =COUNTIFS(Helper!$B:$B,"Milestone 2",Helper!$D:$D,"In QA") -> 0 | F71: =COUNTIFS(Helper!$B:$B,"Milestone 2",Helper!$D:$D,"Pre-PROD / UAT") -> 1 | G71: =COUNTIFS(Helper!$B:$B,"Milestone 2",Helper!$D:$D,"Not Started") -> 0 | H71: =COUNTIFS(Helper!$B:$B,"Milestone 2",Helper!$D:$D,"Partial Delivery") -> 0 | I71: =SUM(B71:H71) -> 32
A72: Milestone 3 | B72: =COUNTIFS(Helper!$B:$B,"Milestone 3",Helper!$D:$D,"Delivered") -> 8 | C72: =COUNTIFS(Helper!$B:$B,"Milestone 3",Helper!$D:$D,"Dev Complete") -> 0 | D72: =COUNTIFS(Helper!$B:$B,"Milestone 3",Helper!$D:$D,"In Development") -> 0 | E72: =COUNTIFS(Helper!$B:$B,"Milestone 3",Helper!$D:$D,"In QA") -> 0 | F72: =COUNTIFS(Helper!$B:$B,"Milestone 3",Helper!$D:$D,"Pre-PROD / UAT") -> 0 | G72: =COUNTIFS(Helper!$B:$B,"Milestone 3",Helper!$D:$D,"Not Started") -> 0 | H72: =COUNTIFS(Helper!$B:$B,"Milestone 3",Helper!$D:$D,"Partial Delivery") -> 0 | I72: =SUM(B72:H72) -> 8
A73: Milestone 4 | B73: =COUNTIFS(Helper!$B:$B,"Milestone 4",Helper!$D:$D,"Delivered") -> 47 | C73: =COUNTIFS(Helper!$B:$B,"Milestone 4",Helper!$D:$D,"Dev Complete") -> 0 | D73: =COUNTIFS(Helper!$B:$B,"Milestone 4",Helper!$D:$D,"In Development") -> 0 | E73: =COUNTIFS(Helper!$B:$B,"Milestone 4",Helper!$D:$D,"In QA") -> 0 | F73: =COUNTIFS(Helper!$B:$B,"Milestone 4",Helper!$D:$D,"Pre-PROD / UAT") -> 4 | G73: =COUNTIFS(Helper!$B:$B,"Milestone 4",Helper!$D:$D,"Not Started") -> 4 | H73: =COUNTIFS(Helper!$B:$B,"Milestone 4",Helper!$D:$D,"Partial Delivery") -> 2 | I73: =SUM(B73:H73) -> 57
A74: Milestone 5 | B74: =COUNTIFS(Helper!$B:$B,"Milestone 5",Helper!$D:$D,"Delivered") -> 31 | C74: =COUNTIFS(Helper!$B:$B,"Milestone 5",Helper!$D:$D,"Dev Complete") -> 1 | D74: =COUNTIFS(Helper!$B:$B,"Milestone 5",Helper!$D:$D,"In Development") -> 8 | E74: =COUNTIFS(Helper!$B:$B,"Milestone 5",Helper!$D:$D,"In QA") -> 1 | F74: =COUNTIFS(Helper!$B:$B,"Milestone 5",Helper!$D:$D,"Pre-PROD / UAT") -> 8 | G74: =COUNTIFS(Helper!$B:$B,"Milestone 5",Helper!$D:$D,"Not Started") -> 18 | H74: =COUNTIFS(Helper!$B:$B,"Milestone 5",Helper!$D:$D,"Partial Delivery") -> 1 | I74: =SUM(B74:H74) -> 68
A75: Milestone 6 | B75: =COUNTIFS(Helper!$B:$B,"Milestone 6",Helper!$D:$D,"Delivered") -> 130 | C75: =COUNTIFS(Helper!$B:$B,"Milestone 6",Helper!$D:$D,"Dev Complete") -> 0 | D75: =COUNTIFS(Helper!$B:$B,"Milestone 6",Helper!$D:$D,"In Development") -> 5 | E75: =COUNTIFS(Helper!$B:$B,"Milestone 6",Helper!$D:$D,"In QA") -> 0 | F75: =COUNTIFS(Helper!$B:$B,"Milestone 6",Helper!$D:$D,"Pre-PROD / UAT") -> 5 | G75: =COUNTIFS(Helper!$B:$B,"Milestone 6",Helper!$D:$D,"Not Started") -> 20 | H75: =COUNTIFS(Helper!$B:$B,"Milestone 6",Helper!$D:$D,"Partial Delivery") -> 0 | I75: =SUM(B75:H75) -> 160
A76: TOTAL | B76: =SUM(B70:B75) -> 276 | C76: =SUM(C70:C75) -> 1 | D76: =SUM(D70:D75) -> 13 | E76: =SUM(E70:E75) -> 1 | F76: =SUM(F70:F75) -> 18 | G76: =SUM(G70:G75) -> 42 | H76: =SUM(H70:H75) -> 3 | I76: =SUM(I70:I75) -> 354
A78: % Complete = Delivered ÷ (Delivered + Pending). N/A items (duplicates) are excluded from the calculation. All figures update live from the 'SOW, Feedbacks-Bug & CR_Items' sheet.

Sheet 📅 20-Jul
A1: WEEK OF 20 Jul 2026 → 26 Jul 2026 — 20 items · 20 delivered · 0 pending · LAST WEEK
A3: ⚠️ Static snapshot. To update: edit STATUS/ETA in the source sheet, then re-run build_iirm_summary.py
A5: # | B5: Module | C5: Feature | D5: Functionality | E5: Status | F5: Milestone | G5: Requested | H5: ETA | I5: Resource | J5: Remarks
A6: iWork (Backlog & CRs) · 20 items · 20 delivered · 0 pending
A7: 1 | B7: iWork | C7: IBP - Send "Welcome Emails" or any email from IBP to include CC by HR or CRM User | D7: IBP - Send "Welcome Emails" or any email from IBP to include CC by HR or CRM User | E7: Delivered | F7: Milestone 6 | G7: 20-Jul-2026 | H7: 21-Jul-2026 | I7: Ravi
A8: 2 | B8: iWork | C8: BizDone & Dashboard - Data Issue | D8: Delete demo company, Demo company, Dummy company, Nokia Corporation (ref number 22337) | E8: Delivered | F8: Milestone 6 | G8: 20-Jul-2026 | H8: 21-Jul-2026 | I8: Karan | J8: Instead of delete, we maked the status NOT to show in the BizDone & Dashboard
A9: 3 | B9: iWork | C9: BizDone | D9: Update the associate CRM and Lead CRM as per enclosed sheet. This sheet has policy data. As per this, related SO, RO, Company also to be updated. Their are few records without any associate CRM assignment. So leave them blank. -- Refer to Data update.msg & CRM-Update.xlsx | E9: Delivered | F9: Milestone 6 | G9: 20-Jul-2026 | H9: 21-Jul-2026 | I9: Jagadeesh
A10: 4 | B10: iWork | C10: BizDone | D10: Update Net Premium, Brokerage %, Brokerage Amount, & Income Month -- Refer to Data update - Set 2.msg & cl-updated.xlsx | E10: Delivered | F10: Milestone 6 | G10: 20-Jul-2026 | H10: 21-Jul-2026 | I10: Jagadeesh
A11: 5 | B11: iWork | C11: BizDone | D11: Update Lead CRM as Policy Owner for the selected Policies provided by Kapil | E11: Delivered | F11: Milestone 6 | G11: 21-Jul-2026 | H11: 21-Jul-2026 | I11: Jagadeesh
A12: 6 | B12: iWork | C12: BizDone | D12: Update Opty. Owner value to Lead CRM of the Company | E12: Delivered | F12: Milestone 6 | G12: 21-Jul-2026 | H12: 21-Jul-2026 | I12: Jagadeesh
A13: 7 | B13: iWork | C13: MIR Entry Mgmt | D13: Entry Form, Print to Document, List of Earlier MIRs, Search on MIRs | E13: Delivered | F13: Milestone 3 | G13: 16-May-2025 | H13: 22-Jul-2026 | I13: Sunil
A14: 8 | B14: iWork | C14: MIR Entry Mgmt | D14: Module to manage MIR {Monthly Infomatiom Report} | E14: Delivered | F14: Milestone 3 | G14: 16-May-2025 | H14: 22-Jul-2026 | I14: Sunil
A15: 9 | B15: iWork | C15: Surya's feedback | D15: Policy Details - Strip - Remove view more button and company is clickable | E15: Delivered | F15: Milestone 6 | G15: 14-Jul-2026 | H15: 22-Jul-2026 | I15: Pushyami
A16: 10 | B16: iWork | C16: Access Issue | D16: When a user above the hirerchary is accessing the data, application is throwing "unauthorized" message | E16: Delivered | F16: Milestone 6 | G16: 22-Jul-2026 | H16: 22-Jul-2026 | I16: Pushyami
A17: 11 | B17: iWork | C17: Kapil's feedback | D17: Data change requests - Madhav's - Ass. CRM & Others - Refer to Jagadeesh email | E17: Delivered | F17: Milestone 6 | G17: 23-Jul-2026 | H17: 23-Jul-2026 | I17: Jagadeesh
A18: 12 | B18: iWork | D18: Income month prefilling in endorsements | E18: Delivered | F18: Milestone 6 | G18: 23-Jul-2026 | H18: 23-Jul-2026 | I18: Jagadeesh
A19: 13 | B19: iWork | C19: UX issue | D19: Display of complete amounts in KPI cards on hover | E19: Delivered | F19: Milestone 6 | G19: 23-Jul-2026 | H19: 23-Jul-2026 | I19: Pushyami
A20: 14 | B20: iWork | D20: Dashboard and BizDone Brokerage mismatch | E20: Delivered | F20: Milestone 6 | G20: 23-Jul-2026 | H20: 23-Jul-2026 | I20: Jagadeesh
A21: 15 | B21: iWork | C21: Surya's feedback | D21: Removal of + or - 5 days logic in the filters - Revert the logic | E21: Delivered | F21: Milestone 6 | G21: 23-Jul-2026 | H21: 23-Jul-2026 | I21: Karan
A22: 16 | B22: IBP/iWork | C22: TPA Integration Mgmt [Framework] | D22: 1. Framework in iWork 2. Validate the integration for the existing 6 TPA's | E22: Delivered | F22: Milestone 4 | G22: 10-Jun-2025 | H22: 24-Jul-2026 | I22: Ravi
A23: 17 | B23: iWork | C23: Integration UI Component | D23: Integration UI Component (for TPA, HRMS, Insurer) Similar to TPA API Integration Framework for any 3'rd Party | E23: Delivered | F23: Milestone 5 | G23: 31-Jul-2025 | H23: 24-Jul-2026
A24: 18 | B24: iWork | C24: Application Access similar to SysAdmin | D24: Need one more user like SYSADMIN. This user to be below SYSADMIN - and should be 100% read-only user - access etc all like SYSADMIN including Bizdone report download etc Also, inpersonate the user and see the data | E24: Delivered | F24: Milestone 6 | G24: 20-Jul-2026 | H24: 24-Jul-2026 | I24: Pushyami | J24: 1. Kapil sir sent it via Teams Chat. 2. Surya sir mentioned this in Call on Saturday
A25: 19 | B25: iWork | C25: Madhav & Veera | D25: Data Load - Company, Policy, & Insurer - 38 Files | E25: Delivered | F25: Milestone 6 | G25: 20-Jul-2026 | H25: 24-Jul-2026 | I25: Rama
A26: 20 | B26: iWork | C26: Neeraj Joshi | D26: Production Bugs - Via Emails/Tickets - 10 | E26: Delivered | F26: Milestone 6 | G26: 20-Jul-2026 | H26: 24-Jul-2026 | I26: Rama

Sheet 📍 27-Jul
A1: WEEK OF 27 Jul 2026 → 02 Aug 2026 — 11 items · 11 delivered · 0 pending · CURRENT WEEK
A3: ⚠️ Static snapshot. To update: edit STATUS/ETA in the source sheet, then re-run build_iirm_summary.py
A5: # | B5: Module | C5: Feature | D5: Functionality | E5: Status | F5: Milestone | G5: Requested | H5: ETA | I5: Resource | J5: Remarks
A6: iWork (Backlog & CRs) · 9 items · 9 delivered · 0 pending
A7: 1 | B7: iWork | C7: My Client Portfolio | D7: My Client Portfolio: issues - company search and brokerage | E7: Delivered | F7: Milestone 6 | G7: 27-Jul-2026 | H7: 27-Jul-2026 | I7: Pushyami
A8: 2 | B8: iWork | C8: Dashboard | D8: Dashboard issue - ISG planning count mismatch | E8: Delivered | F8: Milestone 6 | G8: 28-Jul-2026 | H8: 28-Jul-2026 | I8: Pushyami
A9: 3 | B9: iWork | C9: Dashboard | D9: Business Performance-breakup - count mismatch | E9: Delivered | F9: Milestone 6 | G9: 28-Jul-2026 | H9: 28-Jul-2026 | I9: Pushyami
A10: 4 | B10: iWork | C10: View Service Score | D10: My Client Portfolio: Service Score - Single Table (drillable) to calculate an overall score Dashboard - Service Score - Widget | E10: Delivered | F10: Milestone 4 | G10: 10-Jun-2025 | H10: 29-Jul-2026 | I10: Sunil
A11: 5 | B11: iWork | C11: Manage Insurer | D11: Insurer-branch-edit | E11: Delivered | F11: Milestone 6 | G11: 29-Jul-2026 | H11: 29-Jul-2026
A12: 6 | B12: IBP/iWork | C12: Core Infrastructure | D12: Core Infra | E12: Delivered | F12: Milestone 5 | G12: 31-Jul-2025 | H12: 31-Jul-2026 | I12: Velangini Raju | J12: Pending: Mobile responsive
A13: 7 | B13: iWork | C13: HRMS Integration Mgmt Framework provided to link the HRMS portal in Risk Watch | D13: Base framework needs to be built and actual integration should be on need - Need to create the API's for each service flow process (Endorsement - Add/Delete) - Endorsement process - What is the process for this? HRMS - integrations with enrolment portal (POC - with Zoho People), client mentioned that they have already integrated MB360 for HCL IBP & HRMS Integration - HCL | E13: Delivered | F13: Milestone 5 | G13: 31-Jul-2025 | H13: 31-Jul-2026
A14: 8 | B14: IBP/iWork | C14: Enrolment Journey - EMI's | D14: Based on Employee's enrolment period, the EMI months should be pro-ration month. Ex: Day-1 should show the all months EMI. If someone enrol after 2-months then EMI should be based on that. | E14: Delivered | F14: Milestone 6 | G14: 29-Jul-2026 | H14: 31-Jul-2026 | J14: Kriti raised
A15: 9 | B15: iWork | C15: BizDone - Data Updates | D15: Bizdone 2025-26 - Ass. CRM & Lead CRM Corrections | E15: Delivered | F15: Milestone 6 | G15: 30-Jul-2026 | H15: 31-Jul-2026 | J15: Madhav sent in IIRM email
A16: IBP (Backlog & CRs) · 2 items · 2 delivered · 0 pending
A17: 10 | B17: IBP | C17: Chat Interface | D17: Floater on the screen - Integrate with AI Component and IWork support channel | E17: Delivered | F17: Milestone 5 | G17: 31-Jul-2025 | H17: 31-Jul-2026
A18: 11 | B18: IBP | C18: Chat for End Users | D18: Chat Module to interact with Chat Bot and Customer Support Representative | E18: Delivered | F18: Milestone 5 | G18: 31-Jul-2025 | H18: 31-Jul-2026 | I18: Abhilash | J18: External chatbot integration?

Sheet 📅 03-Aug
A1: WEEK OF 03 Aug 2026 → 09 Aug 2026 — 76 items · 1 delivered · 75 pending · NEXT WEEK
A3: ⚠️ Static snapshot. To update: edit STATUS/ETA in the source sheet, then re-run build_iirm_summary.py
A5: # | B5: Module | C5: Feature | D5: Functionality | E5: Status | F5: Milestone | G5: Requested | H5: ETA | I5: Resource | J5: Remarks
A6: iWork (Backlog & CRs) · 36 items · 0 delivered · 36 pending
A7: 1 | B7: iWork | C7: Cut Off Mgmt | E7: Pre-PROD | F7: Milestone 2 | G7: 16-Apr-2025 | H7: 03-Aug-2026 | I7: Karan
A8: 2 | B8: IBP/iWork | C8: Wellness Discount List Management | D8: Add/Remove/update Discount program benefits | E8: Pre-PROD | F8: Milestone 4 | G8: 10-Jun-2025 | H8: 03-Aug-2026
A9: 3 | B9: IBP/iWork | C9: Upload from Partner of services bought on Partner site | D9: Upload, listing, confirm & load into DB by an Iwork user. These are services purchased / discounts availed on partner sites by IBP corporate users | E9: Pre-PROD | F9: Milestone 4 | G9: 10-Jun-2025 | H9: 03-Aug-2026
A10: 4 | B10: IBP/iWork | C10: End User Portal Configurator | D10: What set of features to be enabled or disabled, Offers, Benefits etc. More or less how portal should contain and visible to end user needs to be configured (per Corporate Configuration) | E10: Pre-PROD | F10: Milestone 5 | G10: 31-Jul-2025 | H10: 03-Aug-2026 | I10: Manjusha | J10: Pending: Offer, Feature flagging (UI)
A11: 5 | B11: IBP/iWork | C11: Wellness Admin Configurator | D11: Admin side of IBP (in iWork) needs to customize/configure the offerings/page per Corporate. | E11: Pre-PROD | F11: Milestone 5 | G11: 31-Jul-2025 | H11: 03-Aug-2026 | I11: Ravi
A12: 6 | B12: iWork | C12: ISG Flow Changes | D12: Placement Slip flow - Terrorism premium in Insurer Sharing | E12: Pre-PROD | F12: Milestone 6 | G12: 27-Jul-2026 | H12: 03-Aug-2026 | I12: Karan | J12: Madhav sent in IIRM email
A13: 7 | B13: IBP/iWork - CR | C13: Service Flow - Upload Employee Details | D13: Upsert logic - Tough there is an employee data historically, when user upload latest file we have to update the "Empolyee" or "Dependent" details with the latest information | E13: DEV - WIP | F13: Milestone 6 | G13: 01-Jul-2026 | H13: 04-Aug-2026 | I13: Jagadeesh
A14: 8 | B14: IBP/iWork | C14: IBP - Email Communication | D14: For an enrolled employee with Dependents using Service, instead of Welcome Email they should get Confirmation email | E14: Pre-PROD | F14: Milestone 6 | G14: 25-Jul-2026 | H14: 04-Aug-2026 | I14: Abhilash | J14: API is ready. Need to add into Notification framework
A15: 9 | B15: iWork | C15: Reports | D15: Generic template for all the reports, Bizdone Report, Missing entries from commission statement against policies | E15: Delivered - Deficit | F15: Milestone 5 | G15: 31-Jul-2025 | H15: 05-Aug-2026 | J15: Linked with Reconciliation Management & Commission
A16: 10 | B16: IBP/iWork | C16: Country Handling {Data Source Mgmt} | D16: 23-May: Respective org. data should reside in the same country. | E16: Yet to start | F16: Milestone 4 | G16: 10-Jun-2025 | H16: 07-Aug-2026 | I16: Rama
A17: 11 | B17: iWork | C17: Teams Integration | D17: MS Teams - Meetings & Tasks integration into iWork Bi-Directional | E17: Yet to start | F17: Milestone 4 | G17: 10-Jun-2025 | H17: 07-Aug-2026 | I17: Rama
A18: 12 | B18: IBP/iWork | C18: Wellness IIRM View | D18: IIRM View of Wellness usage by Corporates/Employees (IBP Admin) | E18: Yet to start | F18: Milestone 5 | G18: 31-Jul-2025 | H18: 07-Aug-2026 | I18: Manjusha | J18: Wellness HR View
A19: 13 | B19: iWork | C19: Insurer Integration Mgmt | D19: Can be used as a part of External API Intergration | E19: Yet to start | F19: Milestone 5 | G19: 31-Jul-2025 | H19: 07-Aug-2026
A20: 14 | B20: iWork | C20: Reconciliation Management Upload Commission Statement | D20: Upload commission statement, reconcile against issued policies; Upload invoice & reconcile against commission stmt; Upload invoice statuses and reconcile paid/unpaid Premium vs Brokerage Invoice vs Brokerage Collected; Data from Finops | E20: Yet to start | F20: Milestone 5 | G20: 31-Jul-2025 | H20: 07-Aug-2026 | J20: Need inputs from Kapil
A21: 15 | B21: iWork | C21: Reconciliation Mgmt | E21: Yet to start | F21: Milestone 5 | G21: 31-Jul-2025 | H21: 07-Aug-2026
A22: 16 | B22: iWork - CR | C22: Policy Configuration | D22: Premium Rater Table | E22: Yet to start | F22: Milestone 6 | G22: 21-Apr-2026 | H22: 07-Aug-2026 | I22: Jagadeesh
A23: 17 | B23: iWork - CR | C23: Policy Configuration | D23: Enable Parent-Child Policy Mapping for GMC and Sub-Plans (Parental, OPD, Dental, Others) - How to view config from Base to Child Policiy? - How to handle endorsement & Claims? (Entire Service Flow) | E23: Yet to start | F23: Milestone 6 | G23: 01-May-2026 | H23: 07-Aug-2026 | I23: Sunil
A24: 18 | B24: iWork - CR | C24: Opportunity - Validate uploaded documents | D24: Using AI - Extract the documents, validate, populate the data in the Opty. flow (Ex. KDM Meeting, Policy Hard Copy, & Others) | E24: Yet to start | F24: Milestone 6 | G24: 08-May-2026 | H24: 07-Aug-2026 | J24: Need some information about the document rules that defines the idenity of it
A25: 19 | B25: iWork - CR | C25: SSO - MS AD Account | D25: iWork - SSO with Microsoft AD (POC) | E25: DEV - WIP | F25: Milestone 6 | G25: 05-Jun-2026 | H25: 07-Aug-2026 | I25: Rama | J25: 10-Jun-2026: POC Demo to Venu completed
A26: 20 | B26: iWork | C26: Export to Excel | D26: Export to excel - iWork all the results table; Download is on Previlage | E26: Yet to start | F26: Milestone 6 | G26: 15-Jun-2026 | H26: 07-Aug-2026
A27: 21 | B27: IBP/iWork - CR | C27: IIRM-10667 | D27: iWork - Knowledge Central Re-Design | E27: Yet to start | F27: Milestone 6 | G27: 15-Jun-2026 | H27: 07-Aug-2026
A28: 22 | B28: IBP/iWork - CR | C28: IIRM-10668 | D28: iLearn: Document Preview in-app | E28: Yet to start | F28: Milestone 6 | G28: 15-Jun-2026 | H28: 07-Aug-2026
A29: 23 | B29: iWork | C29: Discuss with Madhav | D29: 19-Jun-2026: Financial Impact fields should be seperated from actual fields. These fields should NOT be populated on their own. (Mainly BizDone & Dashboard) Also, check if we are there are any data loads for 2025-26 | E29: Yet to start | F29: Milestone 6 | G29: 15-Jun-2026 | H29: 07-Aug-2026
A30: 24 | B30: iWork | C30: Installment & Fee Requirements | D30: Installments & Fee to BizDone | E30: Yet to start | F30: Milestone 6 | G30: 15-Jun-2026 | H30: 07-Aug-2026
A31: 25 | B31: IBP/iWork - CR | C31: InsureEasy | D31: InsureEasy Integration - Retail Business | E31: Yet to start | F31: Milestone 6 | G31: 25-Jun-2026 | H31: 07-Aug-2026
A32: 26 | B32: iWork | C32: AI | D32: Wherever AI is implemented, there should be fallback if one day we turnoff AI then there shouldn’t be any impact in the working functionality | E32: Yet to start | F32: Milestone 6 | G32: 25-Jun-2026 | H32: 07-Aug-2026 | I32: Rama
A33: 27 | B33: iWork | C33: AI | D33: AI Nudges are NOT working. If there is NO AI, then DB scripts should run and show data | E33: Yet to start | F33: Milestone 6 | G33: 25-Jun-2026 | H33: 07-Aug-2026 | I33: Rama
A34: 28 | B34: iWork | C34: Inception/Endorsement | D34: Endorsement data upload related * Track-1: TeamLease - 2024-2025 Year policies * All endorsement -> Headers, Member data, & endorsement Document * Track-2: Old Financial data * Track-3: Current Financial data * Track-4: Handle the data in IBP-Risk Watch | E34: Dev - WIP | F34: Milestone 6 | G34: 25-Jun-2026 | H34: 07-Aug-2026 | I34: Rama
A35: 29 | B35: iWork - CR | C35: BizDone | D35: Computed value & Reported values * Computed values - It’s the real-time values base on Policy inception/endorsement * Reported values - It’s validated by the mgmt. and share this number to update in the column. * Reported value MUST be used for the Dashboard & BizDone, which was declared by the company to public. * In the admin a feature to update the Reported values from the computed values * Legacy data - Premiums, Brokerage, CD Balance | E35: Yet to start | F35: Milestone 6 | G35: 25-Jun-2026 | H35: 07-Aug-2026
A36: 30 | B36: IBP/iWork | C36: IBP - Raise Ticket | D36: Edit the ticket and update the status by the Lead CRM & System Admin | E36: Pre-PROD | F36: Milestone 6 | G36: 01-Jul-2026 | H36: 07-Aug-2026 | I36: Manjusha
A37: 31 | B37: IBP/iWork - CR | C37: No Policy Config - Enrolment Journey | D37: Enrolment Journey - Collect Dependents Details ONLY | E37: Dev - WIP | F37: Milestone 6 | G37: 04-Jul-2026 | H37: 07-Aug-2026 | I37: Jagadeesh | J37: 1. IBP - Enrolment - Completed 2. Service - WIP
A38: 32 | B38: IBP/iWork | C38: Toast Message - UI | D38: Update the font & style for Toast message across application | E38: Yet to start | F38: Milestone 6 | G38: 09-Jul-2026 | H38: 07-Aug-2026 | I38: Tharun | J38: Surya sir provided an idea via email to Me & Naveen
A39: 33 | B39: IBP/iWork - CR | C39: IBP - Welcome Emails | D39: Dual approval/confirmation - Before sending to Employees. 1. 2 levels in iWork 2. CRM will submit & HR will approve in Risk Watch | E39: Yet to start | F39: Milestone 6 | G39: 14-Jul-2026 | H39: 07-Aug-2026
A40: 34 | B40: iWork - CR | C40: Help Info - Field formulaes or field values | D40: In any of the screen, we have to provide an info icon where it will help the users how critical fields in that screen are derieved or got populated | E40: Yet to start | F40: Milestone 6 | G40: 17-Jul-2026 | H40: 07-Aug-2026
A41: 35 | B41: IBP/iWork | C41: Application Performance | D41: IIRM-10799_Performance (Database & Infra) | E41: Yet to start | F41: Milestone 6 | G41: 24-Jul-2026 | H41: 07-Aug-2026
A42: 36 | B42: iWork | C42: Personal Line Data Integrations | D42: DSR and iWork Integration Enablement | E42: Yet to start | F42: Milestone 6 | G42: 25-Jul-2026 | H42: 07-Aug-2026 | J42: Madhav sent in IIRM email
A43: IBP (Backlog & CRs) · 21 items · 0 delivered · 21 pending
A44: 37 | B44: IBP | C44: Landing Page Services | D44: Benefits Summary View, Upcoming welness appointment, Policy renewals, Individual Plans Summary views | E44: Pre-PROD | F44: Milestone 5 | G44: 31-Jul-2025 | H44: 03-Aug-2026 | I44: Manjusha
A45: 38 | B45: IBP | C45: User Profile | D45: Profile, Service Subscriptions, Feedback | E45: Pre-PROD | F45: Milestone 5 | G45: 31-Jul-2025 | H45: 03-Aug-2026 | I45: Ravi | J45: Pending: Service Subscriptions, Feedback
A46: 39 | B46: IBP | C46: Evexia Club Integration | D46: Integration to Evexia | E46: Pre-PROD | F46: Milestone 5 | G46: 31-Jul-2025 | H46: 03-Aug-2026 | I46: Abhilash
A47: 40 | B47: IBP | C47: Benefits Summary | D47: End User's Summary View | E47: Pre-PROD | F47: Milestone 5 | G47: 31-Jul-2025 | H47: 03-Aug-2026 | I47: Ravi
A48: 41 | B48: IBP | C48: Basic Wellness Hub | D48: Basic wellness hub - Currently only 3 wellness programs (3rd parties) supported | E48: Pre-PROD | F48: Milestone 5 | G48: 31-Jul-2025 | H48: 03-Aug-2026 | I48: Manjusha | J48: Wellness
A49: 42 | B49: IBP - CR | C49: Claim Intimation & Submission | D49: POC - Using AI(Amazon Textract) - Extract Claim documents and populate the data | E49: Pre-PROD | F49: Milestone 6 | G49: 08-May-2026 | H49: 03-Aug-2026 | I49: Abhilash
A50: 43 | B50: IBP | C50: Enrolment Journey - Component - Notes | D50: Policy Level - Component Notes from Stapi | E50: Yet to start | F50: Milestone 6 | G50: 29-Jul-2026 | H50: 04-Aug-2026 | J50: Kriti raised
A51: 44 | B51: IBP | C51: NFR_Usability | D51: NFR-USA-011: The system should support at least 100 concurrent users without performance degradation. | E51: Pre-PROD | F51: Milestone 4 | G51: 10-Jun-2025 | H51: 07-Aug-2026 | I51: Akhila | J51: Fine tuning the API's where there is a delay
A52: 45 | B52: IBP | C52: Premium Range Calculator | D52: Calculate insurance premium range. Calculate the IDV of various assets | E52: Yet to start | F52: Milestone 5 | G52: 31-Jul-2025 | H52: 07-Aug-2026 | I52: Ravi | J52: Retail Business
A53: 46 | B53: IBP | C53: Multiple 3rd Party Service Mgmt | D53: Elderly Services, Dental Services etc. 3rd Party integrations. Multiple providers 3 such services are in scope at this stage {Redhealth, MyDental, AkinCare} | E53: Yet to start | F53: Milestone 5 | G53: 31-Jul-2025 | H53: 07-Aug-2026 | J53: Retail Business
A54: 47 | B54: IBP | C54: Claims Mgmt | D54: Part-2: Personal Policy based claim mgmt, Tracking status, Document Mgmt related to claims | E54: Yet to start | F54: Milestone 5 | G54: 31-Jul-2025 | H54: 07-Aug-2026 | J54: Retail Business
A55: 48 | B55: IBP | C55: Individual Insurance Plan Mgmt | D55: Support for multiple categories of plans. Configuration Mgmt for Infomration capture, Flow and Summaries. Add on configuration, Insurer configuration, Offer configuration, Post the request to Sales Channel (Iwork) 7 Policy Types to be taken care of | E55: Yet to start | F55: Milestone 5 | G55: 31-Jul-2025 | H55: 07-Aug-2026 | I55: Ravi | J55: Retail Business
A56: 49 | B56: IBP | C56: My Insurance | D56: Part-2: Hub of all plans I have as an employee - individually signed up. Mostly a navigational page | E56: Yet to start | F56: Milestone 5 | G56: 31-Jul-2025 | H56: 07-Aug-2026 | I56: Ravi | J56: Retail Business
A57: 50 | B57: IBP | C57: Wellness HR View | D57: HR View of Wellness usage by Employees | E57: Yet to start | F57: Milestone 5 | G57: 31-Jul-2025 | H57: 07-Aug-2026 | I57: Manjusha | J57: Wellness
A58: 51 | B58: IBP | C58: Wellness Partner View | D58: Partner/service provider view of the usage of their corresponding services | E58: Yet to start | F58: Milestone 5 | G58: 31-Jul-2025 | H58: 07-Aug-2026 | I58: Manjusha | J58: Wellness
A59: 52 | B59: IBP | C59: Individual Plans | D59: Quotation flow of a new insurance - multple products; quotation ranges after basic data collection; cross-sells and finally an summary page that someone will get back to you. About 7 individual products - could be 4-5 screens in the flow of which 2 screens may be product-specific. | E59: Yet to start | F59: Milestone 5 | G59: 31-Jul-2025 | H59: 07-Aug-2026 | I59: Ravi | J59: Retail Business
A60: 53 | B60: IBP | C60: Individual Plan Summary | D60: View of individual Plans currently owned with renewal dates, premiums etc. | E60: Yet to start | F60: Milestone 5 | G60: 31-Jul-2025 | H60: 07-Aug-2026 | I60: Ravi | J60: Retail Business
A61: 54 | B61: IBP | C61: Profile Migration | D61: Request migration of Corporate Profile to Individual | E61: Yet to start | F61: Milestone 5 | G61: 31-Jul-2025 | H61: 07-Aug-2026 | I61: Abhilash | J61: Retail Business
A62: 55 | B62: IBP | C62: Profile Migration | D62: Request migration of Individual Profile to Corporate | E62: Yet to start | F62: Milestone 5 | G62: 31-Jul-2025 | H62: 07-Aug-2026 | I62: Abhilash | J62: Retail Business
A63: 56 | B63: IBP | C63: IIRM-10666 | D63: IBP - Policy Component Card Re-design | E63: Yet to start | F63: Milestone 6 | G63: 21-Jun-2026 | H63: 07-Aug-2026 | I63: Manjusha
A64: 57 | B64: IBP | C64: Claims Corner | D64: Claims Corner - Screen Re-design | E64: Dev - WIP | F64: Milestone 6 | G64: 21-Jun-2026 | H64: 07-Aug-2026 | I64: Ravi
A65: Framework (DPDP, NFR, Framework) · 19 items · 1 delivered · 18 pending
A66: 58 | B66: Framework | C66: Notifications Management | D66: Different email notification - Madhav excel. 1. Renewal Reminders - ASAP 2. Instalment Reminders 3. Others | E66: Pre-PROD | F66: Milestone 4 | G66: 10-Jun-2025 | H66: 03-Aug-2026 | I66: Pushyami
A67: 59 | B67: DPDP | C67: Archived Oppurtunity, Policy Mgmt {Archived Biz Data and Retrieval on need} - DPDP | E67: Yet to start | F67: Milestone 4 | G67: 10-Jun-2025 | H67: 07-Aug-2026 | I67: Rama | J67: Duplicate of Archival from NFR & DPDP
A68: 60 | B68: Framework | C68: Accessibility | D68: 20-Jul: Jagadees --> Need More details | E68: Yet to start | F68: Milestone 4 | G68: 10-Jun-2025 | H68: 07-Aug-2026
A69: 61 | B69: Framework | C69: Localisation | E69: Delivered - Deficit | F69: Milestone 4 | G69: 10-Jun-2025 | H69: 07-Aug-2026 | I69: Tharun | J69: Pending: Service Flow
A70: 62 | B70: NFR | C70: NFR_Usability | D70: NFR-USA-021: Guidelines for document management should be provided | E70: Delivered - Deficit | F70: Milestone 4 | G70: 10-Jun-2025 | H70: 07-Aug-2026 | I70: Rama | J70: Pending: Provide the document on how do we store and view it
A71: 63 | B71: DPDP | C71: App vulnerability scans | E71: Dev - WIP | F71: Milestone 5 | G71: 31-Jul-2025 | H71: 07-Aug-2026
A72: 64 | B72: DPDP | C72: Document Flows | E72: Dev - WIP | F72: Milestone 5 | G72: 31-Jul-2025 | H72: 07-Aug-2026
A73: 65 | B73: DPDP | C73: Perform security UAT | E73: Dev - WIP | F73: Milestone 5 | G73: 31-Jul-2025 | H73: 07-Aug-2026
A74: 66 | B74: DPDP | C74: Remove unnecessary fields | E74: Dev - Done | F74: Milestone 5 | G74: 31-Jul-2025 | H74: 07-Aug-2026
A75: 67 | B75: DPDP | C75: Enforce business logic to restrict purpose | E75: Dev - WIP | F75: Milestone 5 | G75: 31-Jul-2025 | H75: 07-Aug-2026
A76: 68 | B76: DPDP | C76: Allow user corrections | E76: Dev - WIP | F76: Milestone 5 | G76: 31-Jul-2025 | H76: 07-Aug-2026
A77: 69 | B77: DPDP | C77: Delete expired data | E77: Dev - WIP | F77: Milestone 5 | G77: 31-Jul-2025 | H77: 07-Aug-2026
A78: 70 | B78: DPDP | C78: Map PII tables | E78: QA - WIP | F78: Milestone 5 | G78: 31-Jul-2025 | H78: 07-Aug-2026 | I78: Rama
A79: 71 | B79: DPDP | C79: Enable delete pipeline | E79: Yet to start | F79: Milestone 5 | G79: 31-Jul-2025 | H79: 07-Aug-2026
A80: 72 | B80: DPDP | C80: Define archival | E80: Yet to start | F80: Milestone 5 | G80: 31-Jul-2025 | H80: 07-Aug-2026
A81: 73 | B81: DPDP | C81: Sign DPDP clauses | E81: Dev - WIP | F81: Milestone 5 | G81: 31-Jul-2025 | H81: 07-Aug-2026
A82: 74 | B82: NFR | C82: NFR-OTH-022: A self-service report generator must be available for dynamic query/report creation. | E82: Yet to start | F82: Milestone 5 | G82: 31-Jul-2025 | H82: 07-Aug-2026 | J82: Discussed this with Surya sir last visit to Divami office
A83: 75 | B83: NFR | C83: NFR-OTH-015: The application must cryptographic Failures, previously known as Sensitive Data Exposure, which was broad symptom rather than a root cause. The renewed focus here is on failures related to cryptography which often leads to sensitive data exposure or system compromise. | E83: Dev - WIP | F83: Milestone 5 | G83: 31-Jul-2025 | H83: 07-Aug-2026
A84: 76 | B84: DPDP | C84: Quarterly restore tests | E84: Pre-PROD | F84: Milestone 5 | G84: 31-Jul-2025 | H84: 07-Aug-2026 | I84: Rama

Sheet 📅 Upcoming
A1: UPCOMING (ETA beyond 03 Aug week) — 0 items · 0 delivered · 0 pending
A3: ⚠️ Static snapshot. To update: edit STATUS/ETA in the source sheet, then re-run build_iirm_summary.py
A5: # | B5: Module | C5: Feature | D5: Functionality | E5: Status | F5: Milestone | G5: Requested | H5: ETA | I5: Resource | J5: Remarks

Sheet VRK Feedbacks
A1: VRK — PROD FEEDBACK TRACKER · 68 items · 66 delivered · 2 pending
A3: All 'VRK - PROD Feedback:' items, broken up by week (status then ETA within a week). Excluded from the other views. Static snapshot.
A5: # | B5: Module | C5: Feature | D5: Functionality | E5: Status | F5: Milestone | G5: Requested | H5: ETA | I5: Resource | J5: Remarks
A6: 📅 WEEK OF 08 Jun → 14 Jun 2026 · PAST · 27 items
A7: 1 | B7: iWork | C7: VRK - PROD Feedback: 5-Jun-2026 | D7: Manage SO - Update the date filters to "SO Expiry Date" | E7: Delivered | F7: Milestone 6 | G7: 05-Jun-2026 | H7: 08-Jun-2026
A8: 2 | B8: iWork | C8: VRK - PROD Feedback: 8-Jun-2026 | D8: Critical: SO expiry logic and date validation should allow within 365 days at the time so creation. | E8: Delivered | F8: Milestone 6 | G8: 08-Jun-2026 | H8: 08-Jun-2026
A9: 3 | B9: iWork | C9: VRK - PROD Feedback: 8-Jun-2026 | D9: Dashboard - Save View button to be moved to Run button --> Move the Save View button beside Reset | E9: Delivered | F9: Milestone 6 | G9: 08-Jun-2026 | H9: 08-Jun-2026
A10: 4 | B10: iWork | C10: VRK - PROD Feedback: 8-Jun-2026 | D10: Dont display CD management in menu link - move under Admin | E10: Delivered | F10: Milestone 6 | G10: 08-Jun-2026 | H10: 08-Jun-2026
A11: 5 | B11: iWork | C11: VRK - PROD Feedback: 8-Jun-2026 | D11: filter out support services from the dashboard | E11: Delivered | F11: Milestone 6 | G11: 08-Jun-2026 | H11: 08-Jun-2026
A12: 6 | B12: iWork | C12: VRK - PROD Feedback: 8-Jun-2026 | D12: funnels - hide Overall conversion values | E12: Delivered | F12: Milestone 6 | G12: 08-Jun-2026 | H12: 08-Jun-2026
A13: 7 | B13: iWork | C13: VRK - PROD Feedback: 8-Jun-2026 | D13: In My RO, "BD planning" title should change to "Renewal Planning" for RO | E13: Delivered | F13: Milestone 6 | G13: 08-Jun-2026 | H13: 08-Jun-2026
A14: 8 | B14: iWork | C14: VRK - PROD Feedback: 8-Jun-2026 | D14: Manage TPA/BRoker/Insurer should be moved to Admin Module | E14: Delivered | F14: Milestone 6 | G14: 08-Jun-2026 | H14: 08-Jun-2026
A15: 9 | B15: iWork | C15: VRK - PROD Feedback: 8-Jun-2026 | D15: My Follow Up - hide "All" option - RO should be default | E15: Delivered | F15: Milestone 6 | G15: 08-Jun-2026 | H15: 08-Jun-2026
A16: 10 | B16: iWork | C16: VRK - PROD Feedback: 8-Jun-2026 | D16: Policy Expiry Timeline by SBU - change to "Renewal Schedule by SBU" and move under renewal funnel | E16: Delivered | F16: Milestone 6 | G16: 08-Jun-2026 | H16: 08-Jun-2026
A17: 11 | B17: iWork | C17: VRK - PROD Feedback: 8-Jun-2026 | D17: Ribbon level reports link should be hidden --> Hide "Reports" on the header menu. And also move the "Utilization report" to Admin Module. | E17: Delivered | F17: Milestone 6 | G17: 08-Jun-2026 | H17: 08-Jun-2026
A18: 12 | B18: iWork | C18: VRK - PROD Feedback: 8-Jun-2026 IIRM-10589 | D18: My client portfolio - Period (Company created) change to - Period (policies created) --- Show the same filters of Manage Policy | E18: Delivered | F18: Milestone 6 | G18: 08-Jun-2026 | H18: 09-Jun-2026 | I18: Karan
A19: 13 | B19: iWork | C19: VRK - PROD Feedback: 8-Jun-2026 | D19: isg roles: manage quotes screen should display the opportunities which are related to ISG only. | E19: Delivered | F19: Milestone 6 | G19: 08-Jun-2026 | H19: 09-Jun-2026
A20: 14 | B20: iWork | C20: VRK - PROD Feedback: 9-Jun-2026 | D20: BD/ISG planning dates should be empty and mandatory - should be mandatory to start the journey. | E20: Delivered | F20: Milestone 6 | G20: 09-Jun-2026 | H20: 09-Jun-2026
A21: 15 | B21: iWork | C21: VRK - PROD Feedback: 9-Jun-2026 | D21: In "Manage Quotes"/"Manage SO" page, a link should be provided on the activity name, it should get redirected to respective activity stage. | E21: Delivered | F21: Milestone 6 | G21: 09-Jun-2026 | H21: 09-Jun-2026 | I21: Pushyami
A22: 16 | B22: iWork | C22: VRK - PROD Feedback: 9-Jun-2026 | D22: Issue in Bizdone search results - Company name not visible | E22: Delivered | F22: Milestone 6 | G22: 09-Jun-2026 | H22: 09-Jun-2026 | I22: Pushyami
A23: 17 | B23: iWork | C23: VRK - PROD Feedback: 9-Jun-2026 IIRM-10588 | D23: Rename "My SO" to "Manage SO" in the sales portfolio. | E23: Delivered | F23: Milestone 6 | G23: 09-Jun-2026 | H23: 09-Jun-2026 | I23: Pushyami
A24: 18 | B24: iWork | C24: VRK - PROD Feedback: 9-Jun-2026 | D24: SO creation process: SO Expiry field title should be changed to "Opportunity/Existing Policy Expiry" - label to be changed. Nithin --> Also, change in SO details page as well | E24: Delivered | F24: Milestone 6 | G24: 09-Jun-2026 | H24: 09-Jun-2026 | I24: Pushyami
A25: 19 | B25: iWork | C25: VRK - PROD Feedback: 8-Jun-2026 | D25: My RO clicked should not get highlighted to My SO menu link. | E25: Delivered | F25: Milestone 6 | G25: 08-Jun-2026 | H25: 10-Jun-2026
A26: 20 | B26: iWork | C26: VRK - PROD Feedback: 9-Jun-2026 | D26: My followup section in the dashboard - should display default Activity names and show the values even there are zeros for each activity. | E26: Delivered | F26: Milestone 6 | G26: 09-Jun-2026 | H26: 10-Jun-2026 | I26: Prathiphala
A27: 21 | B27: iWork | C27: VRK - PROD Feedback: 9-Jun-2026 | D27: Opportunity lost logic:- if placement slip is not crossed, instantly mark the opportunity as "Lost" based on Opty. Expiry date | E27: Delivered | F27: Milestone 6 | G27: 09-Jun-2026 | H27: 10-Jun-2026 | I27: Jagadeesh
A28: 22 | B28: iWork | C28: VRK - PROD Feedback: 9-Jun-2026 | D28: Opportunity lost logic:- if the activity crossed "Placement Slip", premium calculation and crossed 5 days, then mark the opportunity as "Lost" based on Opty. expiry date+5 days | E28: Delivered | F28: Milestone 6 | G28: 09-Jun-2026 | H28: 10-Jun-2026 | I28: Jagadeesh
A29: 23 | B29: iWork | C29: VRK - PROD Feedback: 8-Jun-2026 IIRM-10589 | D29: My client portfolio - list of all companies for Active policies only | E29: Delivered | F29: Milestone 6 | G29: 08-Jun-2026 | H29: 12-Jun-2026 | I29: Karan
A30: 24 | B30: iWork | C30: VRK - PROD Feedback: 8-Jun-2026 | D30: Policy Expiry Timeline by SBU - when clicked, redirect to RO screen with the counts. | E30: Delivered | F30: Milestone 6 | G30: 08-Jun-2026 | H30: 12-Jun-2026
A31: 25 | B31: iWork | C31: VRK - PROD Feedback: 9-Jun-2026 | D31: BDR results list should display the link of policy ID and Opty ID. | E31: Delivered | F31: Milestone 6 | G31: 09-Jun-2026 | H31: 12-Jun-2026 | I31: Prathiphala
A32: 26 | B32: iWork | C32: VRK - PROD Feedback: 8-Jun-2026 | D32: My client portfolio: List of Companies should be displayed for which there are active RO's. The premium and brokerage should be displayed as per RO cards. --> Que: Yesterday it was asked to get the data related to Active Policies???? | E32: Not a bug | F32: Milestone 6 | G32: 08-Jun-2026 | H32: 08-Jun-2026 | J32: 10-Jun: As per Surya/Kapil Sir. It's Active Policies only
A33: 27 | B33: iWork | C33: VRK - PROD Feedback: 8-Jun-2026 | D33: my followup should be added into my actionalables with default display instead of "All" tab. | E33: Not a bug | F33: Milestone 6 | G33: 08-Jun-2026 | H33: 08-Jun-2026
A34: 📅 WEEK OF 15 Jun → 21 Jun 2026 · PAST · 8 items
A35: 28 | B35: iWork | C35: VRK - PROD Feedback: 9-Jun-2026 IIRM-10589 | D35: All SO and RO items should be displayed order by Expiry Date (ascending) in the same page once "Manage Quotes" is clicked by the user. | E35: Delivered | F35: Milestone 6 | G35: 09-Jun-2026 | H35: 15-Jun-2026 | I35: Karan
A36: 29 | B36: iWork | C36: VRK - PROD Feedback: 9-Jun-2026 IIRM-10589 | D36: ISG users should be able to view ISG activities only and BD related activities should be collapsable and hidden; accordingly manage the breadcrums. Similarly, vice versa for BD users. | E36: Delivered | F36: Milestone 6 | G36: 09-Jun-2026 | H36: 15-Jun-2026 | I36: Karan
A37: 30 | B37: iWork | C37: VRK - PROD Feedback: 9-Jun-2026 IIRM-10589 | D37: Manage Quote RO and Manager Quote SO should be clubbed to "Manage Quotes" link for ISG team only. --> 10-Jun: Surya -> Show the data only when opty. is in ISG Activity. | E37: Delivered | F37: Milestone 6 | G37: 09-Jun-2026 | H37: 15-Jun-2026 | I37: Karan
A38: 31 | B38: iWork | C38: VRK - PROD Feedback: 9-Jun-2026 IIRM-10589 | D38: My client portfolio: There must be a provision of "Past company" view in the Client Portfolio. | E38: Delivered | F38: Milestone 6 | G38: 09-Jun-2026 | H38: 15-Jun-2026
A39: 32 | B39: iWork | C39: VRK - PROD Feedback: 9-Jun-2026 IIRM-10589 | D39: Nithin -> Add the filters required to handle both SO & RO in "Manage Quotes" | E39: Delivered | F39: Milestone 6 | G39: 09-Jun-2026 | H39: 15-Jun-2026 | I39: Karan
A40: 33 | B40: iWork | C40: VRK - PROD Feedback: 9-Jun-2026 IIRM-10589 | D40: Hide "My RO" from the Sales portfolio. Add in the "My Client Portfolio" | E40: Delivered | F40: Milestone 6 | G40: 09-Jun-2026 | H40: 16-Jun-2026
A41: 34 | B41: iWork | C41: VRK - PROD Feedback: 8-Jun-2026 | D41: Commercial lines 25-26 numbers should be rectified; it should be 24.99 | E41: Delivered | F41: Milestone 6 | G41: 08-Jun-2026 | H41: 19-Jun-2026 | I41: Rama
A42: 35 | B42: iWork | C42: VRK - PROD Feedback: 9-Jun-2026 | D42: All Stage/Activity-wise wherever Document upload option is there, should be a mandatory | E42: Delivered | F42: Milestone 6 | G42: 09-Jun-2026 | H42: 19-Jun-2026 | I42: Karan
A43: 📅 WEEK OF 22 Jun → 28 Jun 2026 · PAST · 1 item
A44: 36 | B44: iWork | C44: VRK - PROD Feedback: 8-Jun-2026 | D44: funnels - alignment graph issues with grid; | E44: Delivered | F44: Milestone 6 | G44: 08-Jun-2026 | H44: 24-Jun-2026
A45: 📅 WEEK OF 29 Jun → 05 Jul 2026 · PAST · 8 items
A46: 37 | B46: iWork | C46: VRK - PROD Feedback: 8-Jun-2026 | D46: Policy Hard copy receipt stage - When User uploads the Policy copy, system should capture the policy level elements like Ins Pol No., Dates, Premium amounts, etc and validate with the policy record saved. - Need discussion for more details to use the deviation and approval process to modify the values as per deviation from Policy Hard copy. | E46: Delivered | F46: Milestone 6 | G46: 08-Jun-2026 | H46: 30-Jun-2026 | I46: Jagadeesh
A47: 38 | B47: iWork - CR | C47: VRK - PROD Feedback: 23-Jun-2026 | D47: Ribbon level: Reports should include Poppins & Bizdone report | E47: Delivered | F47: Milestone 6 | G47: 23-Jun-2026 | H47: 01-Jul-2026 | I47: Pushyami
A48: 39 | B48: iWork - CR | C48: VRK - PROD Feedback: 23-Jun-2026 | D48: Hide "Reports" from Left Menu | E48: Delivered | F48: Milestone 6 | G48: 23-Jun-2026 | H48: 01-Jul-2026 | I48: Pushyami
A49: 40 | B49: iWork - CR | C49: VRK - PROD Feedback: 23-Jun-2026 | D49: Remove "±5 days of expiry" | E49: Delivered | F49: Milestone 6 | G49: 23-Jun-2026 | H49: 01-Jul-2026 | I49: Pushyami
A50: 41 | B50: iWork - CR | C50: VRK - PROD Feedback: 23-Jun-2026 | D50: Dashboard - SO - Add SBU schedule & My Follow-ups | E50: Delivered | F50: Milestone 6 | G50: 23-Jun-2026 | H50: 01-Jul-2026 | I50: Pushyami
A51: 42 | B51: iWork - CR | C51: VRK - PROD Feedback: 23-Jun-2026 | D51: Dashboard - RO - Add SBU schedule & My Follow-ups | E51: Delivered | F51: Milestone 6 | G51: 23-Jun-2026 | H51: 01-Jul-2026 | I51: Pushyami
A52: 43 | B52: iWork - CR | C52: VRK - PROD Feedback: 23-Jun-2026 | D52: Business Performance - Update to stacked bar | E52: Delivered | F52: Milestone 6 | G52: 23-Jun-2026 | H52: 01-Jul-2026 | I52: Pushyami
A53: 44 | B53: iWork | C53: VRK - PROD Feedback: 8-Jun-2026 | D53: Filter stickyness is not working for Bizdone and check with all the other screens. (Filters Persistence in all the screens) | E53: Delivered | F53: Milestone 6 | G53: 08-Jun-2026 | H53: 02-Jul-2026
A54: 📅 WEEK OF 06 Jul → 12 Jul 2026 · PAST · 3 items
A55: 45 | B55: iWork - CR | C55: VRK - PROD Feedback: 23-Jun-2026 | D55: My RO - SBU, Vertical, Branch break-down with details | E55: Delivered | F55: Milestone 6 | G55: 23-Jun-2026 | H55: 07-Jul-2026 | I55: Pushyami
A56: 46 | B56: iWork - CR | C56: VRK - PROD Feedback: 23-Jun-2026 | D56: Manage SO - SBU, Vertical, Branch break-down with details | E56: Delivered | F56: Milestone 6 | G56: 23-Jun-2026 | H56: 08-Jul-2026 | I56: Pushyami
A57: 47 | B57: iWork - CR | C57: VRK - PROD Feedback: 23-Jun-2026 | D57: BizDone - SBU, Vertical, Branch break-down with details | E57: Delivered | F57: Milestone 6 | G57: 23-Jun-2026 | H57: 08-Jul-2026 | I57: Pushyami
A58: 📅 WEEK OF 13 Jul → 19 Jul 2026 · PAST · 13 items
A59: 48 | B59: iWork - CR | C59: VRK - PROD Feedback: 13-Jul-2026 | D59: Enhanced Screens: Layout Changes - Remove the Vertical section. Keep only Branch. | E59: Delivered | F59: Milestone 6 | G59: 13-Jul-2026 | H59: 13-Jul-2026
A60: 49 | B60: iWork - CR | C60: VRK - PROD Feedback: 23-Jun-2026 | D60: My Client Portfolio - SBU, Vertical, Branch break-down with details | E60: Delivered | F60: Milestone 6 | G60: 23-Jun-2026 | H60: 14-Jul-2026 | I60: Karan
A61: 50 | B61: iWork - CR | C61: VRK - PROD Feedback: 23-Jun-2026 | D61: Dashboard - Filter & drill-down | E61: Delivered | F61: Milestone 6 | G61: 23-Jun-2026 | H61: 14-Jul-2026 | I61: Karan
A62: 51 | B62: iWork - CR | C62: VRK - PROD Feedback: 13-Jul-2026 | D62: Dashboard UI & Visualization - Remove the SO/RO labels from the bar charts. Display only the figures inside the bars, with the corresponding details available on mouse hover (tooltip). | E62: Delivered | F62: Milestone 6 | G62: 13-Jul-2026 | H62: 14-Jul-2026
A63: 52 | B63: iWork - CR | C63: VRK - PROD Feedback: 13-Jul-2026 | D63: Dashboard UI & Visualization - Review and correct the display of negative values for TeamLease under RO, particularly for Q3 bar-chart. | E63: Delivered | F63: Milestone 6 | G63: 13-Jul-2026 | H63: 14-Jul-2026
A64: 53 | B64: iWork - CR | C64: VRK - PROD Feedback: 13-Jul-2026 | D64: Brokerage Display - Display Brokerage information only. Hide Premium values in the enhanced screens. | E64: Delivered | F64: Milestone 6 | G64: 13-Jul-2026 | H64: 15-Jul-2026
A65: 54 | B65: iWork - CR | C65: VRK - PROD Feedback: 13-Jul-2026 | D65: BizDone Enhanced Screen - Hide Premium. Display: RO Brokerage SO Brokerage | E65: Delivered | F65: Milestone 6 | G65: 13-Jul-2026 | H65: 15-Jul-2026
A66: 55 | B66: iWork - CR | C66: VRK - PROD Feedback: 13-Jul-2026 | D66: Dashboard UI & Visualization - Resolve the Premium value formatting issue. Values should be displayed consistently in Millions/Billions. | E66: Delivered | F66: Milestone 6 | G66: 13-Jul-2026 | H66: 15-Jul-2026
A67: 56 | B67: iWork - CR | C67: VRK - PROD Feedback: 13-Jul-2026 | D67: Dashboard UI & Visualization - Display the Endorsement section above the section “Business Collection Summary”. | E67: Delivered | F67: Milestone 6 | G67: 13-Jul-2026 | H67: 15-Jul-2026
A68: 57 | B68: iWork - CR | C68: VRK - PROD Feedback: 13-Jul-2026 | D68: Dashboard UI & Visualization - Move the Policy Type Distribution section above RO by SBU. | E68: Delivered | F68: Milestone 6 | G68: 13-Jul-2026 | H68: 15-Jul-2026
A69: 58 | B69: iWork - CR | C69: VRK - PROD Feedback: 13-Jul-2026 | D69: Dashboard UI & Visualization - Rename/update the Policy Type names “Fire & Engineering”, “Speciality Lines - Liability” | E69: Delivered | F69: Milestone 6 | G69: 13-Jul-2026 | H69: 15-Jul-2026
A70: 59 | B70: iWork - CR | C70: VRK - PROD Feedback: 13-Jul-2026 | D70: Functional Changes - The SO Activity Follow-up screen should not display ISG-related activities. | E70: Delivered | F70: Milestone 6 | G70: 13-Jul-2026 | H70: 15-Jul-2026
A71: 60 | B71: iWork - CR | C71: VRK - PROD Feedback: 13-Jul-2026 | D71: Dashboard Issues - When IIRM Holdings is selected, the Organization-level cards and graphs are not displayed. Verify and fix the issue. | E71: Delivered | F71: Milestone 6 | G71: 13-Jul-2026 | H71: 17-Jul-2026
A72: 📅 WEEK OF 20 Jul → 26 Jul 2026 · LAST WEEK · 3 items
A73: 61 | B73: iWork - CR | C73: VRK - PROD Feedback: 13-Jul-2026 | D73: Enhanced Screens: Layout Changes - Display the data using an Accordion layout in the following order: Company → SBU → Branch → Executive → Client → Policy | E73: Delivered | F73: Milestone 6 | G73: 13-Jul-2026 | H73: 20-Jul-2026
A74: 62 | B74: iWork - CR | C74: VRK - PROD Feedback: 13-Jul-2026 | D74: Functional Changes - Make the Funnel interactive so that clicking on each stage navigates to the corresponding enhanced screen. Also, when we click on "Numbers" also it has to move to respective screens | E74: Delivered | F74: Milestone 6 | G74: 13-Jul-2026 | H74: 22-Jul-2026 | I74: Pushyami | J74: Pending: Becuase the enhanced screens are yet to Approve
A75: 63 | B75: iWork - CR | C75: VRK - PROD Feedback: 13-Jul-2026 | D75: Dashboard Issues - Under PL, the bar chart should represent SO-level data instead of the currently displayed RO-level data. | E75: Delivered | F75: Milestone 6 | G75: 13-Jul-2026 | H75: 22-Jul-2026 | I75: Jagadeesh
A76: 📍 WEEK OF 27 Jul → 02 Aug 2026 · CURRENT WEEK · 2 items
A77: 64 | B77: iWork - CR | C77: VRK - PROD Feedback: 23-Jun-2026 | D77: Additional section display: Placement Funnel, Schedule, Followup | E77: Delivered | F77: Milestone 6 | G77: 23-Jun-2026 | H77: 30-Jul-2026 | I77: Karan
A78: 65 | B78: iWork - CR | C78: VRK - PROD Feedback: 13-Jul-2026 | D78: Enhanced screen: My Client Portfolio | E78: Delivered | F78: Milestone 6 | G78: 27-Jul-2026 | H78: 30-Jul-2026
A79: 📅 WEEK OF 03 Aug → 09 Aug 2026 · NEXT WEEK · 2 items
A80: 66 | B80: iWork - CR | C80: VRK - PROD Feedback: 23-Jun-2026 | D80: iWork and iTicket should be accessible via VPN | E80: Yet to start | F80: Milestone 6 | G80: 23-Jun-2026 | H80: 07-Aug-2026 | I80: Pushyami
A81: 67 | B81: iWork | C81: VRK - PROD Feedback: 9-Jun-2026 | D81: Dual approval mechanism - current logic and recommendation to enable as per the current CRM hierarchy | E81: Pre-PROD | F81: Milestone 6 | G81: 09-Jun-2026 | H81: 03-Aug-2026 | I81: Jagadeesh
A82: 🗓 No ETA assigned · 1 item
A83: 68 | B83: iWork - CR | C83: VRK - PROD Feedback: 13-Jul-2026 | D83: Dashboard Issues - Organization-wise summary cards are not required. | E83: Not in scope | F83: Milestone 6 | G83: 13-Jul-2026 | J83: Madhav sir confirmed via Teams Chat

Sheet SOW - Actual Items
A1: Module | B1: Functionality | C1: Module | D1: Module | E1: Match Status | F1: Refer to "SOW, Feedbacks-Bug & CR_Items"
A2: UI Approach Style Establishment | B2: UI Style Establishment | C2: Framework | D2: Milestone 1 | E2: ✓ Found in tracker
A3: UI Approach Design System | B3: Building Design System | C3: Framework | D3: Milestone 1 | E3: ✓ Found in tracker
A4: Project setup | B4: Basic project / Development environment setup | C4: Framework | D4: Milestone 1 | E4: ✓ Found in tracker
A5: Build UI components | B5: This includes all the UI componnets to compose the application and module definitions: Form, Toast, Filter, Cards, Visualisation, Grid, Menu, Header, Footer, Maps Integration | C5: Framework | D5: Milestone 1 | E5: ✓ Found in tracker
A6: Core System | C6: Framework | D6: Milestone 1 | E6: ✓ Found in tracker
A7: ACL & RBAC Control Framework | C7: Framework | D7: Milestone 1 | E7: ✓ Found in tracker
A8: Micro Frontend Setup | C8: Framework | D8: Milestone 1 | E8: ✓ Found in tracker
A9: Service Workers Implementation | C9: Framework | D9: Milestone 1 | E9: ✓ Found in tracker
A10: Landing Page | C10: Framework | D10: Milestone 1 | E10: ✓ Found in tracker
A11: Access Control Management | C11: Framework | D11: Milestone 1 | E11: ✓ Found in tracker
A12: Auth Module (Simple Auth) | C12: Framework | D12: Milestone 1 | E12: ✓ Found in tracker
A13: Micro Service Framework Setup | C13: Framework | D13: Milestone 1 | E13: ✓ Found in tracker
A14: Company (Prospect) Hub | B14: Top 10/Latest companies, with search/filter, Table of basic attributes with GPS etc. | C14: iWork | D14: Milestone 1 | E14: ✓ Found in tracker
A15: Add/View/Edit Company | B15: Large form with basic format based validations, some mandatory fields, multiple addresses, couple of Rich Text Editor fields; Some multi-line fields (e.g., GST), uploads; Duplicate detection on Company name, GST/PAN etc. Simple edit like Add; View is multiple widgets (Contacts, Opportunities, Policies, Claims, SLAs, Document list) | C15: iWork | D15: Milestone 1 | E15: ✓ Found in tracker
A16: Contact Hub | B16: Top 10/Latest Contacts, with search/filter, list with basic attributes | C16: iWork | D16: Milestone 1 | E16: ✓ Found in tracker
A17: Add/View/Edit Contact | B17: Simple edit like Add Contacts should maintain Company history although only 1 Company active with 1 contact; Medium size form with fields, linked in connect | C17: iWork | D17: Milestone 1 | E17: ✓ Found in tracker
A18: Opportunity Hub | B18: Top Opportunities with search/filter, List of opportunities with high level summaries | C18: iWork | D18: Milestone 1 | E18: ✓ Found in tracker
A19: Add/View/Edit Opportunity | B19: Add Medium size form with 1->N list of Claims; Multiple drop downs Large View with several widgets, Simple Edit | C19: iWork | D19: Milestone 1 | E19: ✓ Found in tracker
A20: Insurer/TPA Hub | B20: List with Filter/Search | C20: iWork | D20: Milestone 1 | E20: ✓ Found in tracker
A21: Manage TPA/Insurer | B21: Basic Add, View with edit of basic data, with lists of policies/companies | C21: iWork | D21: Milestone 1 | E21: ✓ Found in tracker
A22: Contact /Company/Insurer/TPA Mgmt | C22: iWork | D22: Milestone 1 | E22: ✓ Found in tracker
A23: Task Mgmt | C23: iWork | D23: Milestone 1 | E23: ✓ Found in tracker
A24: Meeting Mgmt | C24: iWork | D24: Milestone 1 | E24: ✓ Found in tracker
A25: Employee Mgmt | C25: iWork | D25: Milestone 1 | E25: ✓ Found in tracker
A26: RBAC and ACL setup for Iwork Module | C26: iWork | D26: Milestone 1 | E26: ✓ Found in tracker
A27: Opportunity Mgmt | C27: iWork | D27: Milestone 1 | E27: ✓ Found in tracker
A28: Common - Audit Trail Mgmt - Becomes critical in this phase iteself | C28: iWork | D28: Milestone 1 | E28: ✓ Found in tracker
A29: Visualization framework | B29: Charts and KPIs | C29: Framework | D29: Milestone 2 | E29: ✓ Found in tracker
A30: Visualization framework (mobile) | B30: Charts and KPIs | C30: Framework | D30: Milestone 2 | E30: 🔗 Mapped (see note) | F30: Map to line number 35 in Sheet-SOW, Feedbacks-Bug & CR_Items
A31: User Management | C31: Framework | D31: Milestone 2 | E31: ✓ Found in tracker
A32: Notifications Management | C32: Framework | D32: Milestone 2 | E32: ✓ Found in tracker
A33: Document Management | B33: Create, Upload, Seach, Download | C33: Framework | D33: Milestone 2 | E33: ✓ Found in tracker
A34: Document Management (Mobile) | B34: Create, Upload, Seach, Download | C34: Framework | D34: Milestone 2 | E34: 🔗 Mapped (see note) | F34: Map to line number 36 in Sheet-SOW, Feedbacks-Bug & CR_Items
A35: Caching of API Data | C35: Framework | D35: Milestone 2 | E35: ✓ Found in tracker
A36: Caching of API Data (Mobile) | C36: Framework | D36: Milestone 2 | E36: 🔗 Mapped (see note) | F36: Map to line number 37 in Sheet-SOW, Feedbacks-Bug & CR_Items
A37: Master Data Management | C37: Framework | D37: Milestone 2 | E37: ✓ Found in tracker
A38: User Management | C38: Framework | D38: Milestone 2 | E38: ✓ Found in tracker
A39: Notification and Communication Management | C39: Framework | D39: Milestone 2 | E39: ✓ Found in tracker
A40: Audit Data Capturing | C40: Framework | D40: Milestone 2 | E40: ✓ Found in tracker
A41: Usage Tracking System | C41: Framework | D41: Milestone 2 | E41: 🔗 Mapped (see note) | F41: Map to line number 41 in Sheet-SOW, Feedbacks-Bug & CR_Items
A42: CMS | C42: Framework | D42: Milestone 2 | E42: ✓ Found in tracker
A43: Data Security Considerations | B43: Data ca n be accessed only through the APIs and in the same network Database can be accessed on through Jumphost Database access is based on privilages | C43: Framework | D43: Milestone 2 | E43: ✓ Found in tracker
A44: Dashboard | B44: Multiple KPI Cards: Business Performance, Svc Performance, Table of targets vs. actuals vs. lost, Sales Funnel, Renewal Funnel, Servce Funnel, AR from Insurers, Pending Activities(iWork Stages) Widget, Followups widget, Meetings widget Filters available (Geo, Branch, Team/Team Member, Dates), Approvals, iWork Stages, Tasks, Meetings | C44: iWork | D44: Milestone 2 | E44: ✓ Found in tracker
A45: Dashboard - Drilldowns | B45: Drill down from the Tables (Targets vs. Actuals, Pending Activities, Followups, AR Report, Schedule) | C45: iWork | D45: Milestone 2 | E45: ✓ Found in tracker
A46: Dashboard - Pending tasks, approvals | B46: Pending tasks/approvals, | C46: iWork | D46: Milestone 2 | E46: ✓ Found in tracker
A47: Manage Stage Planning/Performance/Approval | B47: Add iWork Stages (table) - Dates with each iWork Stage and who are the team members assigned to each Stage; Once all iWork stages are complete, ISG Team activities must be planned ISG Team can approve/reject each iWork Stage. Approving RFP Stage approves all iWork stages Completion of each iWork Stage (Activity) & ISG Stage - Comments, Attach Document, Date recorded, submit | C47: iWork | D47: Milestone 2 | E47: ✓ Found in tracker
A48: Sales Team Hierarchy | B48: Hierarchy / Org chart tied to Platform Users | C48: iWork | D48: Milestone 2 | E48: ✓ Found in tracker
A49: View Policy | B49: Long View, multiple widgets/entities, endorsements (each month), Claims, etc. | C49: iWork | D49: Milestone 2 | E49: ✓ Found in tracker
A50: Common Data Mapping Component | B50: Map input fields to output fields & Order | C50: iWork | D50: Milestone 2 | E50: ✓ Found in tracker
A51: Reports - Biz Done | B51: Report View, Download, List of earlier snaps of the report, Search and Filter | C51: iWork | D51: Milestone 2 | E51: ✓ Found in tracker
A52: Smart Add Component | B52: Allow Upload of Document/Image, select what to create (Company/Contact/Opportunity) | C52: iWork | D52: Milestone 2 | E52: ✓ Found in tracker
A53: Organisation, Branch, Employee, & Hierarchy Mgmt | C53: iWork | D53: Milestone 2 | E53: ✓ Found in tracker
A54: Cut Off Mgmt | C54: iWork | D54: Milestone 2 | E54: ✓ Found in tracker
A55: Dashboard (Place Holder) | C55: iWork | D55: Milestone 2 | E55: ✓ Found in tracker
A56: Planning, Perform and Approval Mgmt | C56: iWork | D56: Milestone 2 | E56: ✓ Found in tracker
A57: Policy Mgmt | C57: iWork | D57: Milestone 2 | E57: ✓ Found in tracker
A58: AI - (Non-OCR) Digital Document Processing for Content recognition (Company/Opportunity/Contact Creation from Previous Policy Document, Bizcard document) | C58: iWork | D58: Milestone 2 | E58: ✓ Found in tracker
A59: AI - OCR for Content Collection | C59: iWork | D59: Milestone 2 | E59: ✓ Found in tracker
A60: AI - Company Information by AI Search | C60: iWork | D60: Milestone 2 | E60: ✓ Found in tracker
A61: Common, Contexual Upload Component | C61: iWork | D61: Milestone 2 | E61: ✓ Found in tracker
A62: Common, Contexual Read and Spread Component | C62: iWork | D62: Milestone 2 | E62: 🔗 Mapped (see note) | F62: Map to line number 47 in Sheet-SOW, Feedbacks-Bug & CR_Items
A63: HR/Admin Portal View | B63: Supporting services for Admin Portal | C63: IBP | D63: Milestone 2 | E63: ✓ Found in tracker
A64: Document Generation | C64: Framework | D64: Milestone 3 | E64: ✓ Found in tracker
A65: Manage Policy (Endorsements) | B65: Add Endorsement - basic form with uploads of excel/document Validations of endorsement format - Map customer fields to internal fields Map internal fields to TPA fields (occasional per TPA) View/Update Endorsement, List View, Endorsement Performance | C65: iWork | D65: Milestone 3 | E65: ✓ Found in tracker
A66: MIR Entry Mgmt | B66: Entry Form, Print to Document, List of Earlier MIRs, Search on MIRs | C66: iWork | D66: Milestone 3 | E66: ✓ Found in tracker
A67: Master Data Mgmt {Common, Contexual Master Data Mgmt} | C67: iWork | D67: Milestone 3 | E67: ✓ Found in tracker
A68: Stage Mgmt (Activity/Transaction/Quote) | C68: iWork | D68: Milestone 3 | E68: ✓ Found in tracker
A69: Asset/Member Data Mgmt | C69: iWork | D69: Milestone 3 | E69: ✓ Found in tracker
A70: Cover Mgmt | C70: iWork | D70: Milestone 3 | E70: ✓ Found in tracker
A71: Endorsement Mgmt | C71: iWork | D71: Milestone 3 | E71: ✓ Found in tracker
A72: MIR Entry Mgmt | B72: Module to manage MIR {Monthly Information Report} | C72: iWork | D72: Milestone 3 | E72: ✓ Found in tracker
A73: Accessibility | C73: Framework | D73: Milestone 4 | E73: ✓ Found in tracker
A74: Localisation | C74: Framework | D74: Milestone 4 | E74: ✓ Found in tracker
A75: Configuration Management | C75: Framework | D75: Milestone 4 | E75: ✓ Found in tracker
A76: Feature Flag Control Management | C76: Framework | D76: Milestone 4 | E76: ✓ Found in tracker
A77: Workflow Management | C77: Framework | D77: Milestone 4 | E77: ✓ Found in tracker
A78: Rule Definition Management | C78: Framework | D78: Milestone 4 | E78: ✓ Found in tracker
A79: Caching Implementation | C79: Framework | D79: Milestone 4 | E79: ✓ Found in tracker
A80: Localistation Management | C80: Framework | D80: Milestone 4 | E80: ✓ Found in tracker
A81: Knowledge Central | B81: Grouped list of Documents/Resources, Add a Document, Remove a Document (Add/remove only for admins) | C81: iWork | D81: Milestone 4 | E81: ✓ Found in tracker
A82: View Service Score | B82: Servicing Stats Dashboard - Single Table (drillable) to calculate an overall score | C82: iWork | D82: Milestone 4 | E82: ✓ Found in tracker
A83: Knowledge Central | C83: iWork | D83: Milestone 4 | E83: ✓ Found in tracker
A84: TAT/SLA Mgmt (Including Service Score) | C84: iWork | D84: Milestone 4 | E84: ✓ Found in tracker
A85: Country Handling {Data Source Mgmt} | B85: Physical data storage is limiited to a particular country and can't be combined with other country data | C85: iWork | D85: Milestone 4 | E85: 🔗 Mapped (see note) | F85: Map to line number 115 in Sheet-SOW, Feedbacks-Bug & CR_Items
A86: Archived Oppurtunity, Policy Mgmt {Archived Biz Data and Retrieval on need} | C86: iWork | D86: Milestone 4 | E86: 🔗 Mapped (see note) | F86: Map to line number 71 in Sheet-SOW, Feedbacks-Bug & CR_Items
A87: IBP Landing Page - Basic | B87: Basic Landing Page with only company plans and summary | C87: IBP | D87: Milestone 4 | E87: ✓ Found in tracker
A88: My Insurance | B88: Hub of all plans I have as an employee - both Company provided and individually signed up. Mostly a navigational page | C88: IBP | D88: Milestone 4 | E88: ✓ Found in tracker
A89: Company Plans | B89: 6 Policies - GMC, GPA, GTL, Parental Plicy, Top-ups, OPD Policy (Summary view of policies | C89: IBP | D89: Milestone 4 | E89: ✓ Found in tracker
A90: Per-policy Enrolment | B90: Enrolment and addon policy selection | C90: IBP | D90: Milestone 4 | E90: ✓ Found in tracker
A91: Company Plan Configurator | B91: Admin side of IBP should configure (per Corporate) how to define a Policy and determine how it breaks down the Premium and Coverage rules | C91: IBP/iWork | D91: Milestone 4 | E91: ✓ Found in tracker
A92: My Documents | B92: Document Hub - covers Policies, Prescriptions, Reports | C92: IBP | D92: Milestone 4 | E92: ✓ Found in tracker
A93: User Profile | B93: Profile, Service Subscriptions, Feedback | C93: IBP | D93: Milestone 4 | E93: ✓ Found in tracker
A94: Whitelabelling | B94: Whitelabelling based on Org needs (IBP Admin) | C94: IBP/iWork | D94: Milestone 4 | E94: ✓ Found in tracker
A95: Contact Matrix | B95: Configure the Conact Info Matrix (IBP Admin) | C95: IBP/iWork | D95: Milestone 4 | E95: ✓ Found in tracker
A96: Contact Matrix View | B96: Contact Matrix View for end user | C96: IBP | D96: Milestone 4 | E96: ✓ Found in tracker
A97: Auth Config UI | B97: Config for Auth Rules setup | C97: IBP/iWork | D97: Milestone 4 | E97: ✓ Found in tracker
A98: Wellness Discount List Management | B98: Add/Remove/update Discount program benefits | C98: IBP/iWork | D98: Milestone 4 | E98: ✓ Found in tracker | F98: Map to line number 126 in Sheet-SOW, Feedbacks-Bug & CR_Items
A99: HR Portal View | B99: Employee Search, Resend Email, Update Employee Info, Delete Employees, Extend Enrollment Windows, Reports, Bulk Email | C99: IBP | D99: Milestone 4 | E99: ✓ Found in tracker
A100: Basic Landing Page Services | B100: Company provided plans only | C100: IBP | D100: Milestone 4 | E100: ✓ Found in tracker
...

Sheet Stablization Items
A1: List of Stabilization Items
A2: Sl. # | B2: Module | C2: Sub-Module | D2: Item | E2: Efforts (Hrs.) | F2: Assigned To | G2: Status | H2: Start Date | I2: End Date | J2: Requested Date
A3: 1 | B3: BizDone | D3: Offload Excel Generation: Disconnect report generation from HTTP requests to prevent timeout issues. Use an asynchronous thread or long polling for status updates and file downloading.
B4: BizDone | C4: 1-A | D4: API Tweaks for making data request | E4: 2 | F4: Sunil | G4: Yet to start | H4: 46237 | I4: 46237 | J4: 46234
B5: BizDone | D5: Implementing queue / query building | E5: 10 | F5: Sunil | G5: Yet to start | H5: 46237 | I5: 46238 | J5: 46234
B6: BizDone | D6: Tweaks / Update Procees the data onto file and store / upload to storage | E6: 8 | F6: Sunil | G6: Yet to start | H6: 46238 | I6: 46239 | J6: 46234
B7: BizDone | D7: Long Poling Implementation for Bizdone Download - Front End | E7: 4 | F7: Sunil | G7: Yet to start | H7: 46239 | I7: 46239 | J7: 46234
B8: BizDone | C8: 1-B | D8: Query Tuning for Binzdone Query, Dashboard Performances | E8: 16 | F8: Abhilash | G8: Yet to start | H8: 46237 | I8: 46238 | J8: 46234
B9: Dashboard | C9: 1-C | D9: Implementation of the dynamic fetching of the dashboard widgets data without depending on performance output cron job | E9: 8 | F9: Ravi | G9: DEV - WIP | H9: 46237 | I9: 46237 | J9: 46234
B10: Dashboard | D10: Centralised code or util function to fetch the KPIs in biz done report and dashboard data for re-usability | E10: 16 | F10: Ravi | G10: Yet to start | H10: 46238 | I10: 46239 | J10: 46234
B11: BizDone | C11: 1-D | D11: Migration Data load Should be always complete only Performances Job Execution - Continous acitivity | E11: 0 | F11: Rama | G11: Yet to start | H11: 46237 | I11: 46237 | J11: 46234
A12: 2 | B12: Dashboard | D12: Having individual component loaders on the landing page for each component and web-socket framework to avoid long-loading blank page issue. | G12: Yet to start | J12: 46234
A13: 3 | B13: Jobs | D13: Process Jobs - Review, Enhance and document
B14: Jobs | C14: 3-A | D14: Job - Expiry Opportunity - Review and Enhance
B15: Jobs | C15: 3-B | D15: Job - Opportunity Creation - Review and Enhance
B16: Jobs | C16: 3-C | D16: Job - Dashboard
B17: Jobs | C17: 3-D
B18: Jobs | C18: 3-E
B19: Jobs | C19: 3-F
B20: Jobs | C20: 3-G
B21: Jobs | C21: 3-H
A22: 4
A23: 5
A24: 6
A25: 7
A26: 8
A27: 9
A28: 10

Sheet Jira Report
A1: Sl. # | B1: Jira ID | C1: Issue Type | D1: Summary | E1: Status | F1: Reporter | G1: Product | H1: Parent

Sheet Helper
A1: Module | B1: Phase | C1: Status | D1: Category | E1: Bucket | F1: ReqDate
A2: ='SOW, Feedbacks-Bug & CR_Items'!D2 -> Framework | B2: ='SOW, Feedbacks-Bug & CR_Items'!E2 -> Milestone 1 | C2: ='SOW, Feedbacks-Bug & CR_Items'!F2 -> Delivered | D2: =IFERROR(VLOOKUP(C2,Config!$A:$B,2,0),"Unknown") -> Delivered | E2: =IFERROR(VLOOKUP(C2,Config!$A:$C,3,0),"N/A") -> Delivered | F2: =IF('SOW, Feedbacks-Bug & CR_Items'!H2="","",'SOW, Feedbacks-Bug & CR_Items'!H2) -> 45717
A3: ='SOW, Feedbacks-Bug & CR_Items'!D3 -> Framework | B3: ='SOW, Feedbacks-Bug & CR_Items'!E3 -> Milestone 1 | C3: ='SOW, Feedbacks-Bug & CR_Items'!F3 -> Delivered | D3: =IFERROR(VLOOKUP(C3,Config!$A:$B,2,0),"Unknown") -> Delivered | E3: =IFERROR(VLOOKUP(C3,Config!$A:$C,3,0),"N/A") -> Delivered | F3: =IF('SOW, Feedbacks-Bug & CR_Items'!H3="","",'SOW, Feedbacks-Bug & CR_Items'!H3) -> 45717
A4: ='SOW, Feedbacks-Bug & CR_Items'!D4 -> Framework | B4: ='SOW, Feedbacks-Bug & CR_Items'!E4 -> Milestone 1 | C4: ='SOW, Feedbacks-Bug & CR_Items'!F4 -> Delivered | D4: =IFERROR(VLOOKUP(C4,Config!$A:$B,2,0),"Unknown") -> Delivered | E4: =IFERROR(VLOOKUP(C4,Config!$A:$C,3,0),"N/A") -> Delivered | F4: =IF('SOW, Feedbacks-Bug & CR_Items'!H4="","",'SOW, Feedbacks-Bug & CR_Items'!H4) -> 45717
A5: ='SOW, Feedbacks-Bug & CR_Items'!D5 -> Framework | B5: ='SOW, Feedbacks-Bug & CR_Items'!E5 -> Milestone 1 | C5: ='SOW, Feedbacks-Bug & CR_Items'!F5 -> Delivered | D5: =IFERROR(VLOOKUP(C5,Config!$A:$B,2,0),"Unknown") -> Delivered | E5: =IFERROR(VLOOKUP(C5,Config!$A:$C,3,0),"N/A") -> Delivered | F5: =IF('SOW, Feedbacks-Bug & CR_Items'!H5="","",'SOW, Feedbacks-Bug & CR_Items'!H5) -> 45717
A6: ='SOW, Feedbacks-Bug & CR_Items'!D6 -> Framework | B6: ='SOW, Feedbacks-Bug & CR_Items'!E6 -> Milestone 1 | C6: ='SOW, Feedbacks-Bug & CR_Items'!F6 -> Delivered | D6: =IFERROR(VLOOKUP(C6,Config!$A:$B,2,0),"Unknown") -> Delivered | E6: =IFERROR(VLOOKUP(C6,Config!$A:$C,3,0),"N/A") -> Delivered | F6: =IF('SOW, Feedbacks-Bug & CR_Items'!H6="","",'SOW, Feedbacks-Bug & CR_Items'!H6) -> 45717
A7: ='SOW, Feedbacks-Bug & CR_Items'!D7 -> Framework | B7: ='SOW, Feedbacks-Bug & CR_Items'!E7 -> Milestone 1 | C7: ='SOW, Feedbacks-Bug & CR_Items'!F7 -> Delivered | D7: =IFERROR(VLOOKUP(C7,Config!$A:$B,2,0),"Unknown") -> Delivered | E7: =IFERROR(VLOOKUP(C7,Config!$A:$C,3,0),"N/A") -> Delivered | F7: =IF('SOW, Feedbacks-Bug & CR_Items'!H7="","",'SOW, Feedbacks-Bug & CR_Items'!H7) -> 45717
A8: ='SOW, Feedbacks-Bug & CR_Items'!D8 -> Framework | B8: ='SOW, Feedbacks-Bug & CR_Items'!E8 -> Milestone 1 | C8: ='SOW, Feedbacks-Bug & CR_Items'!F8 -> Delivered | D8: =IFERROR(VLOOKUP(C8,Config!$A:$B,2,0),"Unknown") -> Delivered | E8: =IFERROR(VLOOKUP(C8,Config!$A:$C,3,0),"N/A") -> Delivered | F8: =IF('SOW, Feedbacks-Bug & CR_Items'!H8="","",'SOW, Feedbacks-Bug & CR_Items'!H8) -> 45717
A9: ='SOW, Feedbacks-Bug & CR_Items'!D9 -> Framework | B9: ='SOW, Feedbacks-Bug & CR_Items'!E9 -> Milestone 1 | C9: ='SOW, Feedbacks-Bug & CR_Items'!F9 -> Delivered | D9: =IFERROR(VLOOKUP(C9,Config!$A:$B,2,0),"Unknown") -> Delivered | E9: =IFERROR(VLOOKUP(C9,Config!$A:$C,3,0),"N/A") -> Delivered | F9: =IF('SOW, Feedbacks-Bug & CR_Items'!H9="","",'SOW, Feedbacks-Bug & CR_Items'!H9) -> 45717
A10: ='SOW, Feedbacks-Bug & CR_Items'!D10 -> Framework | B10: ='SOW, Feedbacks-Bug & CR_Items'!E10 -> Milestone 1 | C10: ='SOW, Feedbacks-Bug & CR_Items'!F10 -> Delivered | D10: =IFERROR(VLOOKUP(C10,Config!$A:$B,2,0),"Unknown") -> Delivered | E10: =IFERROR(VLOOKUP(C10,Config!$A:$C,3,0),"N/A") -> Delivered | F10: =IF('SOW, Feedbacks-Bug & CR_Items'!H10="","",'SOW, Feedbacks-Bug & CR_Items'!H10) -> 45717
A11: ='SOW, Feedbacks-Bug & CR_Items'!D11 -> Framework | B11: ='SOW, Feedbacks-Bug & CR_Items'!E11 -> Milestone 1 | C11: ='SOW, Feedbacks-Bug & CR_Items'!F11 -> Delivered | D11: =IFERROR(VLOOKUP(C11,Config!$A:$B,2,0),"Unknown") -> Delivered | E11: =IFERROR(VLOOKUP(C11,Config!$A:$C,3,0),"N/A") -> Delivered | F11: =IF('SOW, Feedbacks-Bug & CR_Items'!H11="","",'SOW, Feedbacks-Bug & CR_Items'!H11) -> 45717
A12: ='SOW, Feedbacks-Bug & CR_Items'!D12 -> Framework | B12: ='SOW, Feedbacks-Bug & CR_Items'!E12 -> Milestone 1 | C12: ='SOW, Feedbacks-Bug & CR_Items'!F12 -> Delivered | D12: =IFERROR(VLOOKUP(C12,Config!$A:$B,2,0),"Unknown") -> Delivered | E12: =IFERROR(VLOOKUP(C12,Config!$A:$C,3,0),"N/A") -> Delivered | F12: =IF('SOW, Feedbacks-Bug & CR_Items'!H12="","",'SOW, Feedbacks-Bug & CR_Items'!H12) -> 45717
A13: ='SOW, Feedbacks-Bug & CR_Items'!D13 -> Framework | B13: ='SOW, Feedbacks-Bug & CR_Items'!E13 -> Milestone 1 | C13: ='SOW, Feedbacks-Bug & CR_Items'!F13 -> Delivered | D13: =IFERROR(VLOOKUP(C13,Config!$A:$B,2,0),"Unknown") -> Delivered | E13: =IFERROR(VLOOKUP(C13,Config!$A:$C,3,0),"N/A") -> Delivered | F13: =IF('SOW, Feedbacks-Bug & CR_Items'!H13="","",'SOW, Feedbacks-Bug & CR_Items'!H13) -> 45717
... A355: ='SOW, Feedbacks-Bug & CR_Items'!D355 -> iWork | B355: ='SOW, Feedbacks-Bug & CR_Items'!E355 -> Milestone 6 | C355: ='SOW, Feedbacks-Bug & CR_Items'!F355 -> Delivered | D355: =IFERROR(VLOOKUP(C355,Config!$A:$B,2,0),"Unknown") -> Delivered | E355: =IFERROR(VLOOKUP(C355,Config!$A:$C,3,0),"N/A") -> Delivered | F355: =IF('SOW, Feedbacks-Bug & CR_Items'!H355="","",'SOW, Feedbacks-Bug & CR_Items'!H355) -> 46233

Sheet Config
A1: Status_Raw | B1: Category | C1: Bucket
A2: Delivered | B2: Delivered | C2: Delivered
A3: Dev - Done | B3: Dev Complete | C3: Delivered
A4: Dev - WIP | B4: In Development | C4: Pending
A5: DEV - WIP | B5: In Development | C5: Pending
A6: QA - WIP | B6: In QA | C6: Pending
A7: Pre-PROD | B7: Pre-PROD / UAT | C7: Pending
A8: Yet to start | B8: Not Started | C8: Pending
A9: Delivered - Deficit | B9: Partial Delivery | C9: Pending
A10: Duplicate | B10: N/A | C10: N/A
A11: Not a bug | B11: Delivered | C11: Delivered
A12: Not in scope | B12: Delivered | C12: Delivered
