Workbook

Sheet SOW, Feedbacks-Bug & CR_Items
A1: Area | B1: Feature | C1: Functionality | D1: Module | E1: Phase | F1: Status | G1: Remarks | H1: Requested Date | I1: ETA | J1: Priority | K1: Start Date | L1: End Date | M1: Resource | N1: Jira ID
A2: Framework: DPDP | B2: Enable SAST | D2: DPDP | E2: Milestone 5 | F2: Delivered | H2: 45869 | I2: 46188
A3: Framework: DPDP | B3: Integrate SSO / MFA | D3: DPDP | E3: Milestone 5 | F3: Delivered | H3: 45869 | I3: 46142
A4: Framework: DPDP | B4: Capture consent within app | D4: DPDP | E4: Milestone 5 | F4: Delivered | H4: 45869 | I4: 46172 | N4: IIRM-8015
A5: Framework: DPDP | B5: Allow easy consent withdrawal | D5: DPDP | E5: Milestone 5 | F5: Delivered | H5: 45869 | I5: 46172 | N5: IIRM-8015
A6: Framework: DPDP | B6: Approval workflow | D6: DPDP | E6: Milestone 5 | F6: Delivered | H6: 45869 | I6: 46172
A7: Framework: DPDP | B7: Show privacy notice with purpose, retention, rights | D7: DPDP | E7: Milestone 5 | F7: Delivered | H7: 45869 | I7: 46172
A8: Framework: DPDP | B8: App vulnerability scans | D8: DPDP | E8: Milestone 5 | F8: DEV - WIP | H8: 45869 | I8: 46241
A9: Framework: DPDP | B9: Document Flows | D9: DPDP | E9: Milestone 5 | F9: DEV - WIP | H9: 45869 | I9: 46241
A10: Framework: DPDP | B10: Perform security UAT | D10: DPDP | E10: Milestone 5 | F10: DEV - WIP | H10: 45869 | I10: 46241
A11: Framework: DPDP | B11: Remove unnecessary fields | D11: DPDP | E11: Milestone 5 | F11: DEV - Done | H11: 45869 | I11: 46241
A12: Framework: DPDP | B12: Enforce business logic to restrict purpose | D12: DPDP | E12: Milestone 5 | F12: DEV - WIP | H12: 45869 | I12: 46241
A13: Framework: DPDP | B13: Allow user corrections | D13: DPDP | E13: Milestone 5 | F13: DEV - WIP | H13: 45869 | I13: 46241 | N13: IIRM-8015
A14: Framework: DPDP | B14: Delete expired data | D14: DPDP | E14: Milestone 5 | F14: DEV - WIP | H14: 45869 | I14: 46241 | N14: IIRM-8015
A15: Framework: DPDP | B15: Map PII tables | D15: DPDP | E15: Milestone 5 | F15: QA - WIP | H15: 45869 | I15: 46241 | M15: Rama
A16: Framework: DPDP | B16: Enable delete pipeline | D16: DPDP | E16: Milestone 5 | F16: Yet to start | H16: 45869 | I16: 46241 | N16: IIRM-8015
A17: Framework: DPDP | B17: Sign DPDP clauses | D17: DPDP | E17: Milestone 5 | F17: DEV - WIP | H17: 45869 | I17: 46241 | N17: IIRM-8015
A18: Framework: DPDP | B18: Quarterly restore tests | D18: DPDP | E18: Milestone 5 | F18: Pre-PROD | H18: 45869 | I18: 46241 | M18: Rama
A19: FRAMEWORK: Frontend | B19: Project setup | C19: Basic project / Development environment setup | D19: Framework | E19: Milestone 1 | F19: Delivered | H19: 45717 | N19: IIRM-17
A20: FRAMEWORK: Frontend | B20: UI Approach Design System | C20: Building Design System | D20: Framework | E20: Milestone 1 | F20: Delivered | H20: 45717 | N20: IIRM-734
A21: FRAMEWORK: Frontend | B21: Core Infrastructure | C21: Core Infra | D21: Framework | E21: Milestone 1 | F21: Delivered | H21: 45717
A22: FRAMEWORK: Frontend | B22: Build UI components | C22: This includes all the UI componnets to compose the application and module definitions: Form, Toast, Filter, Cards, Visualisation, Grid, Menu, Header, Footer, Maps Integration | D22: Framework | E22: Milestone 1 | F22: Delivered | H22: 45717 | N22: IIRM-836
A23: FRAMEWORK: Frontend | B23: UI Approach Style Establishment | C23: UI Style Establishment | D23: Framework | E23: Milestone 1 | F23: Delivered | H23: 45717 | N23: IIRM-838
A24: FRAMEWORK: Frontend | B24: Service Workers Implementation | D24: Framework | E24: Milestone 1 | F24: Delivered | H24: 45717 | N24: IIRM-19
A25: FRAMEWORK: Frontend | B25: Core System | D25: Framework | E25: Milestone 1 | F25: Delivered | H25: 45717 | N25: IIRM-80
A26: FRAMEWORK: Frontend | B26: ACL & RBAC Control Framework | D26: Framework | E26: Milestone 1 | F26: Delivered | H26: 45717 | N26: IIRM-18
A27: FRAMEWORK: Frontend | B27: Micro Frontend Setup | D27: Framework | E27: Milestone 1 | F27: Delivered | H27: 45717 | N27: IIRM-15
A28: FRAMEWORK: Frontend | B28: Landing Page | D28: Framework | E28: Milestone 1 | F28: Delivered | H28: 45717
A29: FRAMEWORK: Frontend | B29: Master Data Management | D29: Framework | E29: Milestone 2 | F29: Delivered | H29: 45763 | I29: 46169 | N29: IIRM-745
A30: FRAMEWORK: Frontend | B30: User Management | C30: 22-May: Other than iWork employee | D30: Framework | E30: Milestone 2 | F30: Delivered | G30: Pending: User deletion | H30: 45763 | I30: 46185 | N30: IIRM-744
A31: FRAMEWORK: Frontend | B31: Visualization framework | C31: Charts and KPIs | D31: Framework | E31: Milestone 2 | F31: Delivered | H31: 45763 | N31: IIRM-743
A32: FRAMEWORK: Frontend | B32: Document Management | C32: Create, Upload, Seach, Download | D32: Framework | E32: Milestone 2 | F32: Delivered | H32: 45763 | N32: IIRM-750
A33: FRAMEWORK: Frontend | B33: Caching of API Data | D33: Framework | E33: Milestone 2 | F33: Delivered | H33: 45763
A34: FRAMEWORK: Frontend | B34: Notifications Management | C34: Different email notification - Madhav excel. 1. Renewal Reminders - ASAP 2. Instalment Reminders 3. Others | D34: Framework | E34: Milestone 4 | F34: Pre-PROD | H34: 45818 | I34: 46237 | M34: Pushyami | N34: IIRM-761, IIRM-4740
A35: FRAMEWORK: Frontend | B35: Accessibility | C35: 20-Jul: Jagadees --> Need More details | D35: Framework | E35: Milestone 4 | F35: Yet to start | H35: 45818 | I35: 46241 | N35: IIRM-763
A36: FRAMEWORK: Frontend | B36: Localisation | D36: Framework | E36: Milestone 4 | F36: Delivered - Deficit | G36: Pending: Service Flow | H36: 45818 | I36: 46241 | M36: Tharun | N36: IIRM-764
A37: Framework: NFR | B37: NFR_Usability | C37: NFR-USA-018: The session management should be configurable from UI 23-May: Configure from UI & store in DB; When changed then restart server | D37: IBP | E37: Milestone 4 | F37: Delivered | H37: 45818 | I37: 46188 | M37: Manjusha | N37: IIRM-9912
A38: Framework: NFR | B38: NFR_Usability | C38: NFR-USA-015: The system must show personalized welcome messages and profile information based on locale. | D38: IBP | E38: Milestone 4 | F38: Delivered | H38: 45818 | N38: IIRM-4477
A39: Framework: NFR | B39: NFR_Usability | C39: NFR-USA-016: Notification banners must be dismissible and configurable based on role. | D39: IBP | E39: Milestone 4 | F39: Delivered | G39: No notifications in IBP | H39: 45818 | N39: IIRM-4478
A40: Framework: NFR | B40: NFR_Usability | C40: NFR-USA-021: Guidelines for document management should be provided | D40: NFR | E40: Milestone 4 | F40: Delivered - Deficit | G40: Pending: Provide the document on how do we store and view it | H40: 45818 | I40: 46241 | M40: Rama | N40: IIRM-4482
A41: Framework: NFR | B41: NFR_Usability | C41: NFR-USA-011: The system should support at least 100 concurrent users without performance degradation. | D41: IBP | E41: Milestone 4 | F41: Pre-PROD | G41: Fine tuning the API's where there is a delay | H41: 45818 | I41: 46241 | M41: Akhila | N41: IIRM-4473
A42: Framework: NFR | B42: NFR-COM-019: Terms and Conditions: The application must ensure require the customer to accept the Terms & Conditions at the first login to the application. This ensures compliance with PII regulations requiring Company group to inform the user of why Company is accessing/collecting personal data and why Company is using it. IIRM-4480 | D42: NFR | E42: Milestone 5 | F42: Delivered | H42: 45869 | I42: 46178 | N42: IIRM-4480
A43: Framework: NFR | B43: NFR-OTH-022: A self-service report generator must be available for dynamic query/report creation. | D43: NFR | E43: Milestone 5 | F43: Yet to start | G43: Discussed this with Surya sir last visit to Divami office | H43: 45869 | I43: 46241 | N43: IIRM-4533
A44: Framework: NFR | B44: NFR-OTH-015: The application must cryptographic Failures, previously known as Sensitive Data Exposure, which was broad symptom rather than a root cause. The renewed focus here is on failures related to cryptography which often leads to sensitive data exposure or system compromise. | D44: NFR | E44: Milestone 5 | F44: DEV - WIP | H44: 45869 | I44: 46241 | N44: IIRM-4526
A45: FRAMEWORK: Services - Basic Modules | B45: Access Control Management | D45: Framework | E45: Milestone 1 | F45: Delivered | H45: 45717 | N45: IIRM-1528
A46: FRAMEWORK: Services - Basic Modules | B46: User Management | C46: 22-May: Other than iWork employee | D46: Framework | E46: Milestone 2 | F46: Delivered | G46: Pending: User deletion | H46: 45763 | I46: 46185 | N46: IIRM-744
A47: FRAMEWORK: Services - Basic Modules | B47: Audit Data Capturing | D47: Framework | E47: Milestone 2 | F47: Delivered | H47: 45763 | N47: IIRM-4613
A48: FRAMEWORK: Services - Basic Modules | B48: Notification and Communication Management | D48: Framework | E48: Milestone 2 | F48: Delivered | H48: 45763 | N48: IIRM-746
A49: FRAMEWORK: Services - Basic Modules | B49: Usage Tracking System (Reports) | C49: 23-May: Handle as a part of Reports | D49: Framework | E49: Milestone 2 | F49: Delivered | H49: 45763
A50: FRAMEWORK: Services - Basic Modules | B50: Configuration Management | D50: Framework | E50: Milestone 4 | F50: Delivered | H50: 45818 | N50: IIRM-762
A51: FRAMEWORK: Services - Basic Modules | B51: Feature Flag Control Management | D51: Framework | E51: Milestone 4 | F51: Delivered | H51: 45818
A52: FRAMEWORK: Services - Larger Modules | B52: Auth Module (Simple Auth) | D52: Framework | E52: Milestone 1 | F52: Delivered | H52: 45717 | N52: IIRM-62
A53: FRAMEWORK: Services - Larger Modules | B53: Micro Service Framework Setup | D53: Framework | E53: Milestone 1 | F53: Delivered | H53: 45717 | N53: IIRM-16, IIRM-834
A54: FRAMEWORK: Services - Larger Modules | B54: Data Security Considerations | D54: Framework | E54: Milestone 2 | F54: Delivered | G54: Duplicate of Covers in DPDP items | H54: 45763 | I54: 46203 | N54: IIRM-749
A55: FRAMEWORK: Services - Larger Modules | B55: CMS | D55: Framework | E55: Milestone 2 | F55: Delivered | G55: Used in IBP | H55: 45763 | N55: IIRM-750
A56: FRAMEWORK: Services - Larger Modules | B56: Document Generation | D56: Framework | E56: Milestone 3 | F56: Delivered | H56: 45793 | N56: IIRM-760
A57: FRAMEWORK: Services - Larger Modules | B57: Localistation Management | D57: Framework | E57: Milestone 4 | F57: Delivered | H57: 45818 | N57: IIRM-764
A58: FRAMEWORK: Services - Larger Modules | B58: Caching Implementation | D58: Framework | E58: Milestone 4 | F58: Delivered | H58: 45818
A59: FRAMEWORK: Services - Larger Modules | B59: Workflow Management | C59: 23-May: Integrate the 3'rd party libraries | D59: Framework | E59: Milestone 4 | F59: Not in scope | G59: 23-Jul-2026: As per Gopal as this system custom and most of the data is driven from Master creating/plug any 3'rd Party will make complex. | H59: 45818 | N59: IIRM-766
A60: FRAMEWORK: Services - Larger Modules | B60: Rule Definition Management | C60: 23-May: Integrate the 3'rd party libraries | D60: Framework | E60: Milestone 4 | F60: Not in scope | G60: 23-Jul-2026: As per Gopal as this system custom and most of the data is driven from Master creating/plug any 3'rd Party will make complex. | H60: 45818 | N60: IIRM-765
A61: IBP: Common Components | B61: Simple Auth | C61: Username and Password based authentication and RBAC on simple-auth users. Auth rules needs configuration capability. IBP - HR User Management | D61: IBP | E61: Milestone 4 | F61: Delivered | H61: 45818 | I61: 46185 | M61: Abhilash
A62: IBP: Common Components | B62: Whitelabelling Support | D62: IBP | E62: Milestone 4 | F62: Delivered | H62: 45818 | N62: IIRM-775
A63: IBP: Common Components | B63: 3rd Party SSO | C63: Props based SSO links to 3rd Parties | D63: IBP | E63: Milestone 5 | F63: Delivered | G63: SSO Framework implemented fro TPA | H63: 45869 | M63: Abhilash | N63: IIRM-10433
A64: IBP: FRONTEND | B64: HR Portal View | C64: Employee Search, Resend Email, Delete Employees, Extend Enrollment Windows, Reports, Bulk Email | D64: IBP | E64: Milestone 4 | F64: Delivered | H64: 45818 | I64: 46184 | M64: Abhilash | N64: IIRM-776
A65: IBP: FRONTEND | B65: My Documents | C65: Document Hub - Covers Policies, Prescriptions, Reports | D65: IBP | E65: Milestone 4 | F65: Delivered | G65: Pending: Design | H65: 45818 | I65: 46185 | M65: Manjusha
A66: IBP: FRONTEND | B66: Policy Document | C66: IBP-Risk Watch: Show the each policy document | D66: IBP | E66: Milestone 4 | F66: Delivered | H66: 45818 | I66: 46192 | M66: Tharun
A67: IBP: FRONTEND | B67: Company Plans | C67: 6 Policies - GMC, GPA, GTL, Parental Plicy, Top-ups, OPD Policy (Summary view of policies) | D67: IBP | E67: Milestone 4 | F67: Delivered | H67: 45818 | N67: IIRM-774
A68: IBP: FRONTEND | B68: IBP Landing Page - Basic | C68: Basic Landing Page with only company plans and summart | D68: IBP | E68: Milestone 4 | F68: Delivered | H68: 45818 | N68: IIRM-771
A69: IBP: FRONTEND | B69: Contact Matrix View | C69: Contact Matrix View for end user | D69: IBP | E69: Milestone 4 | F69: Delivered | H69: 45818 | N69: IIRM-8036
A70: IBP: FRONTEND | B70: Core Infrastructure | C70: Core Infra | D70: IBP | E70: Milestone 4 | F70: Delivered | H70: 45818
A71: IBP: FRONTEND | B71: Per-policy Enrolment | C71: Enrolment and addon policy selection | D71: IBP | E71: Milestone 4 | F71: Delivered | H71: 45818
A72: IBP: FRONTEND | B72: My Insurance | C72: Part-1: Hub of all plans I have as an employee - Company provided. Mostly a navigational page | D72: IBP | E72: Milestone 4 | F72: Delivered | H72: 45818
A73: IBP: FRONTEND | B73: Wellness Discount List Management | C73: Add/Remove/update Discount program benefits | D73: IBP/iWork | E73: Milestone 4 | F73: Pre-PROD | H73: 45818 | I73: 46237
A74: IBP: FRONTEND | B74: Company Plan Configurator | C74: Admin side of IBP should configure (per Corporate) how to define a Policy and determine how it breaks down the Premium and Coverage rules | D74: IBP/iWork | E74: Milestone 4 | F74: Delivered | H74: 45818
A75: IBP: FRONTEND | B75: Auth Config UI | C75: Config for Auth Rules setup | D75: IBP/iWork | E75: Milestone 4 | F75: Delivered | H75: 45818
A76: IBP: FRONTEND | B76: Contact Matrix | C76: Configure the Conact Info Matrix (IBP Admin) | D76: IBP/iWork | E76: Milestone 4 | F76: Delivered | H76: 45818 | N76: IIRM-8036
A77: IBP: FRONTEND | B77: Whitelabelling | C77: Whitelabelling based on Org needs (IBP Admin) | D77: IBP/iWork | E77: Milestone 4 | F77: Delivered | H77: 45818 | N77: IIRM-775
A78: IBP: FRONTEND | B78: Upload from Partner of services bought on Partner site | C78: Upload, listing, confirm & load into DB by an Iwork user. These are services purchased / discounts availed on partner sites by IBP corporate users | D78: IBP/iWork | E78: Milestone 4 | F78: Pre-PROD | H78: 45818 | I78: 46237 | N78: IIRM-793
A79: IBP: FRONTEND | B79: User Profile | C79: Profile, Service Subscriptions, Feedback | D79: IBP | E79: Milestone 5 | F79: Pre-PROD | G79: Pending: Service Subscriptions, Feedback | H79: 45869 | I79: 46237 | M79: Ravi
A80: IBP: FRONTEND | B80: Static Info Sections - Landing | C80: Benefits Guide, FAQs, Help | D80: IBP | E80: Milestone 5 | F80: Delivered | H80: 45869 | N80: IIRM-791
A81: IBP: FRONTEND | B81: Initiate Claim | C81: Initiate claim for GMC (non-cashless), upload docs etc. | D81: IBP | E81: Milestone 5 | F81: Delivered | G81: Pending: TPA & Insurer API integrations | H81: 45869
A82: IBP: FRONTEND | B82: Claims Corner | C82: View Claim Data for Individual Plans (if available), Track Status for Claims initiated from IBP for Group Plans, Track Status for Claims initiated with TPA directly, TAT reporting for Cashless (for Preauth and Discharge) | D82: IBP | E82: Milestone 5 | F82: Delivered | G82: Pending: TPA & Insurer API integrations | H82: 45869 | N82: IIRM-7631
A83: IBP: FRONTEND | B83: IBP Landing Page - Advanced | C83: Advanced Landing Page with individual plans & wellness programs introduced Quick Links, Promotional, high level dashboard, my plans, individual policies, company benefits, etc. Whitelabelling may be required (only Company Logo), but for future, theming may have to be supported | D83: IBP | E83: Milestone 5 | F83: Delivered | H83: 45869
A84: IBP: FRONTEND | B84: Dynamic Info Sections - Landing | C84: Hospital network, Offers and Discounts, Benfits at Glance, Quick Links | D84: IBP | E84: Milestone 5 | F84: Delivered | G84: Pending: Offers & Discuounts | H84: 45869 | I84: 46122 | M84: Manjusha | N84: IIRM-791
A85: IBP: FRONTEND | B85: Basic Wellness Hub | C85: Basic wellness hub - Currently only 3 wellness programs (3rd parties) supported | D85: IBP | E85: Milestone 5 | F85: Pre-PROD | G85: Wellness | H85: 45869 | I85: 46237 | M85: Manjusha | N85: IIRM-784
A86: IBP: FRONTEND | B86: Wellness Admin Configurator | C86: Admin side of IBP (in iWork) needs to customize/configure the offerings/page per Corporate. | D86: IBP/iWork | E86: Milestone 5 | F86: Pre-PROD | H86: 45869 | I86: 46237 | M86: Ravi | N86: IIRM-790
A87: IBP: FRONTEND | B87: Book Ambulance | C87: Floater on the screen - Integrate to Ambulance Service | D87: IBP | E87: Milestone 5 | F87: Not in scope | H87: 45869
A88: IBP: FRONTEND | B88: My Insurance | C88: Part-2: Hub of all plans I have as an employee - individually signed up. Mostly a navigational page | D88: IBP | E88: Milestone 5 | F88: Yet to start | G88: Retail Business | H88: 45869 | I88: 46241 | M88: Ravi
A89: IBP: FRONTEND | B89: Wellness HR View | C89: HR View of Wellness usage by Employees | D89: IBP | E89: Milestone 5 | F89: Yet to start | G89: Wellness | H89: 45869 | I89: 46241 | M89: Manjusha | N89: IIRM-785
A90: IBP: FRONTEND | B90: Wellness Partner View | C90: Partner/service provider view of the usage of their corresponding services | D90: IBP | E90: Milestone 5 | F90: Yet to start | G90: Wellness | H90: 45869 | I90: 46241 | M90: Manjusha
A91: IBP: FRONTEND | B91: Individual Plans | C91: Quotation flow of a new insurance - multple products; quotation ranges after basic data collection; cross-sells and finally an summary page that someone will get back to you. About 7 individual products - could be 4-5 screens in the flow of which 2 screens may be product-specific. | D91: IBP | E91: Milestone 5 | F91: Yet to start | G91: Retail Business | H91: 45869 | I91: 46241 | M91: Ravi | N91: IIRM-788
A92: IBP: FRONTEND | B92: Individual Plan Summary | C92: View of individual Plans currently owned with renewal dates, premiums etc. | D92: IBP | E92: Milestone 5 | F92: Yet to start | G92: Retail Business | H92: 45869 | I92: 46241 | M92: Ravi
A93: IBP: FRONTEND | B93: Profile Migration | C93: Request migration of Corporate Profile to Individual | D93: IBP | E93: Milestone 5 | F93: Yet to start | G93: Retail Business | H93: 45869 | I93: 46241 | M93: Abhilash
A94: IBP: FRONTEND | B94: Profile Migration | C94: Request migration of Individual Profile to Corporate | D94: IBP | E94: Milestone 5 | F94: Yet to start | G94: Retail Business | H94: 45869 | I94: 46241 | M94: Abhilash
A95: IBP: FRONTEND | B95: IBP Landing Page - Customization | C95: Landing Page customization in Admin side of IBP - available in iWork (per Corporate) | D95: IBP/iWork | E95: Milestone 5 | F95: Yet to start | H95: 45869 | N95: IIRM-786
A96: IBP: FRONTEND | B96: Wellness IIRM View | C96: IIRM View of Wellness usage by Corporates/Employees (IBP Admin) | D96: IBP/iWork | E96: Milestone 5 | F96: Yet to start | G96: Wellness HR View | H96: 45869 | I96: 46241 | M96: Manjusha | N96: IIRM-785
A97: IBP: FRONTEND | B97: Chat Interface | C97: Floater on the screen - Integrate with AI Component and IWork support channel | D97: IBP | E97: Milestone 5 | F97: Delivered | H97: 45869 | I97: 46234 | N97: IIRM-789
A98: IBP: Services - AI Components | B98: Chat for End Users | C98: Chat Module to interact with Chat Bot and Customer Support Representative | D98: IBP | E98: Milestone 5 | F98: Delivered | G98: External chatbot integration? | H98: 45869 | I98: 46234 | M98: Abhilash
A99: IBP: SERVICES - Basic Modules | B99: Personal Profile Mgmt | C99: Profile settings | D99: IBP | E99: Milestone 4 | F99: Delivered | G99: Pending:Add Dependents | H99: 45818 | I99: 46183 | M99: Manjusha
A100: IBP: SERVICES - Basic Modules | B100: Document Mgmt for End User | C100: Insurance, Health Reports and Prescriptions {No automatic pull from Partners} | D100: IBP | E100: Milestone 4 | F100: Delivered | G100: Pending: Design | H100: 45818 | I100: 46185 | M100: Manjusha
...

Sheet ① Executive Summary
A1: PROJECT DELIVERY PLAN
A4: iWork · IBP · Framework (IIRM SOW) | Status Overview & Forward Roadmap · As of 07-Aug-2026
A6: OVERALL COMPLETION | H6: REMAINING WORK
A7: =ROUND(COUNTIF(Helper!$E:$E,"Delivered")/(COUNTIF(Helper!$E:$E,"Delivered")+COUNTIF(Helper!$E:$E,"Pending")),3) -> 0.674 | D7: =COUNTIF(Helper!$E:$E,"Delivered")&" of "&(COUNTIF(Helper!$E:$E,"Delivered")+COUNTIF(Helper!$E:$E,"Pending"))&" scope items delivered" -> 287 of 426 scope items delivered | H7: =COUNTIF(Helper!$E:$E,"Pending") -> 139 | J7: items still to deliver across all modules — planned week by week in the weekly sheets
A11: SOW SCOPE — ORIGINAL vs CURRENT ITEMS
A12: Static comparison vs the 'SOW - Actual Items' reference sheet (original contracted scope). Matched by Module + Feature name. Recomputed on each re-run of the script.
A14: Original SOW items | G14: 158
A15: Currently tracked (all items) | G15: 426
A16: — new: DPDP / NFR / Change Requests | G16: 77
A17: — new: organic growth (existing modules) | G17: 199
A18: Net growth vs original SOW (158 → 426) | G18: +268
A19: ⚠ 2 original SOW item(s) still need review — no matching row in the tracker and no mapping note yet.
A20: 🔗 15 item(s) already mapped by hand to a renamed/restructured tracker row — see notes in 'SOW - Actual Items'.
A23: WEEKLY INTAKE — items requested (by Requested Date)
A24: Period | B24: Added | C24: Delivered | D24: Pending | E24: % Closed
A25: Before 01-Jun-2026 | B25: =COUNTIFS(Helper!$F:$F,"<"&DATE(2026,6,1)) -> 210 | C25: =COUNTIFS(Helper!$F:$F,"<"&DATE(2026,6,1),Helper!$E:$E,"Delivered") -> 156 | D25: =COUNTIFS(Helper!$F:$F,"<"&DATE(2026,6,1),Helper!$E:$E,"Pending") -> 54 | E25: =IFERROR(C25/B25,0) -> 0.74285714
A26: Week of 01 Jun 2026 | B26: =COUNTIFS(Helper!$F:$F,">="&DATE(2026,6,1),Helper!$F:$F,"<="&DATE(2026,6,7)) -> 5 | C26: =COUNTIFS(Helper!$F:$F,">="&DATE(2026,6,1),Helper!$F:$F,"<="&DATE(2026,6,7),Helper!$E:$E,"Delivered") -> 5 | D26: =COUNTIFS(Helper!$F:$F,">="&DATE(2026,6,1),Helper!$F:$F,"<="&DATE(2026,6,7),Helper!$E:$E,"Pending") -> 0 | E26: =IFERROR(C26/B26,0) -> 1
A27: Week of 08 Jun 2026 | B27: =COUNTIFS(Helper!$F:$F,">="&DATE(2026,6,8),Helper!$F:$F,"<="&DATE(2026,6,14)) -> 43 | C27: =COUNTIFS(Helper!$F:$F,">="&DATE(2026,6,8),Helper!$F:$F,"<="&DATE(2026,6,14),Helper!$E:$E,"Delivered") -> 42 | D27: =COUNTIFS(Helper!$F:$F,">="&DATE(2026,6,8),Helper!$F:$F,"<="&DATE(2026,6,14),Helper!$E:$E,"Pending") -> 1 | E27: =IFERROR(C27/B27,0) -> 0.97674419
A28: Week of 15 Jun 2026 | B28: =COUNTIFS(Helper!$F:$F,">="&DATE(2026,6,15),Helper!$F:$F,"<="&DATE(2026,6,21)) -> 11 | C28: =COUNTIFS(Helper!$F:$F,">="&DATE(2026,6,15),Helper!$F:$F,"<="&DATE(2026,6,21),Helper!$E:$E,"Delivered") -> 5 | D28: =COUNTIFS(Helper!$F:$F,">="&DATE(2026,6,15),Helper!$F:$F,"<="&DATE(2026,6,21),Helper!$E:$E,"Pending") -> 6 | E28: =IFERROR(C28/B28,0) -> 0.45454545
A29: Week of 22 Jun 2026 | B29: =COUNTIFS(Helper!$F:$F,">="&DATE(2026,6,22),Helper!$F:$F,"<="&DATE(2026,6,28)) -> 21 | C29: =COUNTIFS(Helper!$F:$F,">="&DATE(2026,6,22),Helper!$F:$F,"<="&DATE(2026,6,28),Helper!$E:$E,"Delivered") -> 15 | D29: =COUNTIFS(Helper!$F:$F,">="&DATE(2026,6,22),Helper!$F:$F,"<="&DATE(2026,6,28),Helper!$E:$E,"Pending") -> 6 | E29: =IFERROR(C29/B29,0) -> 0.71428571
A30: Week of 29 Jun 2026 | B30: =COUNTIFS(Helper!$F:$F,">="&DATE(2026,6,29),Helper!$F:$F,"<="&DATE(2026,7,5)) -> 5 | C30: =COUNTIFS(Helper!$F:$F,">="&DATE(2026,6,29),Helper!$F:$F,"<="&DATE(2026,7,5),Helper!$E:$E,"Delivered") -> 3 | D30: =COUNTIFS(Helper!$F:$F,">="&DATE(2026,6,29),Helper!$F:$F,"<="&DATE(2026,7,5),Helper!$E:$E,"Pending") -> 2 | E30: =IFERROR(C30/B30,0) -> 0.6
A31: Week of 06 Jul 2026 | B31: =COUNTIFS(Helper!$F:$F,">="&DATE(2026,7,6),Helper!$F:$F,"<="&DATE(2026,7,12)) -> 8 | C31: =COUNTIFS(Helper!$F:$F,">="&DATE(2026,7,6),Helper!$F:$F,"<="&DATE(2026,7,12),Helper!$E:$E,"Delivered") -> 7 | D31: =COUNTIFS(Helper!$F:$F,">="&DATE(2026,7,6),Helper!$F:$F,"<="&DATE(2026,7,12),Helper!$E:$E,"Pending") -> 1 | E31: =IFERROR(C31/B31,0) -> 0.875
A32: Week of 13 Jul 2026 | B32: =COUNTIFS(Helper!$F:$F,">="&DATE(2026,7,13),Helper!$F:$F,"<="&DATE(2026,7,19)) -> 24 | C32: =COUNTIFS(Helper!$F:$F,">="&DATE(2026,7,13),Helper!$F:$F,"<="&DATE(2026,7,19),Helper!$E:$E,"Delivered") -> 19 | D32: =COUNTIFS(Helper!$F:$F,">="&DATE(2026,7,13),Helper!$F:$F,"<="&DATE(2026,7,19),Helper!$E:$E,"Pending") -> 5 | E32: =IFERROR(C32/B32,0) -> 0.79166667
A33: Week of 20 Jul 2026 | B33: =COUNTIFS(Helper!$F:$F,">="&DATE(2026,7,20),Helper!$F:$F,"<="&DATE(2026,7,26)) -> 22 | C33: =COUNTIFS(Helper!$F:$F,">="&DATE(2026,7,20),Helper!$F:$F,"<="&DATE(2026,7,26),Helper!$E:$E,"Delivered") -> 18 | D33: =COUNTIFS(Helper!$F:$F,">="&DATE(2026,7,20),Helper!$F:$F,"<="&DATE(2026,7,26),Helper!$E:$E,"Pending") -> 4 | E33: =IFERROR(C33/B33,0) -> 0.81818182
A34: Week of 27 Jul 2026 — last week | B34: =COUNTIFS(Helper!$F:$F,">="&DATE(2026,7,27),Helper!$F:$F,"<="&DATE(2026,8,2)) -> 58 | C34: =COUNTIFS(Helper!$F:$F,">="&DATE(2026,7,27),Helper!$F:$F,"<="&DATE(2026,8,2),Helper!$E:$E,"Delivered") -> 16 | D34: =COUNTIFS(Helper!$F:$F,">="&DATE(2026,7,27),Helper!$F:$F,"<="&DATE(2026,8,2),Helper!$E:$E,"Pending") -> 42 | E34: =IFERROR(C34/B34,0) -> 0.27586207
A35: Week of 03 Aug 2026 — this week | B35: =COUNTIFS(Helper!$F:$F,">="&DATE(2026,8,3),Helper!$F:$F,"<="&DATE(2026,8,9)) -> 19 | C35: =COUNTIFS(Helper!$F:$F,">="&DATE(2026,8,3),Helper!$F:$F,"<="&DATE(2026,8,9),Helper!$E:$E,"Delivered") -> 1 | D35: =COUNTIFS(Helper!$F:$F,">="&DATE(2026,8,3),Helper!$F:$F,"<="&DATE(2026,8,9),Helper!$E:$E,"Pending") -> 18 | E35: =IFERROR(C35/B35,0) -> 0.052631579
A36: Requested ahead (after 09 Aug) | B36: =COUNTIFS(Helper!$F:$F,">"&DATE(2026,8,9)) -> 0 | C36: =COUNTIFS(Helper!$F:$F,">"&DATE(2026,8,9),Helper!$E:$E,"Delivered") -> 0 | D36: =COUNTIFS(Helper!$F:$F,">"&DATE(2026,8,9),Helper!$E:$E,"Pending") -> 0 | E36: =IFERROR(C36/B36,0) -> 0
A37: No Requested Date | B37: =COUNTA(Helper!$C$2:$C$5000)-COUNT(Helper!$F$2:$F$5000) -> 0 | C37: =COUNTIFS(Helper!$F:$F,"",Helper!$E:$E,"Delivered") -> 0 | D37: =COUNTIFS(Helper!$F:$F,"",Helper!$E:$E,"Pending") -> 0 | E37: =IFERROR(C37/B37,0) -> 0
A38: TOTAL | B38: =SUM(B25:B37) -> 426 | C38: =SUM(C25:C37) -> 287 | D38: =SUM(D25:D37) -> 139 | E38: =IFERROR(C38/B38,0) -> 0.67370892
A40: STATUS BREAKDOWN (all items)
A41: =COUNTIF(Helper!$D:$D,"Delivered") -> 281 | D41: =COUNTIF(Helper!$D:$D,"Dev Complete") -> 6 | G41: =COUNTIF(Helper!$D:$D,"In Development") -> 22 | J41: =COUNTIF(Helper!$D:$D,"In QA") -> 4
A42: Delivered | D42: Dev Complete | G42: In Development | J42: In QA
A43: =COUNTIF(Helper!$D:$D,"Pre-PROD / UAT") -> 20 | D43: =COUNTIF(Helper!$D:$D,"Not Started") -> 90 | G43: =COUNTIF(Helper!$D:$D,"Partial Delivery") -> 3 | J43: =COUNTIF(Helper!$D:$D,"N/A") -> 0
A44: Pre-PROD / UAT | D44: Not Started | G44: Partial Delivery | J44: N/A
A46: PROGRESS BY MODULE
A47: Module | B47: Type | C47: Total | D47: Delivered | E47: Pending | F47: N/A | G47: % Complete | H47: Progress
A48: iWork (Backlog) | B48: Backlog | C48: =COUNTIF(Helper!$A:$A,"iWork") -> 212 | D48: =COUNTIFS(Helper!$A:$A,"iWork",Helper!$E:$E,"Delivered") -> 139 | E48: =COUNTIFS(Helper!$A:$A,"iWork",Helper!$E:$E,"Pending") -> 73 | F48: =COUNTIFS(Helper!$A:$A,"iWork",Helper!$E:$E,"N/A") -> 0 | G48: =IFERROR(D48/(D48+E48),0) -> 0.65566038 | H48: =G48 -> 0.65566038
A49: iWork (Change Requests) | B49: Change Request | C49: =COUNTIF(Helper!$A:$A,"iWork - CR") -> 43 | D49: =COUNTIFS(Helper!$A:$A,"iWork - CR",Helper!$E:$E,"Delivered") -> 37 | E49: =COUNTIFS(Helper!$A:$A,"iWork - CR",Helper!$E:$E,"Pending") -> 6 | F49: =COUNTIFS(Helper!$A:$A,"iWork - CR",Helper!$E:$E,"N/A") -> 0 | G49: =IFERROR(D49/(D49+E49),0) -> 0.86046512 | H49: =G49 -> 0.86046512
A50: IBP (Backlog) | B50: Backlog | C50: =COUNTIF(Helper!$A:$A,"IBP") -> 71 | D50: =COUNTIFS(Helper!$A:$A,"IBP",Helper!$E:$E,"Delivered") -> 51 | E50: =COUNTIFS(Helper!$A:$A,"IBP",Helper!$E:$E,"Pending") -> 20 | F50: =COUNTIFS(Helper!$A:$A,"IBP",Helper!$E:$E,"N/A") -> 0 | G50: =IFERROR(D50/(D50+E50),0) -> 0.71830986 | H50: =G50 -> 0.71830986
A51: IBP (Change Requests) | B51: Change Request | C51: =COUNTIF(Helper!$A:$A,"IBP - CR") -> 3 | D51: =COUNTIFS(Helper!$A:$A,"IBP - CR",Helper!$E:$E,"Delivered") -> 2 | E51: =COUNTIFS(Helper!$A:$A,"IBP - CR",Helper!$E:$E,"Pending") -> 1 | F51: =COUNTIFS(Helper!$A:$A,"IBP - CR",Helper!$E:$E,"N/A") -> 0 | G51: =IFERROR(D51/(D51+E51),0) -> 0.66666667 | H51: =G51 -> 0.66666667
A52: IBP / iWork (Shared) | B52: Backlog | C52: =COUNTIF(Helper!$A:$A,"IBP/iWork") -> 27 | D52: =COUNTIFS(Helper!$A:$A,"IBP/iWork",Helper!$E:$E,"Delivered") -> 15 | E52: =COUNTIFS(Helper!$A:$A,"IBP/iWork",Helper!$E:$E,"Pending") -> 12 | F52: =COUNTIFS(Helper!$A:$A,"IBP/iWork",Helper!$E:$E,"N/A") -> 0 | G52: =IFERROR(D52/(D52+E52),0) -> 0.55555556 | H52: =G52 -> 0.55555556
A53: IBP / iWork (Shared CRs) | B53: Change Request | C53: =COUNTIF(Helper!$A:$A,"IBP/iWork - CR") -> 9 | D53: =COUNTIFS(Helper!$A:$A,"IBP/iWork - CR",Helper!$E:$E,"Delivered") -> 4 | E53: =COUNTIFS(Helper!$A:$A,"IBP/iWork - CR",Helper!$E:$E,"Pending") -> 5 | F53: =COUNTIFS(Helper!$A:$A,"IBP/iWork - CR",Helper!$E:$E,"N/A") -> 0 | G53: =IFERROR(D53/(D53+E53),0) -> 0.44444444 | H53: =G53 -> 0.44444444
A54: Framework | B54: Backlog | C54: =COUNTIF(Helper!$A:$A,"Framework") -> 34 | D54: =COUNTIFS(Helper!$A:$A,"Framework",Helper!$E:$E,"Delivered") -> 31 | E54: =COUNTIFS(Helper!$A:$A,"Framework",Helper!$E:$E,"Pending") -> 3 | F54: =COUNTIFS(Helper!$A:$A,"Framework",Helper!$E:$E,"N/A") -> 0 | G54: =IFERROR(D54/(D54+E54),0) -> 0.91176471 | H54: =G54 -> 0.91176471
A55: DPDP | B55: Backlog | C55: =COUNTIF(Helper!$A:$A,"DPDP") -> 18 | D55: =COUNTIFS(Helper!$A:$A,"DPDP",Helper!$E:$E,"Delivered") -> 7 | E55: =COUNTIFS(Helper!$A:$A,"DPDP",Helper!$E:$E,"Pending") -> 11 | F55: =COUNTIFS(Helper!$A:$A,"DPDP",Helper!$E:$E,"N/A") -> 0 | G55: =IFERROR(D55/(D55+E55),0) -> 0.38888889 | H55: =G55 -> 0.38888889
A56: NFR | B56: Backlog | C56: =COUNTIF(Helper!$A:$A,"NFR") -> 4 | D56: =COUNTIFS(Helper!$A:$A,"NFR",Helper!$E:$E,"Delivered") -> 1 | E56: =COUNTIFS(Helper!$A:$A,"NFR",Helper!$E:$E,"Pending") -> 3 | F56: =COUNTIFS(Helper!$A:$A,"NFR",Helper!$E:$E,"N/A") -> 0 | G56: =IFERROR(D56/(D56+E56),0) -> 0.25 | H56: =G56 -> 0.25
A57: TOTAL | B57: All | C57: =COUNTA(Helper!$A$2:$A$5000) -> 426 | D57: =COUNTIF(Helper!$E:$E,"Delivered") -> 287 | E57: =COUNTIF(Helper!$E:$E,"Pending") -> 139 | F57: =COUNTIF(Helper!$E:$E,"N/A") -> 0 | G57: =IFERROR(D57/(D57+E57),0) -> 0.67370892 | H57: =G57 -> 0.67370892
A59: PENDING BY MILESTONE & MODULE
A60: Milestone | B60: iWork | C60: iWork - CR | D60: IBP | E60: IBP - CR | F60: IBP/iWork | G60: IBP/iWork - CR | H60: Framework | I60: DPDP | J60: NFR | K60: TOTAL PENDING
A61: Milestone 1 | B61: =COUNTIFS(Helper!$B:$B,"Milestone 1",Helper!$A:$A,"iWork",Helper!$E:$E,"Pending") -> 0 | C61: =COUNTIFS(Helper!$B:$B,"Milestone 1",Helper!$A:$A,"iWork - CR",Helper!$E:$E,"Pending") -> 0 | D61: =COUNTIFS(Helper!$B:$B,"Milestone 1",Helper!$A:$A,"IBP",Helper!$E:$E,"Pending") -> 0 | E61: =COUNTIFS(Helper!$B:$B,"Milestone 1",Helper!$A:$A,"IBP - CR",Helper!$E:$E,"Pending") -> 0 | F61: =COUNTIFS(Helper!$B:$B,"Milestone 1",Helper!$A:$A,"IBP/iWork",Helper!$E:$E,"Pending") -> 0 | G61: =COUNTIFS(Helper!$B:$B,"Milestone 1",Helper!$A:$A,"IBP/iWork - CR",Helper!$E:$E,"Pending") -> 0 | H61: =COUNTIFS(Helper!$B:$B,"Milestone 1",Helper!$A:$A,"Framework",Helper!$E:$E,"Pending") -> 0 | I61: =COUNTIFS(Helper!$B:$B,"Milestone 1",Helper!$A:$A,"DPDP",Helper!$E:$E,"Pending") -> 0 | J61: =COUNTIFS(Helper!$B:$B,"Milestone 1",Helper!$A:$A,"NFR",Helper!$E:$E,"Pending") -> 0 | K61: =SUM(B61:J61) -> 0
A62: Milestone 2 | B62: =COUNTIFS(Helper!$B:$B,"Milestone 2",Helper!$A:$A,"iWork",Helper!$E:$E,"Pending") -> 1 | C62: =COUNTIFS(Helper!$B:$B,"Milestone 2",Helper!$A:$A,"iWork - CR",Helper!$E:$E,"Pending") -> 0 | D62: =COUNTIFS(Helper!$B:$B,"Milestone 2",Helper!$A:$A,"IBP",Helper!$E:$E,"Pending") -> 0 | E62: =COUNTIFS(Helper!$B:$B,"Milestone 2",Helper!$A:$A,"IBP - CR",Helper!$E:$E,"Pending") -> 0 | F62: =COUNTIFS(Helper!$B:$B,"Milestone 2",Helper!$A:$A,"IBP/iWork",Helper!$E:$E,"Pending") -> 0 | G62: =COUNTIFS(Helper!$B:$B,"Milestone 2",Helper!$A:$A,"IBP/iWork - CR",Helper!$E:$E,"Pending") -> 0 | H62: =COUNTIFS(Helper!$B:$B,"Milestone 2",Helper!$A:$A,"Framework",Helper!$E:$E,"Pending") -> 0 | I62: =COUNTIFS(Helper!$B:$B,"Milestone 2",Helper!$A:$A,"DPDP",Helper!$E:$E,"Pending") -> 0 | J62: =COUNTIFS(Helper!$B:$B,"Milestone 2",Helper!$A:$A,"NFR",Helper!$E:$E,"Pending") -> 0 | K62: =SUM(B62:J62) -> 1
A63: Milestone 3 | B63: =COUNTIFS(Helper!$B:$B,"Milestone 3",Helper!$A:$A,"iWork",Helper!$E:$E,"Pending") -> 0 | C63: =COUNTIFS(Helper!$B:$B,"Milestone 3",Helper!$A:$A,"iWork - CR",Helper!$E:$E,"Pending") -> 0 | D63: =COUNTIFS(Helper!$B:$B,"Milestone 3",Helper!$A:$A,"IBP",Helper!$E:$E,"Pending") -> 0 | E63: =COUNTIFS(Helper!$B:$B,"Milestone 3",Helper!$A:$A,"IBP - CR",Helper!$E:$E,"Pending") -> 0 | F63: =COUNTIFS(Helper!$B:$B,"Milestone 3",Helper!$A:$A,"IBP/iWork",Helper!$E:$E,"Pending") -> 0 | G63: =COUNTIFS(Helper!$B:$B,"Milestone 3",Helper!$A:$A,"IBP/iWork - CR",Helper!$E:$E,"Pending") -> 0 | H63: =COUNTIFS(Helper!$B:$B,"Milestone 3",Helper!$A:$A,"Framework",Helper!$E:$E,"Pending") -> 0 | I63: =COUNTIFS(Helper!$B:$B,"Milestone 3",Helper!$A:$A,"DPDP",Helper!$E:$E,"Pending") -> 0 | J63: =COUNTIFS(Helper!$B:$B,"Milestone 3",Helper!$A:$A,"NFR",Helper!$E:$E,"Pending") -> 0 | K63: =SUM(B63:J63) -> 0
A64: Milestone 4 | B64: =COUNTIFS(Helper!$B:$B,"Milestone 4",Helper!$A:$A,"iWork",Helper!$E:$E,"Pending") -> 1 | C64: =COUNTIFS(Helper!$B:$B,"Milestone 4",Helper!$A:$A,"iWork - CR",Helper!$E:$E,"Pending") -> 0 | D64: =COUNTIFS(Helper!$B:$B,"Milestone 4",Helper!$A:$A,"IBP",Helper!$E:$E,"Pending") -> 1 | E64: =COUNTIFS(Helper!$B:$B,"Milestone 4",Helper!$A:$A,"IBP - CR",Helper!$E:$E,"Pending") -> 0 | F64: =COUNTIFS(Helper!$B:$B,"Milestone 4",Helper!$A:$A,"IBP/iWork",Helper!$E:$E,"Pending") -> 3 | G64: =COUNTIFS(Helper!$B:$B,"Milestone 4",Helper!$A:$A,"IBP/iWork - CR",Helper!$E:$E,"Pending") -> 0 | H64: =COUNTIFS(Helper!$B:$B,"Milestone 4",Helper!$A:$A,"Framework",Helper!$E:$E,"Pending") -> 3 | I64: =COUNTIFS(Helper!$B:$B,"Milestone 4",Helper!$A:$A,"DPDP",Helper!$E:$E,"Pending") -> 1 | J64: =COUNTIFS(Helper!$B:$B,"Milestone 4",Helper!$A:$A,"NFR",Helper!$E:$E,"Pending") -> 1 | K64: =SUM(B64:J64) -> 10
A65: Milestone 5 | B65: =COUNTIFS(Helper!$B:$B,"Milestone 5",Helper!$A:$A,"iWork",Helper!$E:$E,"Pending") -> 5 | C65: =COUNTIFS(Helper!$B:$B,"Milestone 5",Helper!$A:$A,"iWork - CR",Helper!$E:$E,"Pending") -> 0 | D65: =COUNTIFS(Helper!$B:$B,"Milestone 5",Helper!$A:$A,"IBP",Helper!$E:$E,"Pending") -> 16 | E65: =COUNTIFS(Helper!$B:$B,"Milestone 5",Helper!$A:$A,"IBP - CR",Helper!$E:$E,"Pending") -> 0 | F65: =COUNTIFS(Helper!$B:$B,"Milestone 5",Helper!$A:$A,"IBP/iWork",Helper!$E:$E,"Pending") -> 4 | G65: =COUNTIFS(Helper!$B:$B,"Milestone 5",Helper!$A:$A,"IBP/iWork - CR",Helper!$E:$E,"Pending") -> 0 | H65: =COUNTIFS(Helper!$B:$B,"Milestone 5",Helper!$A:$A,"Framework",Helper!$E:$E,"Pending") -> 0 | I65: =COUNTIFS(Helper!$B:$B,"Milestone 5",Helper!$A:$A,"DPDP",Helper!$E:$E,"Pending") -> 10 | J65: =COUNTIFS(Helper!$B:$B,"Milestone 5",Helper!$A:$A,"NFR",Helper!$E:$E,"Pending") -> 2 | K65: =SUM(B65:J65) -> 37
A66: Milestone 6 | B66: =COUNTIFS(Helper!$B:$B,"Milestone 6",Helper!$A:$A,"iWork",Helper!$E:$E,"Pending") -> 66 | C66: =COUNTIFS(Helper!$B:$B,"Milestone 6",Helper!$A:$A,"iWork - CR",Helper!$E:$E,"Pending") -> 6 | D66: =COUNTIFS(Helper!$B:$B,"Milestone 6",Helper!$A:$A,"IBP",Helper!$E:$E,"Pending") -> 3 | E66: =COUNTIFS(Helper!$B:$B,"Milestone 6",Helper!$A:$A,"IBP - CR",Helper!$E:$E,"Pending") -> 1 | F66: =COUNTIFS(Helper!$B:$B,"Milestone 6",Helper!$A:$A,"IBP/iWork",Helper!$E:$E,"Pending") -> 5 | G66: =COUNTIFS(Helper!$B:$B,"Milestone 6",Helper!$A:$A,"IBP/iWork - CR",Helper!$E:$E,"Pending") -> 5 | H66: =COUNTIFS(Helper!$B:$B,"Milestone 6",Helper!$A:$A,"Framework",Helper!$E:$E,"Pending") -> 0 | I66: =COUNTIFS(Helper!$B:$B,"Milestone 6",Helper!$A:$A,"DPDP",Helper!$E:$E,"Pending") -> 0 | J66: =COUNTIFS(Helper!$B:$B,"Milestone 6",Helper!$A:$A,"NFR",Helper!$E:$E,"Pending") -> 0 | K66: =SUM(B66:J66) -> 86
A67: TOTAL | B67: =SUM(B61:B66) -> 73 | C67: =SUM(C61:C66) -> 6 | D67: =SUM(D61:D66) -> 20 | E67: =SUM(E61:E66) -> 1 | F67: =SUM(F61:F66) -> 12 | G67: =SUM(G61:G66) -> 5 | H67: =SUM(H61:H66) -> 3 | I67: =SUM(I61:I66) -> 11 | ... K67: =SUM(K61:K66) -> 134
A69: ITEMS BY MILESTONE & STATUS
A70: Milestone | B70: Delivered | C70: Dev Complete | D70: In Development | E70: In QA | F70: Pre-PROD / UAT | G70: Not Started | H70: Partial Delivery | I70: TOTAL
A71: Milestone 1 | B71: =COUNTIFS(Helper!$B:$B,"Milestone 1",Helper!$D:$D,"Delivered") -> 29 | C71: =COUNTIFS(Helper!$B:$B,"Milestone 1",Helper!$D:$D,"Dev Complete") -> 0 | D71: =COUNTIFS(Helper!$B:$B,"Milestone 1",Helper!$D:$D,"In Development") -> 0 | E71: =COUNTIFS(Helper!$B:$B,"Milestone 1",Helper!$D:$D,"In QA") -> 0 | F71: =COUNTIFS(Helper!$B:$B,"Milestone 1",Helper!$D:$D,"Pre-PROD / UAT") -> 0 | G71: =COUNTIFS(Helper!$B:$B,"Milestone 1",Helper!$D:$D,"Not Started") -> 0 | H71: =COUNTIFS(Helper!$B:$B,"Milestone 1",Helper!$D:$D,"Partial Delivery") -> 0 | I71: =SUM(B71:H71) -> 29
A72: Milestone 2 | B72: =COUNTIFS(Helper!$B:$B,"Milestone 2",Helper!$D:$D,"Delivered") -> 31 | C72: =COUNTIFS(Helper!$B:$B,"Milestone 2",Helper!$D:$D,"Dev Complete") -> 0 | D72: =COUNTIFS(Helper!$B:$B,"Milestone 2",Helper!$D:$D,"In Development") -> 0 | E72: =COUNTIFS(Helper!$B:$B,"Milestone 2",Helper!$D:$D,"In QA") -> 0 | F72: =COUNTIFS(Helper!$B:$B,"Milestone 2",Helper!$D:$D,"Pre-PROD / UAT") -> 1 | G72: =COUNTIFS(Helper!$B:$B,"Milestone 2",Helper!$D:$D,"Not Started") -> 0 | H72: =COUNTIFS(Helper!$B:$B,"Milestone 2",Helper!$D:$D,"Partial Delivery") -> 0 | I72: =SUM(B72:H72) -> 32
A73: Milestone 3 | B73: =COUNTIFS(Helper!$B:$B,"Milestone 3",Helper!$D:$D,"Delivered") -> 8 | C73: =COUNTIFS(Helper!$B:$B,"Milestone 3",Helper!$D:$D,"Dev Complete") -> 0 | D73: =COUNTIFS(Helper!$B:$B,"Milestone 3",Helper!$D:$D,"In Development") -> 0 | E73: =COUNTIFS(Helper!$B:$B,"Milestone 3",Helper!$D:$D,"In QA") -> 0 | F73: =COUNTIFS(Helper!$B:$B,"Milestone 3",Helper!$D:$D,"Pre-PROD / UAT") -> 0 | G73: =COUNTIFS(Helper!$B:$B,"Milestone 3",Helper!$D:$D,"Not Started") -> 0 | H73: =COUNTIFS(Helper!$B:$B,"Milestone 3",Helper!$D:$D,"Partial Delivery") -> 0 | I73: =SUM(B73:H73) -> 8
A74: Milestone 4 | B74: =COUNTIFS(Helper!$B:$B,"Milestone 4",Helper!$D:$D,"Delivered") -> 47 | C74: =COUNTIFS(Helper!$B:$B,"Milestone 4",Helper!$D:$D,"Dev Complete") -> 0 | D74: =COUNTIFS(Helper!$B:$B,"Milestone 4",Helper!$D:$D,"In Development") -> 0 | E74: =COUNTIFS(Helper!$B:$B,"Milestone 4",Helper!$D:$D,"In QA") -> 0 | F74: =COUNTIFS(Helper!$B:$B,"Milestone 4",Helper!$D:$D,"Pre-PROD / UAT") -> 4 | G74: =COUNTIFS(Helper!$B:$B,"Milestone 4",Helper!$D:$D,"Not Started") -> 4 | H74: =COUNTIFS(Helper!$B:$B,"Milestone 4",Helper!$D:$D,"Partial Delivery") -> 2 | I74: =SUM(B74:H74) -> 57
A75: Milestone 5 | B75: =COUNTIFS(Helper!$B:$B,"Milestone 5",Helper!$D:$D,"Delivered") -> 29 | C75: =COUNTIFS(Helper!$B:$B,"Milestone 5",Helper!$D:$D,"Dev Complete") -> 1 | D75: =COUNTIFS(Helper!$B:$B,"Milestone 5",Helper!$D:$D,"In Development") -> 8 | E75: =COUNTIFS(Helper!$B:$B,"Milestone 5",Helper!$D:$D,"In QA") -> 1 | F75: =COUNTIFS(Helper!$B:$B,"Milestone 5",Helper!$D:$D,"Pre-PROD / UAT") -> 9 | G75: =COUNTIFS(Helper!$B:$B,"Milestone 5",Helper!$D:$D,"Not Started") -> 18 | H75: =COUNTIFS(Helper!$B:$B,"Milestone 5",Helper!$D:$D,"Partial Delivery") -> 1 | I75: =SUM(B75:H75) -> 67
A76: Milestone 6 | B76: =COUNTIFS(Helper!$B:$B,"Milestone 6",Helper!$D:$D,"Delivered") -> 137 | C76: =COUNTIFS(Helper!$B:$B,"Milestone 6",Helper!$D:$D,"Dev Complete") -> 5 | D76: =COUNTIFS(Helper!$B:$B,"Milestone 6",Helper!$D:$D,"In Development") -> 14 | E76: =COUNTIFS(Helper!$B:$B,"Milestone 6",Helper!$D:$D,"In QA") -> 3 | F76: =COUNTIFS(Helper!$B:$B,"Milestone 6",Helper!$D:$D,"Pre-PROD / UAT") -> 6 | G76: =COUNTIFS(Helper!$B:$B,"Milestone 6",Helper!$D:$D,"Not Started") -> 68 | H76: =COUNTIFS(Helper!$B:$B,"Milestone 6",Helper!$D:$D,"Partial Delivery") -> 0 | I76: =SUM(B76:H76) -> 233
A77: TOTAL | B77: =SUM(B71:B76) -> 281 | C77: =SUM(C71:C76) -> 6 | D77: =SUM(D71:D76) -> 22 | E77: =SUM(E71:E76) -> 4 | F77: =SUM(F71:F76) -> 20 | G77: =SUM(G71:G76) -> 90 | H77: =SUM(H71:H76) -> 3 | I77: =SUM(I71:I76) -> 426
A79: % Complete = Delivered ÷ (Delivered + Pending). N/A items (duplicates) are excluded from the calculation. All figures update live from the 'SOW, Feedbacks-Bug & CR_Items' sheet.

Sheet ② Stablization Summary
A1: STABILIZATION — STATUS OVERVIEW
A4: Stabilization Area | Break-up by Feature · As of 07-Aug-2026
A6: OVERALL COMPLETION | H6: REMAINING WORK
A7: =ROUND(COUNTIFS('SOW, Feedbacks-Bug & CR_Items'!$A:$A,"Stablization",Helper!$E:$E,"Delivered")/(COUNTIFS('SOW, Feedbacks-Bug & CR_Items'!$A:$A,"Stablization",Helper!$E:$E,"Delivered")+COUNTIFS('SOW, Feedbacks-Bug & CR_Items'!$A:$A,"Stablization",Helper!$E:$E,"Pending")),3) -> 0.15 | D7: =COUNTIFS('SOW, Feedbacks-Bug & CR_Items'!$A:$A,"Stablization",Helper!$E:$E,"Delivered")&" of "&(COUNTIFS('SOW, Feedbacks-Bug & CR_Items'!$A:$A,"Stablization",Helper!$E:$E,"Delivered")+COUNTIFS('SOW, Feedbacks-Bug & CR_Items'!$A:$A,"Stablization",Helper!$E:$E,"Pending"))&" Stabilization items delivered" -> 9 of 60 Stabilization items delivered | H7: =COUNTIFS('SOW, Feedbacks-Bug & CR_Items'!$A:$A,"Stablization",Helper!$E:$E,"Pending") -> 51 | J7: Stabilization items still to deliver, broken up by Feature below
A11: STATUS BREAKDOWN (Stabilization items)
A12: =COUNTIFS('SOW, Feedbacks-Bug & CR_Items'!$A:$A,"Stablization",Helper!$D:$D,"Delivered") -> 5 | D12: =COUNTIFS('SOW, Feedbacks-Bug & CR_Items'!$A:$A,"Stablization",Helper!$D:$D,"Dev Complete") -> 4 | G12: =COUNTIFS('SOW, Feedbacks-Bug & CR_Items'!$A:$A,"Stablization",Helper!$D:$D,"In Development") -> 8 | J12: =COUNTIFS('SOW, Feedbacks-Bug & CR_Items'!$A:$A,"Stablization",Helper!$D:$D,"In QA") -> 0
A13: Delivered | D13: Dev Complete | G13: In Development | J13: In QA
A14: =COUNTIFS('SOW, Feedbacks-Bug & CR_Items'!$A:$A,"Stablization",Helper!$D:$D,"Pre-PROD / UAT") -> 2 | D14: =COUNTIFS('SOW, Feedbacks-Bug & CR_Items'!$A:$A,"Stablization",Helper!$D:$D,"Not Started") -> 41 | G14: =COUNTIFS('SOW, Feedbacks-Bug & CR_Items'!$A:$A,"Stablization",Helper!$D:$D,"Partial Delivery") -> 0 | J14: =COUNTIFS('SOW, Feedbacks-Bug & CR_Items'!$A:$A,"Stablization",Helper!$D:$D,"N/A") -> 0
A15: Pre-PROD / UAT | D15: Not Started | G15: Partial Delivery | J15: N/A
A17: BREAKDOWN BY FEATURE
A18: Feature | B18: Total | C18: Delivered | D18: Pending | E18: N/A | F18: % Complete | G18: Progress
A19: Business Critical | B19: =COUNTIFS('SOW, Feedbacks-Bug & CR_Items'!$A:$A,"Stablization",'SOW, Feedbacks-Bug & CR_Items'!$B:$B,"Business Critical") -> 22 | C19: =COUNTIFS('SOW, Feedbacks-Bug & CR_Items'!$A:$A,"Stablization",'SOW, Feedbacks-Bug & CR_Items'!$B:$B,"Business Critical",Helper!$E:$E,"Delivered") -> 7 | D19: =COUNTIFS('SOW, Feedbacks-Bug & CR_Items'!$A:$A,"Stablization",'SOW, Feedbacks-Bug & CR_Items'!$B:$B,"Business Critical",Helper!$E:$E,"Pending") -> 15 | E19: =COUNTIFS('SOW, Feedbacks-Bug & CR_Items'!$A:$A,"Stablization",'SOW, Feedbacks-Bug & CR_Items'!$B:$B,"Business Critical",Helper!$E:$E,"N/A") -> 0 | F19: =IFERROR(C19/(C19+D19),0) -> 0.31818182 | G19: =F19 -> 0.31818182
A20: Maintenance | B20: =COUNTIFS('SOW, Feedbacks-Bug & CR_Items'!$A:$A,"Stablization",'SOW, Feedbacks-Bug & CR_Items'!$B:$B,"Maintenance") -> 10 | C20: =COUNTIFS('SOW, Feedbacks-Bug & CR_Items'!$A:$A,"Stablization",'SOW, Feedbacks-Bug & CR_Items'!$B:$B,"Maintenance",Helper!$E:$E,"Delivered") -> 0 | D20: =COUNTIFS('SOW, Feedbacks-Bug & CR_Items'!$A:$A,"Stablization",'SOW, Feedbacks-Bug & CR_Items'!$B:$B,"Maintenance",Helper!$E:$E,"Pending") -> 10 | E20: =COUNTIFS('SOW, Feedbacks-Bug & CR_Items'!$A:$A,"Stablization",'SOW, Feedbacks-Bug & CR_Items'!$B:$B,"Maintenance",Helper!$E:$E,"N/A") -> 0 | F20: =IFERROR(C20/(C20+D20),0) -> 0 | G20: =F20 -> 0
A21: Operational | B21: =COUNTIFS('SOW, Feedbacks-Bug & CR_Items'!$A:$A,"Stablization",'SOW, Feedbacks-Bug & CR_Items'!$B:$B,"Operational") -> 25 | C21: =COUNTIFS('SOW, Feedbacks-Bug & CR_Items'!$A:$A,"Stablization",'SOW, Feedbacks-Bug & CR_Items'!$B:$B,"Operational",Helper!$E:$E,"Delivered") -> 2 | D21: =COUNTIFS('SOW, Feedbacks-Bug & CR_Items'!$A:$A,"Stablization",'SOW, Feedbacks-Bug & CR_Items'!$B:$B,"Operational",Helper!$E:$E,"Pending") -> 23 | E21: =COUNTIFS('SOW, Feedbacks-Bug & CR_Items'!$A:$A,"Stablization",'SOW, Feedbacks-Bug & CR_Items'!$B:$B,"Operational",Helper!$E:$E,"N/A") -> 0 | F21: =IFERROR(C21/(C21+D21),0) -> 0.08 | G21: =F21 -> 0.08
A22: Orphan Records | B22: =COUNTIFS('SOW, Feedbacks-Bug & CR_Items'!$A:$A,"Stablization",'SOW, Feedbacks-Bug & CR_Items'!$B:$B,"Orphan Records") -> 3 | C22: =COUNTIFS('SOW, Feedbacks-Bug & CR_Items'!$A:$A,"Stablization",'SOW, Feedbacks-Bug & CR_Items'!$B:$B,"Orphan Records",Helper!$E:$E,"Delivered") -> 0 | D22: =COUNTIFS('SOW, Feedbacks-Bug & CR_Items'!$A:$A,"Stablization",'SOW, Feedbacks-Bug & CR_Items'!$B:$B,"Orphan Records",Helper!$E:$E,"Pending") -> 3 | E22: =COUNTIFS('SOW, Feedbacks-Bug & CR_Items'!$A:$A,"Stablization",'SOW, Feedbacks-Bug & CR_Items'!$B:$B,"Orphan Records",Helper!$E:$E,"N/A") -> 0 | F22: =IFERROR(C22/(C22+D22),0) -> 0 | G22: =F22 -> 0
A23: TOTAL | B23: =COUNTIFS('SOW, Feedbacks-Bug & CR_Items'!$A:$A,"Stablization") -> 60 | C23: =COUNTIFS('SOW, Feedbacks-Bug & CR_Items'!$A:$A,"Stablization",Helper!$E:$E,"Delivered") -> 9 | D23: =COUNTIFS('SOW, Feedbacks-Bug & CR_Items'!$A:$A,"Stablization",Helper!$E:$E,"Pending") -> 51 | E23: =COUNTIFS('SOW, Feedbacks-Bug & CR_Items'!$A:$A,"Stablization",Helper!$E:$E,"N/A") -> 0 | F23: =IFERROR(C23/(C23+D23),0) -> 0.15 | G23: =F23 -> 0.15
A25: Scope: rows where Area = 'Stablization' in the source sheet. % Complete = Delivered ÷ (Delivered + Pending). N/A items excluded. Counts update live from the source sheet; re-run the script only if a new Feature value is added under this Area (to add its row here).
A27: PRIORITY vs STATUS
A28: Priority | B28: Delivered | C28: Dev Complete | D28: In Development | E28: In QA | F28: Pre-PROD / UAT | G28: Not Started | H28: Partial Delivery | I28: N/A | J28: Unknown | K28: TOTAL
A29: High | B29: =COUNTIFS('SOW, Feedbacks-Bug & CR_Items'!$A:$A,"Stablization",'SOW, Feedbacks-Bug & CR_Items'!$J:$J,"High",Helper!$D:$D,"Delivered") -> 5 | C29: =COUNTIFS('SOW, Feedbacks-Bug & CR_Items'!$A:$A,"Stablization",'SOW, Feedbacks-Bug & CR_Items'!$J:$J,"High",Helper!$D:$D,"Dev Complete") -> 4 | D29: =COUNTIFS('SOW, Feedbacks-Bug & CR_Items'!$A:$A,"Stablization",'SOW, Feedbacks-Bug & CR_Items'!$J:$J,"High",Helper!$D:$D,"In Development") -> 8 | E29: =COUNTIFS('SOW, Feedbacks-Bug & CR_Items'!$A:$A,"Stablization",'SOW, Feedbacks-Bug & CR_Items'!$J:$J,"High",Helper!$D:$D,"In QA") -> 0 | F29: =COUNTIFS('SOW, Feedbacks-Bug & CR_Items'!$A:$A,"Stablization",'SOW, Feedbacks-Bug & CR_Items'!$J:$J,"High",Helper!$D:$D,"Pre-PROD / UAT") -> 2 | G29: =COUNTIFS('SOW, Feedbacks-Bug & CR_Items'!$A:$A,"Stablization",'SOW, Feedbacks-Bug & CR_Items'!$J:$J,"High",Helper!$D:$D,"Not Started") -> 17 | H29: =COUNTIFS('SOW, Feedbacks-Bug & CR_Items'!$A:$A,"Stablization",'SOW, Feedbacks-Bug & CR_Items'!$J:$J,"High",Helper!$D:$D,"Partial Delivery") -> 0 | I29: =COUNTIFS('SOW, Feedbacks-Bug & CR_Items'!$A:$A,"Stablization",'SOW, Feedbacks-Bug & CR_Items'!$J:$J,"High",Helper!$D:$D,"N/A") -> 0 | J29: =COUNTIFS('SOW, Feedbacks-Bug & CR_Items'!$A:$A,"Stablization",'SOW, Feedbacks-Bug & CR_Items'!$J:$J,"High",Helper!$D:$D,"Unknown") -> 0 | K29: =SUM(B29:J29) -> 36
A30: Medium | B30: =COUNTIFS('SOW, Feedbacks-Bug & CR_Items'!$A:$A,"Stablization",'SOW, Feedbacks-Bug & CR_Items'!$J:$J,"Medium",Helper!$D:$D,"Delivered") -> 0 | C30: =COUNTIFS('SOW, Feedbacks-Bug & CR_Items'!$A:$A,"Stablization",'SOW, Feedbacks-Bug & CR_Items'!$J:$J,"Medium",Helper!$D:$D,"Dev Complete") -> 0 | D30: =COUNTIFS('SOW, Feedbacks-Bug & CR_Items'!$A:$A,"Stablization",'SOW, Feedbacks-Bug & CR_Items'!$J:$J,"Medium",Helper!$D:$D,"In Development") -> 0 | E30: =COUNTIFS('SOW, Feedbacks-Bug & CR_Items'!$A:$A,"Stablization",'SOW, Feedbacks-Bug & CR_Items'!$J:$J,"Medium",Helper!$D:$D,"In QA") -> 0 | F30: =COUNTIFS('SOW, Feedbacks-Bug & CR_Items'!$A:$A,"Stablization",'SOW, Feedbacks-Bug & CR_Items'!$J:$J,"Medium",Helper!$D:$D,"Pre-PROD / UAT") -> 0 | G30: =COUNTIFS('SOW, Feedbacks-Bug & CR_Items'!$A:$A,"Stablization",'SOW, Feedbacks-Bug & CR_Items'!$J:$J,"Medium",Helper!$D:$D,"Not Started") -> 6 | H30: =COUNTIFS('SOW, Feedbacks-Bug & CR_Items'!$A:$A,"Stablization",'SOW, Feedbacks-Bug & CR_Items'!$J:$J,"Medium",Helper!$D:$D,"Partial Delivery") -> 0 | I30: =COUNTIFS('SOW, Feedbacks-Bug & CR_Items'!$A:$A,"Stablization",'SOW, Feedbacks-Bug & CR_Items'!$J:$J,"Medium",Helper!$D:$D,"N/A") -> 0 | J30: =COUNTIFS('SOW, Feedbacks-Bug & CR_Items'!$A:$A,"Stablization",'SOW, Feedbacks-Bug & CR_Items'!$J:$J,"Medium",Helper!$D:$D,"Unknown") -> 0 | K30: =SUM(B30:J30) -> 6
A31: Low | B31: =COUNTIFS('SOW, Feedbacks-Bug & CR_Items'!$A:$A,"Stablization",'SOW, Feedbacks-Bug & CR_Items'!$J:$J,"Low",Helper!$D:$D,"Delivered") -> 0 | C31: =COUNTIFS('SOW, Feedbacks-Bug & CR_Items'!$A:$A,"Stablization",'SOW, Feedbacks-Bug & CR_Items'!$J:$J,"Low",Helper!$D:$D,"Dev Complete") -> 0 | D31: =COUNTIFS('SOW, Feedbacks-Bug & CR_Items'!$A:$A,"Stablization",'SOW, Feedbacks-Bug & CR_Items'!$J:$J,"Low",Helper!$D:$D,"In Development") -> 0 | E31: =COUNTIFS('SOW, Feedbacks-Bug & CR_Items'!$A:$A,"Stablization",'SOW, Feedbacks-Bug & CR_Items'!$J:$J,"Low",Helper!$D:$D,"In QA") -> 0 | F31: =COUNTIFS('SOW, Feedbacks-Bug & CR_Items'!$A:$A,"Stablization",'SOW, Feedbacks-Bug & CR_Items'!$J:$J,"Low",Helper!$D:$D,"Pre-PROD / UAT") -> 0 | G31: =COUNTIFS('SOW, Feedbacks-Bug & CR_Items'!$A:$A,"Stablization",'SOW, Feedbacks-Bug & CR_Items'!$J:$J,"Low",Helper!$D:$D,"Not Started") -> 18 | H31: =COUNTIFS('SOW, Feedbacks-Bug & CR_Items'!$A:$A,"Stablization",'SOW, Feedbacks-Bug & CR_Items'!$J:$J,"Low",Helper!$D:$D,"Partial Delivery") -> 0 | I31: =COUNTIFS('SOW, Feedbacks-Bug & CR_Items'!$A:$A,"Stablization",'SOW, Feedbacks-Bug & CR_Items'!$J:$J,"Low",Helper!$D:$D,"N/A") -> 0 | J31: =COUNTIFS('SOW, Feedbacks-Bug & CR_Items'!$A:$A,"Stablization",'SOW, Feedbacks-Bug & CR_Items'!$J:$J,"Low",Helper!$D:$D,"Unknown") -> 0 | K31: =SUM(B31:J31) -> 18
A32: TOTAL | B32: =SUM(B29:B31) -> 5 | C32: =SUM(C29:C31) -> 4 | D32: =SUM(D29:D31) -> 8 | E32: =SUM(E29:E31) -> 0 | F32: =SUM(F29:F31) -> 2 | G32: =SUM(G29:G31) -> 41 | H32: =SUM(H29:H31) -> 0 | I32: =SUM(I29:I31) -> 0 | ... K32: =SUM(K29:K31) -> 60
A34: Scope: rows where Area = 'Stablization', grouped by the 'Priority' column. Counts update live from the source sheet; re-run the script only if a new Priority value is used (to add its row here).
A36: DAILY PROGRESS — toward the 14-Aug-2026 deadline
A37: Date | B37: Total | C37: Planned Delivered | D37: Delivered | E37: Planned Pending | F37: Pending | G37: Delivered Today | H37: % Complete | I37: Ahead/Behind Plan | J37: Days Left | K37: Req. Pace/day
A38: 46237 | B38: 31 | C38: 2 | D38: 0 | E38: 33 | F38: 31 | G38: — | H38: 0 | I38: -2 | J38: 11 | K38: 2.8
A39: 46238 | B39: 31 | C39: 6 | D39: 0 | E39: 29 | F39: 31 | G39: 0 | H39: 0 | I39: -6 | J39: 10 | K39: 3.1
A40: 46239 | B40: — | C40: 10 | D40: — | E40: 25 | F40: — | G40: — | H40: — | I40: — | J40: 9 | K40: —
A41: 46240 | B41: 35 | C41: 16 | D41: 9 | E41: 19 | F41: 26 | G41: 9 | H41: 0.2571 | I41: -7 | J41: 8 | K41: 3.2
A42: 46241 | B42: 35 | C42: 21 | D42: 9 | E42: 14 | F42: 26 | G42: 0 | H42: 0.2571 | I42: -12 | J42: 7 | K42: 3.7
A43: 46242 | B43: — | C43: 21 | D43: — | E43: 14 | F43: — | G43: — | H43: — | I43: — | J43: 6 | K43: —
A44: 46243 | B44: — | C44: 21 | D44: — | E44: 14 | F44: — | G44: — | H44: — | I44: — | J44: 5 | K44: —
A45: 46244 | B45: — | C45: 22 | D45: — | E45: 13 | F45: — | G45: — | H45: — | I45: — | J45: 4 | K45: —
A46: 46245 | B46: — | C46: 29 | D46: — | E46: 6 | F46: — | G46: — | H46: — | I46: — | J46: 3 | K46: —
A47: 46246 | B47: — | C47: 32 | D47: — | E47: 3 | F47: — | G47: — | H47: — | I47: — | J47: 2 | K47: —
A48: 46247 | B48: — | C48: 34 | D48: — | E48: 1 | F48: — | G48: — | H48: — | I48: — | J48: 1 | K48: —
A49: 46248 | B49: — | C49: 35 | D49: — | E49: 0 | F49: — | G49: — | H49: — | I49: — | J49: 0 | K49: —
A50: Unplanned (no ETA / ETA beyond 14-Aug) | C50: 25
A52: Scope: only the 35 Stablization items with an ETA on or before 14-Aug-2026 — that's the actual plan for this deadline. Planned Delivered/Pending = cumulative count of those items due on or before that day, from their real ETA dates (not a smoothed ramp); recomputed every run, so it shifts if ETAs or the item set change. Ahead/Behind Plan = Delivered − Planned Delivered for that day. The 25 item(s) with no ETA (or an ETA after 14-Aug) are listed above, not counted toward this deadline.

Sheet 📅 27-Jul
A1: WEEK OF 27 Jul 2026 → 02 Aug 2026 — 11 items · 10 delivered · 1 pending · LAST WEEK
A3: ⚠️ Static snapshot. To update: edit STATUS/ETA in the source sheet, then re-run build_iirm_summary.py
A5: # | B5: Module | C5: Feature | D5: Functionality | E5: Status | F5: Milestone | G5: Requested | H5: ETA | I5: Resource | J5: Remarks
A6: iWork (Backlog & CRs) · 9 items · 8 delivered · 1 pending
A7: 1 | B7: iWork | C7: My Client Portfolio | D7: My Client Portfolio: issues - company search and brokerage | E7: Delivered | F7: Milestone 6 | G7: 27-Jul-2026 | H7: 27-Jul-2026 | I7: Pushyami
A8: 2 | B8: iWork | C8: Dashboard | D8: Dashboard issue - ISG planning count mismatch | E8: Delivered | F8: Milestone 6 | G8: 28-Jul-2026 | H8: 28-Jul-2026 | I8: Pushyami
A9: 3 | B9: iWork | C9: Dashboard | D9: Business Performance-breakup - count mismatch | E9: Delivered | F9: Milestone 6 | G9: 28-Jul-2026 | H9: 28-Jul-2026 | I9: Pushyami
A10: 4 | B10: iWork | C10: View Service Score | D10: My Client Portfolio: Service Score - Single Table (drillable) to calculate an overall score Dashboard - Service Score - Widget | E10: Delivered | F10: Milestone 4 | G10: 10-Jun-2025 | H10: 29-Jul-2026 | I10: Sunil
A11: 5 | B11: iWork | C11: Manage Insurer | D11: Insurer-branch-edit | E11: Delivered | F11: Milestone 6 | G11: 29-Jul-2026 | H11: 29-Jul-2026
A12: 6 | B12: IBP/iWork | C12: Core Infrastructure | D12: Core Infra | E12: Delivered | F12: Milestone 5 | G12: 31-Jul-2025 | H12: 31-Jul-2026 | I12: Velangini Raju | J12: Pending: Mobile responsive
A13: 7 | B13: iWork | C13: HRMS Integration Mgmt Framework provided to link the HRMS portal in Risk Watch | D13: Base framework needs to be built and actual integration should be on need - Need to create the API's for each service flow process (Endorsement - Add/Delete) - Endorsement process - What is the process for this? HRMS - integrations with enrolment portal (POC - with Zoho People), client mentioned that they have already integrated MB360 for HCL IBP & HRMS Integration - HCL | E13: Pre-PROD | F13: Milestone 5 | G13: 31-Jul-2025 | H13: 31-Jul-2026 | J13: As per us Framework is Ready. Validate integrate HCL API's and test it.
A14: 8 | B14: IBP/iWork | C14: Enrolment Journey - EMI's | D14: Based on Employee's enrolment period, the EMI months should be pro-ration month. Ex: Day-1 should show the all months EMI. If someone enrol after 2-months then EMI should be based on that. | E14: Delivered | F14: Milestone 6 | G14: 29-Jul-2026 | H14: 31-Jul-2026 | J14: Kriti raised
A15: 9 | B15: iWork | C15: BizDone - Data Updates | D15: Bizdone 2025-26 - Ass. CRM & Lead CRM Corrections | E15: Delivered | F15: Milestone 6 | G15: 30-Jul-2026 | H15: 31-Jul-2026 | J15: Madhav sent in IIRM email
A16: IBP (Backlog & CRs) · 2 items · 2 delivered · 0 pending
A17: 10 | B17: IBP | C17: Chat Interface | D17: Floater on the screen - Integrate with AI Component and IWork support channel | E17: Delivered | F17: Milestone 5 | G17: 31-Jul-2025 | H17: 31-Jul-2026
A18: 11 | B18: IBP | C18: Chat for End Users | D18: Chat Module to interact with Chat Bot and Customer Support Representative | E18: Delivered | F18: Milestone 5 | G18: 31-Jul-2025 | H18: 31-Jul-2026 | I18: Abhilash | J18: External chatbot integration?

Sheet 📍 03-Aug
A1: WEEK OF 03 Aug 2026 → 09 Aug 2026 — 86 items · 11 delivered · 75 pending · CURRENT WEEK
A3: ⚠️ Static snapshot. To update: edit STATUS/ETA in the source sheet, then re-run build_iirm_summary.py
A5: # | B5: Module | C5: Feature | D5: Functionality | E5: Status | F5: Milestone | G5: Requested | H5: ETA | I5: Resource | J5: Remarks
A6: iWork (Backlog & CRs) · 49 items · 8 delivered · 41 pending
A7: 1 | B7: iWork | C7: Cut Off Mgmt | E7: Pre-PROD | F7: Milestone 2 | G7: 16-Apr-2025 | H7: 03-Aug-2026 | I7: Karan
A8: 2 | B8: IBP/iWork | C8: Wellness Discount List Management | D8: Add/Remove/update Discount program benefits | E8: Pre-PROD | F8: Milestone 4 | G8: 10-Jun-2025 | H8: 03-Aug-2026
A9: 3 | B9: IBP/iWork | C9: Upload from Partner of services bought on Partner site | D9: Upload, listing, confirm & load into DB by an Iwork user. These are services purchased / discounts availed on partner sites by IBP corporate users | E9: Pre-PROD | F9: Milestone 4 | G9: 10-Jun-2025 | H9: 03-Aug-2026
A10: 4 | B10: IBP/iWork | C10: Wellness Admin Configurator | D10: Admin side of IBP (in iWork) needs to customize/configure the offerings/page per Corporate. | E10: Pre-PROD | F10: Milestone 5 | G10: 31-Jul-2025 | H10: 03-Aug-2026 | I10: Ravi
A11: 5 | B11: IBP/iWork | C11: End User Portal Configurator | D11: What set of features to be enabled or disabled, Offers, Benefits etc. More or less how portal should contain and visible to end user needs to be configured (per Corporate Configuration) | E11: Pre-PROD | F11: Milestone 5 | G11: 31-Jul-2025 | H11: 03-Aug-2026 | I11: Manjusha | J11: Pending: Offer, Feature flagging (UI)
A12: 6 | B12: iWork | C12: ISG Flow Changes | D12: Placement Slip flow - Terrorism premium in Insurer Sharing | E12: Pre-PROD | F12: Milestone 6 | G12: 27-Jul-2026 | H12: 03-Aug-2026 | I12: Karan | J12: Madhav sent in IIRM email
A13: 7 | B13: iWork | C13: Business Critical | D13: Migration Data load should be always complete only after manual Performances Job Execution - Continous acitivity | E13: DEV - WIP | F13: Milestone 6 | G13: 01-Aug-2026 | H13: 03-Aug-2026 | I13: Rama | J13: Anytime, manual load or adjustments are done, performance job needs to be executed for entire period
A14: 8 | B14: iWork | C14: Business Critical | D14: Dashboard: Implementation of the dynamic fetching of widgets data without depending on performance output cron job | E14: UAT - WIP | F14: Milestone 6 | G14: 01-Aug-2026 | H14: 03-Aug-2026 | I14: Jagadeesh
A15: 9 | B15: IBP/iWork - CR | C15: Service Flow - Upload Employee Details | D15: Upsert logic - Tough there is an employee data historically, when user upload latest file we have to update the "Empolyee" or "Dependent" details with the latest information | E15: DEV - WIP | F15: Milestone 6 | G15: 01-Jul-2026 | H15: 04-Aug-2026 | I15: Jagadeesh
A16: 10 | B16: IBP/iWork | C16: IBP - Email Communication | D16: For an enrolled employee with Dependents using Service, instead of Welcome Email they should get Confirmation email | E16: Pre-PROD | F16: Milestone 6 | G16: 25-Jul-2026 | H16: 04-Aug-2026 | I16: Abhilash | J16: API is ready. Need to add into Notification framework
A17: 11 | B17: iWork | C17: IBP - Enrolment Details | D17: DVN Group - Dependent based on SI & Premium changes | E17: DEV - WIP | F17: Milestone 6 | G17: 01-Aug-2026 | H17: 04-Aug-2026 | I17: Abhilash
A18: 12 | B18: iWork | C18: Business Critical | D18: Dashboard: Having individual component loaders on the landing page for each component and web-socket framework to avoid long-loading blank page issue. | E18: Dev - Done | F18: Milestone 6 | G18: 01-Aug-2026 | H18: 04-Aug-2026 | I18: Manjusha
A19: 13 | B19: iWork | C19: Business Critical | D19: BizDone & Dashboard: Filters Persistance | E19: Delivered | F19: Milestone 6 | G19: 01-Aug-2026 | H19: 04-Aug-2026 | I19: Sunil
A20: 14 | B20: iWork - CR | C20: Business Critical | D20: BizDone - Download - User select the desired sheet | E20: Delivered | F20: Milestone 6 | G20: 01-Aug-2026 | H20: 04-Aug-2026 | I20: Karan
A21: 15 | B21: iWork | C21: Business Critical | D21: BizDone - Download - Indian template along with Localization fields | E21: UAT - WIP | F21: Milestone 6 | G21: 01-Aug-2026 | H21: 04-Aug-2026 | I21: Leela
A22: 16 | B22: iWork | C22: Reports | D22: Generic template for all the reports, Bizdone Report, Missing entries from commission statement against policies | E22: Delivered - Deficit | F22: Milestone 5 | G22: 31-Jul-2025 | H22: 05-Aug-2026 | J22: Linked with Reconciliation Management & Commission
A23: 17 | B23: iWork | C23: Operational | D23: Personal Lines Data Integration (DSR and iWork) | E23: Dev - Done | F23: Milestone 6 | G23: 25-Jul-2026 | H23: 05-Aug-2026 | I23: Junaid
A24: 18 | B24: iWork | C24: Business Critical | D24: BizDone - Download - Performance (Offload Excel Generation) - API, Queue, Store in S3 & Download | E24: Delivered | F24: Milestone 6 | G24: 01-Aug-2026 | H24: 05-Aug-2026 | I24: Karan
A25: 19 | B25: iWork | C25: Business Critical | D25: BizDone - Applied filters in the Downloaded file in Sheet-1 | E25: Delivered | F25: Milestone 6 | G25: 01-Aug-2026 | H25: 05-Aug-2026 | I25: Sunil
A26: 20 | B26: IBP/iWork - CR | C26: IBP - Enrolment Journey | D26: Using Policy Config, add only dependent & complete the enrolment. - Hide SI, Premiums, Rate Calculator - Endorsement - Employee only should support SI & Parameter | E26: Yet to start | F26: Milestone 6 | G26: 03-Aug-2026 | H26: 05-Aug-2026 | I26: Jagadeesh
A27: 21 | B27: iWork | C27: Business Critical | D27: The owner selection process remains highly user-unfriendly, with a very small expand ('>') button, incomplete visibility of names, and insufficient hierarchy indentation. | E27: DEV - WIP | F27: Milestone 6 | G27: 18-Jul-2026 | H27: 06-Aug-2026 | I27: Raju
A28: 22 | B28: iWork | C28: Business Critical | D28: BizDone - Old & Enhance Screens - For now both will be live(Metrics) | E28: Dev - WIP | F28: Milestone 6 | G28: 01-Aug-2026 | H28: 06-Aug-2026 | I28: Karan
A29: 23 | B29: iWork | C29: Business Critical | D29: Dashboard & BizDone: Centralised code or utility to fetch the KPIs data for re-usability | E29: Dev - WIP | F29: Milestone 6 | G29: 01-Aug-2026 | H29: 06-Aug-2026 | I29: Sunil
A30: 24 | B30: iWork | C30: Operational | D30: Job - Dashboard - Review, Enhance and document | E30: Delivered | F30: Milestone 6 | G30: 01-Aug-2026 | H30: 06-Aug-2026 | I30: Sunil | J30: Flag based development / remove job post approval
A31: 25 | B31: iWork | C31: Operational | D31: Demo Env. - Stop all the Job; Make sure emails & SMS are working as expected | E31: Yet to start | F31: Milestone 6 | G31: 01-Aug-2026 | H31: 06-Aug-2026 | I31: Tharun
A32: 26 | B32: iWork | C32: Business Critical | D32: PROD Bug: Dashboard vs RO page - When login user applied the same filters in Dashboard and the same in RO then counts are NO matching - Example Milind in email | E32: DEV - WIP | F32: Milestone 6 | G32: 06-Aug-2026 | H32: 06-Aug-2026 | I32: Karan
A33: 27 | B33: IBP/iWork | C33: Country Handling {Data Source Mgmt} | D33: 23-May: Respective org. data should reside in the same country. | E33: Yet to start | F33: Milestone 4 | G33: 10-Jun-2025 | H33: 07-Aug-2026 | I33: Rama
A34: 28 | B34: iWork | C34: Teams Integration | D34: MS Teams - Meetings & Tasks integration into iWork Bi-Directional | E34: Yet to start | F34: Milestone 4 | G34: 10-Jun-2025 | H34: 07-Aug-2026 | I34: Rama
A35: 29 | B35: IBP/iWork | C35: Wellness IIRM View | D35: IIRM View of Wellness usage by Corporates/Employees (IBP Admin) | E35: Yet to start | F35: Milestone 5 | G35: 31-Jul-2025 | H35: 07-Aug-2026 | I35: Manjusha | J35: Wellness HR View
A36: 30 | B36: iWork | C36: Reconciliation Management Upload Commission Statement | D36: Upload commission statement, reconcile against issued policies; Upload invoice & reconcile against commission stmt; Upload invoice statuses and reconcile paid/unpaid Premium vs Brokerage Invoice vs Brokerage Collected; Data from Finops | E36: Yet to start | F36: Milestone 5 | G36: 31-Jul-2025 | H36: 07-Aug-2026 | J36: Need inputs from Kapil
A37: 31 | B37: iWork | C37: Insurer Integration Mgmt | D37: Can be used as a part of External API Intergration | E37: Yet to start | F37: Milestone 5 | G37: 31-Jul-2025 | H37: 07-Aug-2026
A38: 32 | B38: iWork | C38: Reconciliation Mgmt | E38: Yet to start | F38: Milestone 5 | G38: 31-Jul-2025 | H38: 07-Aug-2026
A39: 33 | B39: iWork - CR | C39: Policy Configuration | D39: Enable Parent-Child Policy Mapping for GMC and Sub-Plans (Parental, OPD, Dental, Others) - How to view config from Base to Child Policiy? - How to handle endorsement & Claims? (Entire Service Flow) | E39: Yet to start | F39: Milestone 6 | G39: 01-May-2026 | H39: 07-Aug-2026 | I39: Sunil
A40: 34 | B40: iWork - CR | C40: Opportunity - Validate uploaded documents | D40: Using AI - Extract the documents, validate, populate the data in the Opty. flow (Ex. KDM Meeting, Policy Hard Copy, & Others) | E40: Yet to start | F40: Milestone 6 | G40: 08-May-2026 | H40: 07-Aug-2026 | J40: Need some information about the document rules that defines the idenity of it
A41: 35 | B41: iWork - CR | C41: SSO - MS AD Account | D41: iWork - SSO with Microsoft AD (POC) | E41: DEV - Done | F41: Milestone 6 | G41: 05-Jun-2026 | H41: 07-Aug-2026 | I41: Rama | J41: 10-Jun-2026: POC Demo to Venu completed
A42: 36 | B42: IBP/iWork - CR | C42: IIRM-10667 | D42: iWork - Knowledge Central Re-Design | E42: Yet to start | F42: Milestone 6 | G42: 15-Jun-2026 | H42: 07-Aug-2026
A43: 37 | B43: IBP/iWork - CR | C43: IIRM-10668 | D43: iLearn: Document Preview in-app | E43: Yet to start | F43: Milestone 6 | G43: 15-Jun-2026 | H43: 07-Aug-2026
A44: 38 | B44: iWork | C44: Discuss with Madhav | D44: 19-Jun-2026: Financial Impact fields should be seperated from actual fields. These fields should NOT be populated on their own. (Mainly BizDone & Dashboard) Also, check if we are there are any data loads for 2025-26 | E44: Yet to start | F44: Milestone 6 | G44: 15-Jun-2026 | H44: 07-Aug-2026
A45: 39 | B45: iWork | C45: AI | D45: AI Nudges are NOT working. If there is NO AI, then DB scripts should run and show data | E45: Yet to start | F45: Milestone 6 | G45: 25-Jun-2026 | H45: 07-Aug-2026 | I45: Rama
A46: 40 | B46: IBP/iWork - CR | C46: InsureEasy | D46: InsureEasy Integration - Retail Business | E46: Yet to start | F46: Milestone 6 | G46: 25-Jun-2026 | H46: 07-Aug-2026
A47: 41 | B47: iWork | C47: AI | D47: Wherever AI is implemented, there should be fallback if one day we turnoff AI then there shouldn’t be any impact in the working functionality | E47: Yet to start | F47: Milestone 6 | G47: 25-Jun-2026 | H47: 07-Aug-2026 | I47: Rama
A48: 42 | B48: iWork | C48: Inception/Endorsement | D48: Endorsement data upload related * Track-1: TeamLease - 2024-2025 Year policies * All endorsement -> Headers, Member data, & endorsement Document * Track-2: Old Financial data * Track-3: Current Financial data * Track-4: Handle the data in IBP-Risk Watch | E48: DEV - WIP | F48: Milestone 6 | G48: 25-Jun-2026 | H48: 07-Aug-2026 | I48: Rama
A49: 43 | B49: iWork - CR | C49: Business Critical | D49: Computed value & Reported values * Computed values - It’s the real-time values base on Policy inception/endorsement * Reported values - It’s validated by the mgmt. and share this number to update in the column. * Reported value MUST be used for the Dashboard & BizDone, which was declared by the company to public. * In the admin a feature to update the Reported values from the computed values * Legacy data - Premiums, Brokerage, CD Balance | E49: Yet to start | F49: Milestone 6 | G49: 25-Jun-2026 | H49: 07-Aug-2026
A50: 44 | B50: IBP/iWork | C50: Toast Message - UI | D50: Update the font & style for Toast message across application | E50: Yet to start | F50: Milestone 6 | G50: 09-Jul-2026 | H50: 07-Aug-2026 | I50: Tharun | J50: Surya sir provided an idea via email to Me & Naveen
A51: 45 | B51: iWork | C51: Business Critical | D51: BizDone - Screen & Download data is not consistent | E51: Dev - WIP | F51: Milestone 6 | G51: 18-Jul-2026 | H51: 07-Aug-2026 | I51: Karan
A52: 46 | B52: IBP/iWork | C52: Application Performance | D52: IIRM-10799_Performance (Database & Infra) | E52: Yet to start | F52: Milestone 6 | G52: 24-Jul-2026 | H52: 07-Aug-2026
A53: 47 | B53: iWork | C53: Personal Line Data Integrations | D53: DSR and iWork Integration Enablement | E53: Yet to start | F53: Milestone 6 | G53: 25-Jul-2026 | H53: 07-Aug-2026 | J53: Madhav sent in IIRM email
A54: 48 | B54: iWork | C54: Business Critical | D54: BizDone & Dashboard - Consider Fee & Rewards as "Brokerage" | E54: Yet to start | F54: Milestone 6 | G54: 01-Aug-2026 | H54: 07-Aug-2026 | I54: Sunil
A55: 49 | B55: iWork | C55: Operational | D55: PROD & Other env.: Database Vaccum - Schedule a periodic acitvity in all the env. | E55: Yet to start | F55: Milestone 6 | G55: 01-Aug-2026 | H55: 07-Aug-2026 | I55: Abhilash
A56: IBP (Backlog & CRs) · 19 items · 2 delivered · 17 pending
A57: 50 | B57: IBP | C57: User Profile | D57: Profile, Service Subscriptions, Feedback | E57: Pre-PROD | F57: Milestone 5 | G57: 31-Jul-2025 | H57: 03-Aug-2026 | I57: Ravi | J57: Pending: Service Subscriptions, Feedback
A58: 51 | B58: IBP | C58: Basic Wellness Hub | D58: Basic wellness hub - Currently only 3 wellness programs (3rd parties) supported | E58: Pre-PROD | F58: Milestone 5 | G58: 31-Jul-2025 | H58: 03-Aug-2026 | I58: Manjusha | J58: Wellness
A59: 52 | B59: IBP | C59: Landing Page Services | D59: Benefits Summary View, Upcoming welness appointment, Policy renewals, Individual Plans Summary views | E59: Pre-PROD | F59: Milestone 5 | G59: 31-Jul-2025 | H59: 03-Aug-2026 | I59: Manjusha
A60: 53 | B60: IBP | C60: Benefits Summary | D60: End User's Summary View | E60: Pre-PROD | F60: Milestone 5 | G60: 31-Jul-2025 | H60: 03-Aug-2026 | I60: Ravi
A61: 54 | B61: IBP | C61: Evexia Club Integration | D61: Integration to Evexia | E61: Pre-PROD | F61: Milestone 5 | G61: 31-Jul-2025 | H61: 03-Aug-2026 | I61: Abhilash
A62: 55 | B62: IBP - CR | C62: Claim Intimation & Submission | D62: POC - Using AI(Amazon Textract) - Extract Claim documents and populate the data | E62: Pre-PROD | F62: Milestone 6 | G62: 08-May-2026 | H62: 03-Aug-2026 | I62: Abhilash
A63: 56 | B63: IBP | C63: Business Critical | D63: IBP - Risk Watch - Report Issues - Enrolment Drive - Validate, enhance, and document | E63: Dev - Done | F63: Milestone 6 | G63: 01-Aug-2026 | H63: 05-Aug-2026 | I63: Ravikiran
A64: 57 | B64: IBP | C64: NFR_Usability | D64: NFR-USA-011: The system should support at least 100 concurrent users without performance degradation. | E64: Pre-PROD | F64: Milestone 4 | G64: 10-Jun-2025 | H64: 07-Aug-2026 | I64: Akhila | J64: Fine tuning the API's where there is a delay
A65: 58 | B65: IBP | C65: My Insurance | D65: Part-2: Hub of all plans I have as an employee - individually signed up. Mostly a navigational page | E65: Yet to start | F65: Milestone 5 | G65: 31-Jul-2025 | H65: 07-Aug-2026 | I65: Ravi | J65: Retail Business
A66: 59 | B66: IBP | C66: Wellness HR View | D66: HR View of Wellness usage by Employees | E66: Yet to start | F66: Milestone 5 | G66: 31-Jul-2025 | H66: 07-Aug-2026 | I66: Manjusha | J66: Wellness
A67: 60 | B67: IBP | C67: Wellness Partner View | D67: Partner/service provider view of the usage of their corresponding services | E67: Yet to start | F67: Milestone 5 | G67: 31-Jul-2025 | H67: 07-Aug-2026 | I67: Manjusha | J67: Wellness
A68: 61 | B68: IBP | C68: Individual Plans | D68: Quotation flow of a new insurance - multple products; quotation ranges after basic data collection; cross-sells and finally an summary page that someone will get back to you. About 7 individual products - could be 4-5 screens in the flow of which 2 screens may be product-specific. | E68: Yet to start | F68: Milestone 5 | G68: 31-Jul-2025 | H68: 07-Aug-2026 | I68: Ravi | J68: Retail Business
A69: 62 | B69: IBP | C69: Individual Plan Summary | D69: View of individual Plans currently owned with renewal dates, premiums etc. | E69: Yet to start | F69: Milestone 5 | G69: 31-Jul-2025 | H69: 07-Aug-2026 | I69: Ravi | J69: Retail Business
A70: 63 | B70: IBP | C70: Profile Migration | D70: Request migration of Corporate Profile to Individual | E70: Yet to start | F70: Milestone 5 | G70: 31-Jul-2025 | H70: 07-Aug-2026 | I70: Abhilash | J70: Retail Business
A71: 64 | B71: IBP | C71: Profile Migration | D71: Request migration of Individual Profile to Corporate | E71: Yet to start | F71: Milestone 5 | G71: 31-Jul-2025 | H71: 07-Aug-2026 | I71: Abhilash | J71: Retail Business
A72: 65 | B72: IBP | C72: Individual Insurance Plan Mgmt | D72: Support for multiple categories of plans. Configuration Mgmt for Infomration capture, Flow and Summaries. Add on configuration, Insurer configuration, Offer configuration, Post the request to Sales Channel (Iwork) 7 Policy Types to be taken care of | E72: Yet to start | F72: Milestone 5 | G72: 31-Jul-2025 | H72: 07-Aug-2026 | I72: Ravi | J72: Retail Business
A73: 66 | B73: IBP | C73: IIRM-10666 | D73: IBP - Policy Component Card Re-design | E73: Yet to start | F73: Milestone 6 | G73: 21-Jun-2026 | H73: 07-Aug-2026 | I73: Manjusha
A74: 67 | B74: IBP | C74: Claims Corner | D74: Claims Corner - Screen Re-design | E74: DEV - WIP | F74: Milestone 6 | G74: 21-Jun-2026 | H74: 07-Aug-2026 | I74: Ravi
A75: 68 | B75: IBP | C75: Business Critical | D75: IBP - Risk Watch - Company & Policy Levels are not matching (CD, Endorsement, Claims) | E75: Dev - Done | F75: Milestone 6 | G75: 01-Aug-2026 | H75: 07-Aug-2026 | I75: Ravikiran
A76: Framework (DPDP, NFR, Framework) · 18 items · 1 delivered · 17 pending
A77: 69 | B77: Framework | C77: Notifications Management | D77: Different email notification - Madhav excel. 1. Renewal Reminders - ASAP 2. Instalment Reminders 3. Others | E77: Pre-PROD | F77: Milestone 4 | G77: 10-Jun-2025 | H77: 03-Aug-2026 | I77: Pushyami
A78: 70 | B78: Framework | C78: Accessibility | D78: 20-Jul: Jagadees --> Need More details | E78: Yet to start | F78: Milestone 4 | G78: 10-Jun-2025 | H78: 07-Aug-2026
A79: 71 | B79: Framework | C79: Localisation | E79: Delivered - Deficit | F79: Milestone 4 | G79: 10-Jun-2025 | H79: 07-Aug-2026 | I79: Tharun | J79: Pending: Service Flow
A80: 72 | B80: NFR | C80: NFR_Usability | D80: NFR-USA-021: Guidelines for document management should be provided | E80: Delivered - Deficit | F80: Milestone 4 | G80: 10-Jun-2025 | H80: 07-Aug-2026 | I80: Rama | J80: Pending: Provide the document on how do we store and view it
A81: 73 | B81: DPDP | C81: Archived Oppurtunity, Policy Mgmt {Archived Biz Data and Retrieval on need} - DPDP | E81: Yet to start | F81: Milestone 4 | G81: 10-Jun-2025 | H81: 07-Aug-2026 | I81: Rama
A82: 74 | B82: DPDP | C82: App vulnerability scans | E82: DEV - WIP | F82: Milestone 5 | G82: 31-Jul-2025 | H82: 07-Aug-2026
A83: 75 | B83: DPDP | C83: Document Flows | E83: DEV - WIP | F83: Milestone 5 | G83: 31-Jul-2025 | H83: 07-Aug-2026
A84: 76 | B84: DPDP | C84: Perform security UAT | E84: DEV - WIP | F84: Milestone 5 | G84: 31-Jul-2025 | H84: 07-Aug-2026
A85: 77 | B85: DPDP | C85: Remove unnecessary fields | E85: DEV - Done | F85: Milestone 5 | G85: 31-Jul-2025 | H85: 07-Aug-2026
A86: 78 | B86: DPDP | C86: Enforce business logic to restrict purpose | E86: DEV - WIP | F86: Milestone 5 | G86: 31-Jul-2025 | H86: 07-Aug-2026
A87: 79 | B87: DPDP | C87: Allow user corrections | E87: DEV - WIP | F87: Milestone 5 | G87: 31-Jul-2025 | H87: 07-Aug-2026
A88: 80 | B88: DPDP | C88: Delete expired data | E88: DEV - WIP | F88: Milestone 5 | G88: 31-Jul-2025 | H88: 07-Aug-2026
A89: 81 | B89: DPDP | C89: Map PII tables | E89: QA - WIP | F89: Milestone 5 | G89: 31-Jul-2025 | H89: 07-Aug-2026 | I89: Rama
A90: 82 | B90: DPDP | C90: Enable delete pipeline | E90: Yet to start | F90: Milestone 5 | G90: 31-Jul-2025 | H90: 07-Aug-2026
A91: 83 | B91: DPDP | C91: Sign DPDP clauses | E91: DEV - WIP | F91: Milestone 5 | G91: 31-Jul-2025 | H91: 07-Aug-2026
A92: 84 | B92: DPDP | C92: Quarterly restore tests | E92: Pre-PROD | F92: Milestone 5 | G92: 31-Jul-2025 | H92: 07-Aug-2026 | I92: Rama
A93: 85 | B93: NFR | C93: NFR-OTH-022: A self-service report generator must be available for dynamic query/report creation. | E93: Yet to start | F93: Milestone 5 | G93: 31-Jul-2025 | H93: 07-Aug-2026 | J93: Discussed this with Surya sir last visit to Divami office
A94: 86 | B94: NFR | C94: NFR-OTH-015: The application must cryptographic Failures, previously known as Sensitive Data Exposure, which was broad symptom rather than a root cause. The renewed focus here is on failures related to cryptography which often leads to sensitive data exposure or system compromise. | E94: DEV - WIP | F94: Milestone 5 | G94: 31-Jul-2025 | H94: 07-Aug-2026

Sheet 📅 10-Aug
A1: WEEK OF 10 Aug 2026 → 16 Aug 2026 — 14 items · 0 delivered · 14 pending · NEXT WEEK
A3: ⚠️ Static snapshot. To update: edit STATUS/ETA in the source sheet, then re-run build_iirm_summary.py
A5: # | B5: Module | C5: Feature | D5: Functionality | E5: Status | F5: Milestone | G5: Requested | H5: ETA | I5: Resource | J5: Remarks
A6: iWork (Backlog & CRs) · 13 items · 0 delivered · 13 pending
A7: 1 | B7: iWork | C7: Business Critical | D7: BizDone - Performance - Query Fine Tuning | E7: Dev - WIP | F7: Milestone 6 | G7: 01-Aug-2026 | H7: 10-Aug-2026 | I7: Karan
A8: 2 | B8: iWork | C8: Business Critical | D8: BizDone & other filters - Multi-select for Vertical & Branch | E8: Dev - WIP | F8: Milestone 6 | G8: 18-Jul-2026 | H8: 11-Aug-2026 | I8: Sunil
A9: 3 | B9: iWork | C9: Operational | D9: Demo Env. - Record the application/Infrastruction/DevOps situation when application is in Zero state | E9: Yet to start | F9: Milestone 6 | G9: 01-Aug-2026 | H9: 11-Aug-2026 | I9: Tharun / Jagadeesh
A10: 4 | B10: iWork | C10: Operational | D10: PROD & Demo Env.: Database - Partitioning | E10: Yet to start | F10: Milestone 6 | G10: 01-Aug-2026 | H10: 11-Aug-2026 | I10: Abhilash
A11: 5 | B11: iWork | C11: Orphan Records | D11: Orphan - Companies - Identifying the records, Validate & Delete | E11: Yet to start | F11: Milestone 6 | G11: 06-Aug-2026 | H11: 11-Aug-2026 | I11: Gopal / Rama
A12: 6 | B12: iWork | C12: Orphan Records | D12: Orphan - Oppotunities - Identifying the records, Validate & Delete | E12: Yet to start | F12: Milestone 6 | G12: 06-Aug-2026 | H12: 11-Aug-2026 | I12: Gopal / Rama
A13: 7 | B13: iWork | C13: Orphan Records | D13: Orphan - Policies - Identifying the records, Validate & Delete | E13: Yet to start | F13: Milestone 6 | G13: 06-Aug-2026 | H13: 11-Aug-2026 | I13: Gopal / Rama
A14: 8 | B14: iWork | C14: Business Critical | D14: Dashboard - Performance - Query Fine Tuning | E14: Yet to start | F14: Milestone 6 | G14: 01-Aug-2026 | H14: 12-Aug-2026 | I14: Sunil
A15: 9 | B15: iWork - CR | C15: Business Critical | D15: BizDone - Download - Reduce the file size (Ex. Excel binary or others) | E15: Yet to start | F15: Milestone 6 | G15: 01-Aug-2026 | H15: 12-Aug-2026 | I15: Karan
A16: 10 | B16: iWork | C16: Operational | D16: Job - Expiry Opportunity - Review, Enhance and document | E16: Yet to start | F16: Milestone 6 | G16: 01-Aug-2026 | H16: 12-Aug-2026 | I16: Karan
A17: 11 | B17: iWork | C17: Operational | D17: PROD & Demo Env.: Database - Indexing | E17: Yet to start | F17: Milestone 6 | G17: 01-Aug-2026 | H17: 13-Aug-2026 | I17: Abhilash
A18: 12 | B18: iWork | C18: Operational | D18: Job - RO Creation - Review, Enhance and document | E18: Yet to start | F18: Milestone 6 | G18: 01-Aug-2026 | H18: 13-Aug-2026 | I18: Karan | J18: 6-Aug: Surya sir want to discuss thing
A19: 13 | B19: iWork | C19: Operational | D19: PROD & Demo Env.: Database - SQL Functions for all the reports | E19: Yet to start | F19: Milestone 6 | G19: 01-Aug-2026 | H19: 14-Aug-2026 | I19: Abhilash
A20: Other / Unassigned · 1 item · 0 delivered · 1 pending
A21: 14 | B21: iWork/IBP | C21: Operational | D21: Notification Mgmt - Turn on, Turn off, History, Approval, template changes | E21: Yet to start | F21: Milestone 6 | G21: 01-Aug-2026 | H21: 11-Aug-2026 | I21: Karan

Sheet 📅 Upcoming
A1: UPCOMING (ETA beyond 10 Aug week) — 0 items · 0 delivered · 0 pending
A3: ⚠️ Static snapshot. To update: edit STATUS/ETA in the source sheet, then re-run build_iirm_summary.py
A5: # | B5: Module | C5: Feature | D5: Functionality | E5: Status | F5: Milestone | G5: Requested | H5: ETA | I5: Resource | J5: Remarks

Sheet Unplanned (no ETA)
A1: UNPLANNED — PENDING, NO ETA · 36 items
A3: Pending items with no ETA yet. Assign an ETA in the source sheet to move an item into its week. Static snapshot — re-run to refresh.
A5: # | B5: Module | C5: Feature | D5: Functionality | E5: Status | F5: Milestone | G5: Requested | H5: ETA | I5: Resource | J5: Remarks
A6: iWork (Backlog & CRs) · 28 items
A7: 1 | B7: IBP/iWork | C7: IBP Landing Page - Customization | D7: Landing Page customization in Admin side of IBP - available in iWork (per Corporate) | E7: Yet to start | F7: Milestone 5 | G7: 31-Jul-2025
A8: 2 | B8: iWork | C8: Maintenance | D8: iWork - Reports - View Dump for each download for comparision | E8: Yet to start | F8: Milestone 6 | G8: 20-Apr-2026 | I8: Gopal
A9: 3 | B9: iWork - CR | C9: Operational | D9: Policy Config - Premium Rater Table | E9: Yet to start | F9: Milestone 6 | G9: 21-Apr-2026 | I9: Jagadeesh
A10: 4 | B10: iWork | C10: Operational | D10: Export to excel - iWork all the results table; Download is on Previlage | E10: Yet to start | F10: Milestone 6 | G10: 15-Jun-2026
A11: 5 | B11: IBP/iWork | C11: Operational | D11: IBP - Raise Ticket: Edit the ticket and update the status by the Lead CRM & System Admin Same funtionality should be there in iWork for internal purpose. Should send email notification when there are changes to status | E11: Yet to start | F11: Milestone 6 | G11: 01-Jul-2026 | I11: Manjusha
A12: 6 | B12: IBP/iWork | C12: Operational | D12: IBP - Emails: Dual approval/confirmation - Before sending to Employees. 1. 2 levels in iWork 2. CRM will submit & HR will approve in Risk Watch | E12: Yet to start | F12: Milestone 6 | G12: 14-Jul-2026
A13: 7 | B13: iWork | C13: Maintenance | D13: In any of the screen, we have to provide an info icon where it will help the users how critical fields in that screen are derieved or got populated | E13: Yet to start | F13: Milestone 6 | G13: 17-Jul-2026
A14: 8 | B14: iWork | C14: Operational | D14: CMS - Policy Level - Component Notes from Strapi | E14: Yet to start | F14: Milestone 6 | G14: 31-Jul-2026 | J14: Ex. TL - Parental 2-years Lock-in; SI may vary
A15: 9 | B15: iWork | C15: Maintenance | D15: Convert Policy from Active to Generated | E15: Yet to start | F15: Milestone 6 | G15: 01-Aug-2026
A16: 10 | B16: iWork | C16: Maintenance | D16: Delete - Policy Configuration | E16: Yet to start | F16: Milestone 6 | G16: 01-Aug-2026
A17: 11 | B17: iWork | C17: Maintenance | D17: PROD: Health Check of the Application, Alert notification & Triage the situation | E17: Yet to start | F17: Milestone 6 | G17: 01-Aug-2026
A18: 12 | B18: iWork | C18: Maintenance | D18: Delete - Inception/Endorsement Data | E18: Yet to start | F18: Milestone 6 | G18: 01-Aug-2026
A19: 13 | B19: iWork | C19: Maintenance | D19: Employee Mgmt - Create, Update, Delete - Validate and document | E19: Yet to start | F19: Milestone 6 | G19: 01-Aug-2026
A20: 14 | B20: iWork | C20: Maintenance | D20: Hierarchy Mgmt - View & Update - Report & Visual Chart | E20: Yet to start | F20: Milestone 6 | G20: 01-Aug-2026
A21: 15 | B21: iWork | C21: Maintenance | D21: iWork - Reports - Use BizDone framework | E21: Yet to start | F21: Milestone 6 | G21: 01-Aug-2026
A22: 16 | B22: iWork | C22: Operational | D22: PROD Bug: SES - Notifications - Check what is the configuration. (Scenario: For the very first time Email or SMS is taking time then rest are instant) | E22: Yet to start | F22: Milestone 6 | G22: 01-Aug-2026
A23: 17 | B23: iWork | C23: Operational | D23: Infra - Season based bumping (Example: When policies are expiring, need to bump the infra/DB because load will be more). Identify the data and plan this acitivity. | E23: Yet to start | F23: Milestone 6 | G23: 01-Aug-2026
A24: 18 | B24: iWork | C24: Operational | D24: Optimal allocate the memory/infra size based on the service operational usage rather than generic size for all | E24: Yet to start | F24: Milestone 6 | G24: 01-Aug-2026
A25: 19 | B25: iWork | C25: Operational | D25: Split Service - Risk Watch because it should run on it own and NOT impact other iWork or IBP services | E25: Yet to start | F25: Milestone 6 | G25: 01-Aug-2026
A26: 20 | B26: iWork | C26: Operational | D26: Split Service - Identify service areas because either iWork or IBP utilization should not impact other services | E26: Yet to start | F26: Milestone 6 | G26: 01-Aug-2026
A27: 21 | B27: iWork | C27: Operational | D27: Reports - iWork - Validate, enhance, and document | E27: Yet to start | F27: Milestone 6 | G27: 01-Aug-2026
A28: 22 | B28: iWork | C28: Operational | D28: Automation process for Data Load (Gopal & Rama's Task) | E28: Yet to start | F28: Milestone 6 | G28: 01-Aug-2026 | I28: Rama
A29: 23 | B29: iWork | C29: Operational | D29: Export - IBP-Risk Watch - All the results/Widget must be downloadable based onn Previlage | E29: Yet to start | F29: Milestone 6 | G29: 01-Aug-2026
A30: 24 | B30: iWork | C30: Operational | D30: Email Notifications - Policy Renewals - CRM users & Insurer Contact | E30: Yet to start | F30: Milestone 6 | G30: 01-Aug-2026
A31: 25 | B31: iWork | C31: Operational | D31: Email Notifications - Opty. Lost/ Policy Renewals/ Instalments - CRM users | E31: Yet to start | F31: Milestone 6 | G31: 01-Aug-2026
A32: 26 | B32: iWork | C32: Operational | D32: Add/Update - Address & Contact - Across Application | E32: Yet to start | F32: Milestone 6 | G32: 01-Aug-2026
A33: 27 | B33: iWork | C33: Orphan Records | D33: Admin Screen - to view and delete the records | E33: Yet to start | F33: Milestone 6 | G33: 06-Aug-2026
A34: 28 | B34: iWork | C34: S3 Document Mgmt. | D34: Admin Screen to Delete or Archive files in S3 Need a process to handle it | E34: Yet to start | F34: Milestone 6 | G34: 06-Aug-2026
A35: IBP (Backlog & CRs) · 4 items
A36: 29 | B36: IBP | C36: Premium Range Calculator | D36: Calculate insurance premium range. Calculate the IDV of various assets | E36: Yet to start | F36: Milestone 5 | G36: 31-Jul-2025 | I36: Ravi | J36: Retail Business
A37: 30 | B37: IBP | C37: Multiple 3rd Party Service Mgmt | D37: Elderly Services, Dental Services etc. 3rd Party integrations. Multiple providers 3 such services are in scope at this stage {Redhealth, MyDental, AkinCare} | E37: Yet to start | F37: Milestone 5 | G37: 31-Jul-2025 | J37: Retail Business
A38: 31 | B38: IBP | C38: Claims Mgmt | D38: Part-2: Personal Policy based claim mgmt, Tracking status, Document Mgmt related to claims | E38: Yet to start | F38: Milestone 5 | G38: 31-Jul-2025 | J38: Retail Business
A39: 32 | B39: IBP | C39: IBP - Enrolment Journey | D39: When user save & exit is considered as Enrolled | E39: Yet to start | F39: Milestone 6 | G39: 21-Jul-2026 | I39: Abhilash | J39: Jayakar reported
A40: Other / Unassigned · 4 items
A41: 33 | B41: iWork/IBP | C41: Maintenance | D41: IBP - Go-Live: Check-list document & SOP | E41: Yet to start | F41: Milestone 6 | G41: 20-Apr-2026 | I41: Nithin
A42: 34 | B42: iWork/IBP | C42: Business Critical | D42: iWork/IBP - Claim Process - Intimation & Submission (Different Flows) | E42: Yet to start | F42: Milestone 6 | G42: 01-Aug-2026
A43: 35 | B43: iWork/IBP | C43: Business Critical | D43: Life Events - Create Endorsment & next steps; Notification to CRM/KAM Team | E43: Yet to start | F43: Milestone 6 | G43: 01-Aug-2026
A44: 36 | B44: iWork/IBP | C44: Business Critical | D44: IBP - Email Notification - Company specific email templates for all types (Welcome, Confirmation, Reminder, Raise Ticket, & Others) | E44: Yet to start | F44: Milestone 6 | G44: 01-Aug-2026

Sheet VRK Feedbacks
A1: VRK — PROD FEEDBACK TRACKER · 80 items · 67 delivered · 13 pending
A3: All 'VRK - PROD Feedback:' items, broken up by week (status then ETA within a week). Excluded from the other views. Static snapshot.
A5: # | B5: Module | C5: Feature | D5: Functionality | E5: Status | F5: Milestone | G5: Requested | H5: ETA | I5: Resource | J5: Remarks
A6: 📅 WEEK OF 08 Jun → 14 Jun 2026 · PAST · 27 items
A7: 1 | B7: iWork | C7: VRK - PROD Feedback: 5-Jun-2026 | D7: Manage SO - Update the date filters to "SO Expiry Date" | E7: Delivered | F7: Milestone 6 | G7: 05-Jun-2026 | H7: 08-Jun-2026
A8: 2 | B8: iWork | C8: VRK - PROD Feedback: 8-Jun-2026 | D8: Critical: SO expiry logic and date validation should allow within 365 days at the time so creation. | E8: Delivered | F8: Milestone 6 | G8: 08-Jun-2026 | H8: 08-Jun-2026
A9: 3 | B9: iWork | C9: VRK - PROD Feedback: 8-Jun-2026 | D9: Dashboard - Save View button to be moved to Run button --> Move the Save View button beside Reset | E9: Delivered | F9: Milestone 6 | G9: 08-Jun-2026 | H9: 08-Jun-2026
A10: 4 | B10: iWork | C10: VRK - PROD Feedback: 8-Jun-2026 | D10: Dont display CD management in menu link - move under Admin | E10: Delivered | F10: Milestone 6 | G10: 08-Jun-2026 | H10: 08-Jun-2026
A11: 5 | B11: iWork | C11: VRK - PROD Feedback: 8-Jun-2026 | D11: filter out support services from the dashboard | E11: Delivered | F11: Milestone 6 | G11: 08-Jun-2026 | H11: 08-Jun-2026
A12: 6 | B12: iWork | C12: VRK - PROD Feedback: 8-Jun-2026 | D12: funnels - hide Overall conversion values | E12: Delivered | F12: Milestone 6 | G12: 08-Jun-2026 | H12: 08-Jun-2026
A13: 7 | B13: iWork | C13: VRK - PROD Feedback: 8-Jun-2026 | D13: In My RO, "BD planning" title should change to "Renewal Planning" for RO | E13: Delivered | F13: Milestone 6 | G13: 08-Jun-2026 | H13: 08-Jun-2026
A14: 8 | B14: iWork | C14: VRK - PROD Feedback: 8-Jun-2026 | D14: Manage TPA/BRoker/Insurer should be moved to Admin Module | E14: Delivered | F14: Milestone 6 | G14: 08-Jun-2026 | H14: 08-Jun-2026
A15: 9 | B15: iWork | C15: VRK - PROD Feedback: 8-Jun-2026 | D15: My Follow Up - hide "All" option - RO should be default | E15: Delivered | F15: Milestone 6 | G15: 08-Jun-2026 | H15: 08-Jun-2026
A16: 10 | B16: iWork | C16: VRK - PROD Feedback: 8-Jun-2026 | D16: Policy Expiry Timeline by SBU - change to "Renewal Schedule by SBU" and move under renewal funnel | E16: Delivered | F16: Milestone 6 | G16: 08-Jun-2026 | H16: 08-Jun-2026
A17: 11 | B17: iWork | C17: VRK - PROD Feedback: 8-Jun-2026 | D17: Ribbon level reports link should be hidden --> Hide "Reports" on the header menu. And also move the "Utilization report" to Admin Module. | E17: Delivered | F17: Milestone 6 | G17: 08-Jun-2026 | H17: 08-Jun-2026
A18: 12 | B18: iWork | C18: VRK - PROD Feedback: 8-Jun-2026 IIRM-10589 | D18: My client portfolio - Period (Company created) change to - Period (policies created) --- Show the same filters of Manage Policy | E18: Delivered | F18: Milestone 6 | G18: 08-Jun-2026 | H18: 09-Jun-2026 | I18: Karan
A19: 13 | B19: iWork | C19: VRK - PROD Feedback: 8-Jun-2026 | D19: isg roles: manage quotes screen should display the opportunities which are related to ISG only. | E19: Delivered | F19: Milestone 6 | G19: 08-Jun-2026 | H19: 09-Jun-2026
A20: 14 | B20: iWork | C20: VRK - PROD Feedback: 9-Jun-2026 | D20: BD/ISG planning dates should be empty and mandatory - should be mandatory to start the journey. | E20: Delivered | F20: Milestone 6 | G20: 09-Jun-2026 | H20: 09-Jun-2026
A21: 15 | B21: iWork | C21: VRK - PROD Feedback: 9-Jun-2026 | D21: In "Manage Quotes"/"Manage SO" page, a link should be provided on the activity name, it should get redirected to respective activity stage. | E21: Delivered | F21: Milestone 6 | G21: 09-Jun-2026 | H21: 09-Jun-2026 | I21: Pushyami
A22: 16 | B22: iWork | C22: VRK - PROD Feedback: 9-Jun-2026 | D22: Issue in Bizdone search results - Company name not visible | E22: Delivered | F22: Milestone 6 | G22: 09-Jun-2026 | H22: 09-Jun-2026 | I22: Pushyami
A23: 17 | B23: iWork | C23: VRK - PROD Feedback: 9-Jun-2026 IIRM-10588 | D23: Rename "My SO" to "Manage SO" in the sales portfolio. | E23: Delivered | F23: Milestone 6 | G23: 09-Jun-2026 | H23: 09-Jun-2026 | I23: Pushyami
A24: 18 | B24: iWork | C24: VRK - PROD Feedback: 9-Jun-2026 | D24: SO creation process: SO Expiry field title should be changed to "Opportunity/Existing Policy Expiry" - label to be changed. Nithin --> Also, change in SO details page as well | E24: Delivered | F24: Milestone 6 | G24: 09-Jun-2026 | H24: 09-Jun-2026 | I24: Pushyami
A25: 19 | B25: iWork | C25: VRK - PROD Feedback: 8-Jun-2026 | D25: My RO clicked should not get highlighted to My SO menu link. | E25: Delivered | F25: Milestone 6 | G25: 08-Jun-2026 | H25: 10-Jun-2026
A26: 20 | B26: iWork | C26: VRK - PROD Feedback: 9-Jun-2026 | D26: My followup section in the dashboard - should display default Activity names and show the values even there are zeros for each activity. | E26: Delivered | F26: Milestone 6 | G26: 09-Jun-2026 | H26: 10-Jun-2026 | I26: Prathiphala
A27: 21 | B27: iWork | C27: VRK - PROD Feedback: 9-Jun-2026 | D27: Opportunity lost logic:- if placement slip is not crossed, instantly mark the opportunity as "Lost" based on Opty. Expiry date | E27: Delivered | F27: Milestone 6 | G27: 09-Jun-2026 | H27: 10-Jun-2026 | I27: Jagadeesh
A28: 22 | B28: iWork | C28: VRK - PROD Feedback: 9-Jun-2026 | D28: Opportunity lost logic:- if the activity crossed "Placement Slip", premium calculation and crossed 5 days, then mark the opportunity as "Lost" based on Opty. expiry date+5 days | E28: Delivered | F28: Milestone 6 | G28: 09-Jun-2026 | H28: 10-Jun-2026 | I28: Jagadeesh
A29: 23 | B29: iWork | C29: VRK - PROD Feedback: 8-Jun-2026 IIRM-10589 | D29: My client portfolio - list of all companies for Active policies only | E29: Delivered | F29: Milestone 6 | G29: 08-Jun-2026 | H29: 12-Jun-2026 | I29: Karan
A30: 24 | B30: iWork | C30: VRK - PROD Feedback: 8-Jun-2026 | D30: Policy Expiry Timeline by SBU - when clicked, redirect to RO screen with the counts. | E30: Delivered | F30: Milestone 6 | G30: 08-Jun-2026 | H30: 12-Jun-2026
A31: 25 | B31: iWork | C31: VRK - PROD Feedback: 9-Jun-2026 | D31: BDR results list should display the link of policy ID and Opty ID. | E31: Delivered | F31: Milestone 6 | G31: 09-Jun-2026 | H31: 12-Jun-2026 | I31: Prathiphala
A32: 26 | B32: iWork | C32: VRK - PROD Feedback: 8-Jun-2026 | D32: My client portfolio: List of Companies should be displayed for which there are active RO's. The premium and brokerage should be displayed as per RO cards. --> Que: Yesterday it was asked to get the data related to Active Policies???? | E32: Not a bug | F32: Milestone 6 | G32: 08-Jun-2026 | H32: 08-Jun-2026 | J32: 10-Jun: As per Surya/Kapil Sir. It's Active Policies only
A33: 27 | B33: iWork | C33: VRK - PROD Feedback: 8-Jun-2026 | D33: my followup should be added into my actionalables with default display instead of "All" tab. | E33: Not a bug | F33: Milestone 6 | G33: 08-Jun-2026 | H33: 08-Jun-2026
A34: 📅 WEEK OF 15 Jun → 21 Jun 2026 · PAST · 8 items
A35: 28 | B35: iWork | C35: VRK - PROD Feedback: 9-Jun-2026 IIRM-10589 | D35: All SO and RO items should be displayed order by Expiry Date (ascending) in the same page once "Manage Quotes" is clicked by the user. | E35: Delivered | F35: Milestone 6 | G35: 09-Jun-2026 | H35: 15-Jun-2026 | I35: Karan
A36: 29 | B36: iWork | C36: VRK - PROD Feedback: 9-Jun-2026 IIRM-10589 | D36: ISG users should be able to view ISG activities only and BD related activities should be collapsable and hidden; accordingly manage the breadcrums. Similarly, vice versa for BD users. | E36: Delivered | F36: Milestone 6 | G36: 09-Jun-2026 | H36: 15-Jun-2026 | I36: Karan
A37: 30 | B37: iWork | C37: VRK - PROD Feedback: 9-Jun-2026 IIRM-10589 | D37: Manage Quote RO and Manager Quote SO should be clubbed to "Manage Quotes" link for ISG team only. --> 10-Jun: Surya -> Show the data only when opty. is in ISG Activity. | E37: Delivered | F37: Milestone 6 | G37: 09-Jun-2026 | H37: 15-Jun-2026 | I37: Karan
A38: 31 | B38: iWork | C38: VRK - PROD Feedback: 9-Jun-2026 IIRM-10589 | D38: My client portfolio: There must be a provision of "Past company" view in the Client Portfolio. | E38: Delivered | F38: Milestone 6 | G38: 09-Jun-2026 | H38: 15-Jun-2026
A39: 32 | B39: iWork | C39: VRK - PROD Feedback: 9-Jun-2026 IIRM-10589 | D39: Nithin -> Add the filters required to handle both SO & RO in "Manage Quotes" | E39: Delivered | F39: Milestone 6 | G39: 09-Jun-2026 | H39: 15-Jun-2026 | I39: Karan
A40: 33 | B40: iWork | C40: VRK - PROD Feedback: 9-Jun-2026 IIRM-10589 | D40: Hide "My RO" from the Sales portfolio. Add in the "My Client Portfolio" | E40: Delivered | F40: Milestone 6 | G40: 09-Jun-2026 | H40: 16-Jun-2026
A41: 34 | B41: iWork | C41: VRK - PROD Feedback: 8-Jun-2026 | D41: Commercial lines 25-26 numbers should be rectified; it should be 24.99 | E41: Delivered | F41: Milestone 6 | G41: 08-Jun-2026 | H41: 19-Jun-2026 | I41: Rama
A42: 35 | B42: iWork | C42: VRK - PROD Feedback: 9-Jun-2026 | D42: All Stage/Activity-wise wherever Document upload option is there, should be a mandatory | E42: Delivered | F42: Milestone 6 | G42: 09-Jun-2026 | H42: 19-Jun-2026 | I42: Karan
A43: 📅 WEEK OF 22 Jun → 28 Jun 2026 · PAST · 1 item
A44: 36 | B44: iWork | C44: VRK - PROD Feedback: 8-Jun-2026 | D44: funnels - alignment graph issues with grid; | E44: Delivered | F44: Milestone 6 | G44: 08-Jun-2026 | H44: 24-Jun-2026
A45: 📅 WEEK OF 29 Jun → 05 Jul 2026 · PAST · 8 items
A46: 37 | B46: iWork | C46: VRK - PROD Feedback: 8-Jun-2026 | D46: Policy Hard copy receipt stage - When User uploads the Policy copy, system should capture the policy level elements like Ins Pol No., Dates, Premium amounts, etc and validate with the policy record saved. - Need discussion for more details to use the deviation and approval process to modify the values as per deviation from Policy Hard copy. | E46: Delivered | F46: Milestone 6 | G46: 08-Jun-2026 | H46: 30-Jun-2026 | I46: Jagadeesh
A47: 38 | B47: iWork - CR | C47: VRK - PROD Feedback: 23-Jun-2026 | D47: Ribbon level: Reports should include Poppins & Bizdone report | E47: Delivered | F47: Milestone 6 | G47: 23-Jun-2026 | H47: 01-Jul-2026 | I47: Pushyami
A48: 39 | B48: iWork - CR | C48: VRK - PROD Feedback: 23-Jun-2026 | D48: Hide "Reports" from Left Menu | E48: Delivered | F48: Milestone 6 | G48: 23-Jun-2026 | H48: 01-Jul-2026 | I48: Pushyami
A49: 40 | B49: iWork - CR | C49: VRK - PROD Feedback: 23-Jun-2026 | D49: Remove "±5 days of expiry" | E49: Delivered | F49: Milestone 6 | G49: 23-Jun-2026 | H49: 01-Jul-2026 | I49: Pushyami
A50: 41 | B50: iWork - CR | C50: VRK - PROD Feedback: 23-Jun-2026 | D50: Dashboard - SO - Add SBU schedule & My Follow-ups | E50: Delivered | F50: Milestone 6 | G50: 23-Jun-2026 | H50: 01-Jul-2026 | I50: Pushyami
A51: 42 | B51: iWork - CR | C51: VRK - PROD Feedback: 23-Jun-2026 | D51: Dashboard - RO - Add SBU schedule & My Follow-ups | E51: Delivered | F51: Milestone 6 | G51: 23-Jun-2026 | H51: 01-Jul-2026 | I51: Pushyami
A52: 43 | B52: iWork - CR | C52: VRK - PROD Feedback: 23-Jun-2026 | D52: Business Performance - Update to stacked bar | E52: Delivered | F52: Milestone 6 | G52: 23-Jun-2026 | H52: 01-Jul-2026 | I52: Pushyami
A53: 44 | B53: iWork | C53: VRK - PROD Feedback: 8-Jun-2026 | D53: Filter stickyness is not working for Bizdone and check with all the other screens. (Filters Persistence in all the screens) | E53: Delivered | F53: Milestone 6 | G53: 08-Jun-2026 | H53: 02-Jul-2026
A54: 📅 WEEK OF 06 Jul → 12 Jul 2026 · PAST · 3 items
A55: 45 | B55: iWork - CR | C55: VRK - PROD Feedback: 23-Jun-2026 | D55: My RO - SBU, Vertical, Branch break-down with details | E55: Delivered | F55: Milestone 6 | G55: 23-Jun-2026 | H55: 07-Jul-2026 | I55: Pushyami
A56: 46 | B56: iWork - CR | C56: VRK - PROD Feedback: 23-Jun-2026 | D56: Manage SO - SBU, Vertical, Branch break-down with details | E56: Delivered | F56: Milestone 6 | G56: 23-Jun-2026 | H56: 08-Jul-2026 | I56: Pushyami
A57: 47 | B57: iWork - CR | C57: VRK - PROD Feedback: 23-Jun-2026 | D57: BizDone - SBU, Vertical, Branch break-down with details | E57: Delivered | F57: Milestone 6 | G57: 23-Jun-2026 | H57: 08-Jul-2026 | I57: Pushyami
A58: 📅 WEEK OF 13 Jul → 19 Jul 2026 · PAST · 13 items
A59: 48 | B59: iWork - CR | C59: VRK - PROD Feedback: 13-Jul-2026 | D59: Enhanced Screens: Layout Changes - Remove the Vertical section. Keep only Branch. | E59: Delivered | F59: Milestone 6 | G59: 13-Jul-2026 | H59: 13-Jul-2026
A60: 49 | B60: iWork - CR | C60: VRK - PROD Feedback: 23-Jun-2026 | D60: My Client Portfolio - SBU, Vertical, Branch break-down with details | E60: Delivered | F60: Milestone 6 | G60: 23-Jun-2026 | H60: 14-Jul-2026 | I60: Karan
A61: 50 | B61: iWork - CR | C61: VRK - PROD Feedback: 23-Jun-2026 | D61: Dashboard - Filter & drill-down | E61: Delivered | F61: Milestone 6 | G61: 23-Jun-2026 | H61: 14-Jul-2026 | I61: Karan
A62: 51 | B62: iWork - CR | C62: VRK - PROD Feedback: 13-Jul-2026 | D62: Dashboard UI & Visualization - Remove the SO/RO labels from the bar charts. Display only the figures inside the bars, with the corresponding details available on mouse hover (tooltip). | E62: Delivered | F62: Milestone 6 | G62: 13-Jul-2026 | H62: 14-Jul-2026
A63: 52 | B63: iWork - CR | C63: VRK - PROD Feedback: 13-Jul-2026 | D63: Dashboard UI & Visualization - Review and correct the display of negative values for TeamLease under RO, particularly for Q3 bar-chart. | E63: Delivered | F63: Milestone 6 | G63: 13-Jul-2026 | H63: 14-Jul-2026
A64: 53 | B64: iWork - CR | C64: VRK - PROD Feedback: 13-Jul-2026 | D64: Brokerage Display - Display Brokerage information only. Hide Premium values in the enhanced screens. | E64: Delivered | F64: Milestone 6 | G64: 13-Jul-2026 | H64: 15-Jul-2026
A65: 54 | B65: iWork - CR | C65: VRK - PROD Feedback: 13-Jul-2026 | D65: BizDone Enhanced Screen - Hide Premium. Display: RO Brokerage SO Brokerage | E65: Delivered | F65: Milestone 6 | G65: 13-Jul-2026 | H65: 15-Jul-2026
A66: 55 | B66: iWork - CR | C66: VRK - PROD Feedback: 13-Jul-2026 | D66: Dashboard UI & Visualization - Resolve the Premium value formatting issue. Values should be displayed consistently in Millions/Billions. | E66: Delivered | F66: Milestone 6 | G66: 13-Jul-2026 | H66: 15-Jul-2026
A67: 56 | B67: iWork - CR | C67: VRK - PROD Feedback: 13-Jul-2026 | D67: Dashboard UI & Visualization - Display the Endorsement section above the section “Business Collection Summary”. | E67: Delivered | F67: Milestone 6 | G67: 13-Jul-2026 | H67: 15-Jul-2026
A68: 57 | B68: iWork - CR | C68: VRK - PROD Feedback: 13-Jul-2026 | D68: Dashboard UI & Visualization - Move the Policy Type Distribution section above RO by SBU. | E68: Delivered | F68: Milestone 6 | G68: 13-Jul-2026 | H68: 15-Jul-2026
A69: 58 | B69: iWork - CR | C69: VRK - PROD Feedback: 13-Jul-2026 | D69: Dashboard UI & Visualization - Rename/update the Policy Type names “Fire & Engineering”, “Speciality Lines - Liability” | E69: Delivered | F69: Milestone 6 | G69: 13-Jul-2026 | H69: 15-Jul-2026
A70: 59 | B70: iWork - CR | C70: VRK - PROD Feedback: 13-Jul-2026 | D70: Functional Changes - The SO Activity Follow-up screen should not display ISG-related activities. | E70: Delivered | F70: Milestone 6 | G70: 13-Jul-2026 | H70: 15-Jul-2026
A71: 60 | B71: iWork - CR | C71: VRK - PROD Feedback: 13-Jul-2026 | D71: Dashboard Issues - When IIRM Holdings is selected, the Organization-level cards and graphs are not displayed. Verify and fix the issue. | E71: Delivered | F71: Milestone 6 | G71: 13-Jul-2026 | H71: 17-Jul-2026
A72: 📅 WEEK OF 20 Jul → 26 Jul 2026 · PAST · 3 items
A73: 61 | B73: iWork - CR | C73: VRK - PROD Feedback: 13-Jul-2026 | D73: Enhanced Screens: Layout Changes - Display the data using an Accordion layout in the following order: Company → SBU → Branch → Executive → Client → Policy | E73: Delivered | F73: Milestone 6 | G73: 13-Jul-2026 | H73: 20-Jul-2026
A74: 62 | B74: iWork - CR | C74: VRK - PROD Feedback: 13-Jul-2026 | D74: Functional Changes - Make the Funnel interactive so that clicking on each stage navigates to the corresponding enhanced screen. Also, when we click on "Numbers" also it has to move to respective screens | E74: Delivered | F74: Milestone 6 | G74: 13-Jul-2026 | H74: 22-Jul-2026 | I74: Pushyami | J74: Pending: Becuase the enhanced screens are yet to Approve
A75: 63 | B75: iWork - CR | C75: VRK - PROD Feedback: 13-Jul-2026 | D75: Dashboard Issues - Under PL, the bar chart should represent SO-level data instead of the currently displayed RO-level data. | E75: Delivered | F75: Milestone 6 | G75: 13-Jul-2026 | H75: 22-Jul-2026 | I75: Jagadeesh
A76: 📅 WEEK OF 27 Jul → 02 Aug 2026 · LAST WEEK · 2 items
A77: 64 | B77: iWork - CR | C77: VRK - PROD Feedback: 23-Jun-2026 | D77: Additional section display: Placement Funnel, Schedule, Followup | E77: Delivered | F77: Milestone 6 | G77: 23-Jun-2026 | H77: 30-Jul-2026 | I77: Karan
A78: 65 | B78: iWork - CR | C78: VRK - PROD Feedback: 13-Jul-2026 | D78: Enhanced screen: My Client Portfolio | E78: Delivered | F78: Milestone 6 | G78: 27-Jul-2026 | H78: 30-Jul-2026
A79: 📍 WEEK OF 03 Aug → 09 Aug 2026 · CURRENT WEEK · 8 items
A80: 66 | B80: iWork | C80: VRK - PROD Feedback: 6-Aug-2026 | D80: Update "Won" Logic in Opty. Flow | E80: Yet to start | F80: Milestone 6 | G80: 06-Aug-2026 | H80: 06-Aug-2026
A81: 67 | B81: iWork - CR | C81: VRK - PROD Feedback: 23-Jun-2026 | D81: iWork and iTicket should be accessible via VPN | E81: Yet to start | F81: Milestone 6 | G81: 23-Jun-2026 | H81: 07-Aug-2026 | I81: Pushyami
A82: 68 | B82: iWork | C82: VRK - PROD Feedback: 6-Aug-2026 | D82: RO Expiry Date Logic to add "+1 day" 1. Retrofit the existing data 2. Update the logic in the RO Generation job | E82: DEV - WIP | F82: Milestone 6 | G82: 06-Aug-2026 | H82: 06-Aug-2026
A83: 69 | B83: iWork | C83: VRK - PROD Feedback: 6-Aug-2026 | D83: PROD Bug: Table sorting in each result (Start with BizDone and continue other screen) | E83: DEV - WIP | F83: Milestone 6 | G83: 06-Aug-2026 | H83: 07-Aug-2026 | I83: Pushyami
A84: 70 | B84: iWork | C84: VRK - PROD Feedback: 6-Aug-2026 | D84: BizDone: Update "Policy Owner" to "Policy Created by" | E84: QA - WIP | F84: Milestone 6 | G84: 06-Aug-2026 | H84: 06-Aug-2026 | I84: Prathiphala
A85: 71 | B85: iWork | C85: VRK - PROD Feedback: 6-Aug-2026 | D85: Rename "Associate CRM" with "Associate" throughout the Application and Report | E85: QA - WIP | F85: Milestone 6 | G85: 06-Aug-2026 | H85: 06-Aug-2026 | I85: Prathiphala
A86: 72 | B86: iWork | C86: VRK - PROD Feedback: 9-Jun-2026 | D86: Dual approval mechanism - current logic and recommendation to enable as per the current CRM hierarchy | E86: Pre-PROD | F86: Milestone 6 | G86: 09-Jun-2026 | H86: 03-Aug-2026 | I86: Jagadeesh
A87: 73 | B87: iWork | C87: VRK - PROD Feedback: 6-Aug-2026 | D87: Branches deletion & Map to valid Branch - (PL-XXXXX) | E87: Delivered | F87: Milestone 6 | G87: 06-Aug-2026 | H87: 06-Aug-2026 | I87: Rama
A88: 🗓 No ETA assigned · 7 items
A89: 74 | B89: iWork | C89: VRK - PROD Feedback: 6-Aug-2026 | D89: RO's are showing as 'SO'. Identify the RCA, share the list, and update valid type | E89: Yet to start | F89: Milestone 6 | G89: 06-Aug-2026
A90: 75 | B90: iWork | C90: VRK - PROD Feedback: 6-Aug-2026 | D90: Update Target values in the Application | E90: Yet to start | F90: Milestone 6 | G90: 06-Aug-2026 | J90: IIRM Team to provide the data
A91: 76 | B91: iWork | C91: VRK - PROD Feedback: 6-Aug-2026 | D91: My RO - KPI - Definition & based on business we have to update the logic | E91: Yet to start | F91: Milestone 6 | G91: 06-Aug-2026 | I91: Karan | J91: Nithin Provided the definition
A92: 77 | B92: iWork | C92: VRK - PROD Feedback: 6-Aug-2026 | D92: Bulk Assignment - Redesign to make up a wizard basis | E92: Yet to start | F92: Milestone 6 | G92: 06-Aug-2026
A93: 78 | B93: iWork | C93: VRK - PROD Feedback: 6-Aug-2026 | D93: My Client Portfolio - Drill-down Need a better design. At Company level - View SO, View RO, View Policies | E93: Yet to start | F93: Milestone 6 | G93: 06-Aug-2026
A94: 79 | B94: iWork | C94: VRK - PROD Feedback: 6-Aug-2026 | D94: 2025-26 Ownership Updates: Endorsements - Policy - Company - Opportunity as per the endorsement_crm provided | E94: QA - WIP | F94: Milestone 6 | G94: 06-Aug-2026 | J94: Kapil is validating the data
A95: 80 | B95: iWork - CR | C95: VRK - PROD Feedback: 13-Jul-2026 | D95: Dashboard Issues - Organization-wise summary cards are not required. | E95: Not in scope | F95: Milestone 6 | G95: 13-Jul-2026 | J95: Madhav sir confirmed via Teams Chat

Sheet SOW - Actual Items
A1: Module | B1: Functionality | C1: Module | D1: Module | E1: Match Status | F1: Refer to "SOW, Feedbacks-Bug & CR_Items"
A2: UI Approach Style Establishment | B2: UI Style Establishment | C2: Framework | D2: Milestone 1 | E2: ✓ Found in tracker
A3: UI Approach Design System | B3: Building Design System | C3: Framework | D3: Milestone 1 | E3: ✓ Found in tracker
A4: Project setup | B4: Basic project / Development environment setup | C4: Framework | D4: Milestone 1 | E4: ✓ Found in tracker
A5: Build UI components | B5: This includes all the UI componnets to compose the application and module definitions: Form, Toast, Filter, Cards, Visualisation, Grid, Menu, Header, Footer, Maps Integration | C5: Framework | D5: Milestone 1 | E5: ✓ Found in tracker
A6: Core System | C6: Framework | D6: Milestone 1 | E6: ✓ Found in tracker
A7: ACL & RBAC Control Framework | C7: Framework | D7: Milestone 1 | E7: ✓ Found in tracker
A8: Micro Frontend Setup | C8: Framework | D8: Milestone 1 | E8: ✓ Found in tracker
A9: Service Workers Implementation | C9: Framework | D9: Milestone 1 | E9: ✓ Found in tracker
A10: Landing Page | C10: Framework | D10: Milestone 1 | E10: ✓ Found in tracker
A11: Access Control Management | C11: Framework | D11: Milestone 1 | E11: ✓ Found in tracker
A12: Auth Module (Simple Auth) | C12: Framework | D12: Milestone 1 | E12: ✓ Found in tracker
A13: Micro Service Framework Setup | C13: Framework | D13: Milestone 1 | E13: ✓ Found in tracker
A14: Company (Prospect) Hub | B14: Top 10/Latest companies, with search/filter, Table of basic attributes with GPS etc. | C14: iWork | D14: Milestone 1 | E14: ✓ Found in tracker
A15: Add/View/Edit Company | B15: Large form with basic format based validations, some mandatory fields, multiple addresses, couple of Rich Text Editor fields; Some multi-line fields (e.g., GST), uploads; Duplicate detection on Company name, GST/PAN etc. Simple edit like Add; View is multiple widgets (Contacts, Opportunities, Policies, Claims, SLAs, Document list) | C15: iWork | D15: Milestone 1 | E15: ✓ Found in tracker
A16: Contact Hub | B16: Top 10/Latest Contacts, with search/filter, list with basic attributes | C16: iWork | D16: Milestone 1 | E16: ✓ Found in tracker
A17: Add/View/Edit Contact | B17: Simple edit like Add Contacts should maintain Company history although only 1 Company active with 1 contact; Medium size form with fields, linked in connect | C17: iWork | D17: Milestone 1 | E17: ✓ Found in tracker
A18: Opportunity Hub | B18: Top Opportunities with search/filter, List of opportunities with high level summaries | C18: iWork | D18: Milestone 1 | E18: ✓ Found in tracker
A19: Add/View/Edit Opportunity | B19: Add Medium size form with 1->N list of Claims; Multiple drop downs Large View with several widgets, Simple Edit | C19: iWork | D19: Milestone 1 | E19: ✓ Found in tracker
A20: Insurer/TPA Hub | B20: List with Filter/Search | C20: iWork | D20: Milestone 1 | E20: ✓ Found in tracker
A21: Manage TPA/Insurer | B21: Basic Add, View with edit of basic data, with lists of policies/companies | C21: iWork | D21: Milestone 1 | E21: ✓ Found in tracker
A22: Contact /Company/Insurer/TPA Mgmt | C22: iWork | D22: Milestone 1 | E22: ✓ Found in tracker
A23: Task Mgmt | C23: iWork | D23: Milestone 1 | E23: ✓ Found in tracker
A24: Meeting Mgmt | C24: iWork | D24: Milestone 1 | E24: ✓ Found in tracker
A25: Employee Mgmt | C25: iWork | D25: Milestone 1 | E25: ✓ Found in tracker
A26: RBAC and ACL setup for Iwork Module | C26: iWork | D26: Milestone 1 | E26: ✓ Found in tracker
A27: Opportunity Mgmt | C27: iWork | D27: Milestone 1 | E27: ✓ Found in tracker
A28: Common - Audit Trail Mgmt - Becomes critical in this phase iteself | C28: iWork | D28: Milestone 1 | E28: ✓ Found in tracker
A29: Visualization framework | B29: Charts and KPIs | C29: Framework | D29: Milestone 2 | E29: ✓ Found in tracker
A30: Visualization framework (mobile) | B30: Charts and KPIs | C30: Framework | D30: Milestone 2 | E30: 🔗 Mapped (see note) | F30: Map to line number 35 in Sheet-SOW, Feedbacks-Bug & CR_Items
A31: User Management | C31: Framework | D31: Milestone 2 | E31: ✓ Found in tracker
A32: Notifications Management | C32: Framework | D32: Milestone 2 | E32: ✓ Found in tracker
A33: Document Management | B33: Create, Upload, Seach, Download | C33: Framework | D33: Milestone 2 | E33: ✓ Found in tracker
A34: Document Management (Mobile) | B34: Create, Upload, Seach, Download | C34: Framework | D34: Milestone 2 | E34: 🔗 Mapped (see note) | F34: Map to line number 36 in Sheet-SOW, Feedbacks-Bug & CR_Items
A35: Caching of API Data | C35: Framework | D35: Milestone 2 | E35: ✓ Found in tracker
A36: Caching of API Data (Mobile) | C36: Framework | D36: Milestone 2 | E36: 🔗 Mapped (see note) | F36: Map to line number 37 in Sheet-SOW, Feedbacks-Bug & CR_Items
A37: Master Data Management | C37: Framework | D37: Milestone 2 | E37: ✓ Found in tracker
A38: User Management | C38: Framework | D38: Milestone 2 | E38: ✓ Found in tracker
A39: Notification and Communication Management | C39: Framework | D39: Milestone 2 | E39: ✓ Found in tracker
A40: Audit Data Capturing | C40: Framework | D40: Milestone 2 | E40: ✓ Found in tracker
A41: Usage Tracking System | C41: Framework | D41: Milestone 2 | E41: 🔗 Mapped (see note) | F41: Map to line number 41 in Sheet-SOW, Feedbacks-Bug & CR_Items
A42: CMS | C42: Framework | D42: Milestone 2 | E42: ✓ Found in tracker
A43: Data Security Considerations | B43: Data ca n be accessed only through the APIs and in the same network Database can be accessed on through Jumphost Database access is based on privilages | C43: Framework | D43: Milestone 2 | E43: ✓ Found in tracker
A44: Dashboard | B44: Multiple KPI Cards: Business Performance, Svc Performance, Table of targets vs. actuals vs. lost, Sales Funnel, Renewal Funnel, Servce Funnel, AR from Insurers, Pending Activities(iWork Stages) Widget, Followups widget, Meetings widget Filters available (Geo, Branch, Team/Team Member, Dates), Approvals, iWork Stages, Tasks, Meetings | C44: iWork | D44: Milestone 2 | E44: ✓ Found in tracker
A45: Dashboard - Drilldowns | B45: Drill down from the Tables (Targets vs. Actuals, Pending Activities, Followups, AR Report, Schedule) | C45: iWork | D45: Milestone 2 | E45: ✓ Found in tracker
A46: Dashboard - Pending tasks, approvals | B46: Pending tasks/approvals, | C46: iWork | D46: Milestone 2 | E46: ✓ Found in tracker
A47: Manage Stage Planning/Performance/Approval | B47: Add iWork Stages (table) - Dates with each iWork Stage and who are the team members assigned to each Stage; Once all iWork stages are complete, ISG Team activities must be planned ISG Team can approve/reject each iWork Stage. Approving RFP Stage approves all iWork stages Completion of each iWork Stage (Activity) & ISG Stage - Comments, Attach Document, Date recorded, submit | C47: iWork | D47: Milestone 2 | E47: ✓ Found in tracker
A48: Sales Team Hierarchy | B48: Hierarchy / Org chart tied to Platform Users | C48: iWork | D48: Milestone 2 | E48: ✓ Found in tracker
A49: View Policy | B49: Long View, multiple widgets/entities, endorsements (each month), Claims, etc. | C49: iWork | D49: Milestone 2 | E49: ✓ Found in tracker
A50: Common Data Mapping Component | B50: Map input fields to output fields & Order | C50: iWork | D50: Milestone 2 | E50: ✓ Found in tracker
A51: Reports - Biz Done | B51: Report View, Download, List of earlier snaps of the report, Search and Filter | C51: iWork | D51: Milestone 2 | E51: ✓ Found in tracker
A52: Smart Add Component | B52: Allow Upload of Document/Image, select what to create (Company/Contact/Opportunity) | C52: iWork | D52: Milestone 2 | E52: ✓ Found in tracker
A53: Organisation, Branch, Employee, & Hierarchy Mgmt | C53: iWork | D53: Milestone 2 | E53: ✓ Found in tracker
A54: Cut Off Mgmt | C54: iWork | D54: Milestone 2 | E54: ✓ Found in tracker
A55: Dashboard (Place Holder) | C55: iWork | D55: Milestone 2 | E55: ✓ Found in tracker
A56: Planning, Perform and Approval Mgmt | C56: iWork | D56: Milestone 2 | E56: ✓ Found in tracker
A57: Policy Mgmt | C57: iWork | D57: Milestone 2 | E57: ✓ Found in tracker
A58: AI - (Non-OCR) Digital Document Processing for Content recognition (Company/Opportunity/Contact Creation from Previous Policy Document, Bizcard document) | C58: iWork | D58: Milestone 2 | E58: ✓ Found in tracker
A59: AI - OCR for Content Collection | C59: iWork | D59: Milestone 2 | E59: ✓ Found in tracker
A60: AI - Company Information by AI Search | C60: iWork | D60: Milestone 2 | E60: ✓ Found in tracker
A61: Common, Contexual Upload Component | C61: iWork | D61: Milestone 2 | E61: ✓ Found in tracker
A62: Common, Contexual Read and Spread Component | C62: iWork | D62: Milestone 2 | E62: 🔗 Mapped (see note) | F62: Map to line number 47 in Sheet-SOW, Feedbacks-Bug & CR_Items
A63: HR/Admin Portal View | B63: Supporting services for Admin Portal | C63: IBP | D63: Milestone 2 | E63: ✓ Found in tracker
A64: Document Generation | C64: Framework | D64: Milestone 3 | E64: ✓ Found in tracker
A65: Manage Policy (Endorsements) | B65: Add Endorsement - basic form with uploads of excel/document Validations of endorsement format - Map customer fields to internal fields Map internal fields to TPA fields (occasional per TPA) View/Update Endorsement, List View, Endorsement Performance | C65: iWork | D65: Milestone 3 | E65: ✓ Found in tracker
A66: MIR Entry Mgmt | B66: Entry Form, Print to Document, List of Earlier MIRs, Search on MIRs | C66: iWork | D66: Milestone 3 | E66: ✓ Found in tracker
A67: Master Data Mgmt {Common, Contexual Master Data Mgmt} | C67: iWork | D67: Milestone 3 | E67: ✓ Found in tracker
A68: Stage Mgmt (Activity/Transaction/Quote) | C68: iWork | D68: Milestone 3 | E68: ✓ Found in tracker
A69: Asset/Member Data Mgmt | C69: iWork | D69: Milestone 3 | E69: ✓ Found in tracker
A70: Cover Mgmt | C70: iWork | D70: Milestone 3 | E70: ✓ Found in tracker
A71: Endorsement Mgmt | C71: iWork | D71: Milestone 3 | E71: ✓ Found in tracker
A72: MIR Entry Mgmt | B72: Module to manage MIR {Monthly Information Report} | C72: iWork | D72: Milestone 3 | E72: ✓ Found in tracker
A73: Accessibility | C73: Framework | D73: Milestone 4 | E73: ✓ Found in tracker
A74: Localisation | C74: Framework | D74: Milestone 4 | E74: ✓ Found in tracker
A75: Configuration Management | C75: Framework | D75: Milestone 4 | E75: ✓ Found in tracker
A76: Feature Flag Control Management | C76: Framework | D76: Milestone 4 | E76: ✓ Found in tracker
A77: Workflow Management | C77: Framework | D77: Milestone 4 | E77: ✓ Found in tracker
A78: Rule Definition Management | C78: Framework | D78: Milestone 4 | E78: ✓ Found in tracker
A79: Caching Implementation | C79: Framework | D79: Milestone 4 | E79: ✓ Found in tracker
A80: Localistation Management | C80: Framework | D80: Milestone 4 | E80: ✓ Found in tracker
A81: Knowledge Central | B81: Grouped list of Documents/Resources, Add a Document, Remove a Document (Add/remove only for admins) | C81: iWork | D81: Milestone 4 | E81: ✓ Found in tracker
A82: View Service Score | B82: Servicing Stats Dashboard - Single Table (drillable) to calculate an overall score | C82: iWork | D82: Milestone 4 | E82: ✓ Found in tracker
A83: Knowledge Central | C83: iWork | D83: Milestone 4 | E83: ✓ Found in tracker
A84: TAT/SLA Mgmt (Including Service Score) | C84: iWork | D84: Milestone 4 | E84: ✓ Found in tracker
A85: Country Handling {Data Source Mgmt} | B85: Physical data storage is limiited to a particular country and can't be combined with other country data | C85: iWork | D85: Milestone 4 | E85: 🔗 Mapped (see note) | F85: Map to line number 115 in Sheet-SOW, Feedbacks-Bug & CR_Items
A86: Archived Oppurtunity, Policy Mgmt {Archived Biz Data and Retrieval on need} | C86: iWork | D86: Milestone 4 | E86: 🔗 Mapped (see note) | F86: Map to line number 71 in Sheet-SOW, Feedbacks-Bug & CR_Items
A87: IBP Landing Page - Basic | B87: Basic Landing Page with only company plans and summary | C87: IBP | D87: Milestone 4 | E87: ✓ Found in tracker
A88: My Insurance | B88: Hub of all plans I have as an employee - both Company provided and individually signed up. Mostly a navigational page | C88: IBP | D88: Milestone 4 | E88: ✓ Found in tracker
A89: Company Plans | B89: 6 Policies - GMC, GPA, GTL, Parental Plicy, Top-ups, OPD Policy (Summary view of policies | C89: IBP | D89: Milestone 4 | E89: ✓ Found in tracker
A90: Per-policy Enrolment | B90: Enrolment and addon policy selection | C90: IBP | D90: Milestone 4 | E90: ✓ Found in tracker
A91: Company Plan Configurator | B91: Admin side of IBP should configure (per Corporate) how to define a Policy and determine how it breaks down the Premium and Coverage rules | C91: IBP/iWork | D91: Milestone 4 | E91: ✓ Found in tracker
A92: My Documents | B92: Document Hub - covers Policies, Prescriptions, Reports | C92: IBP | D92: Milestone 4 | E92: ✓ Found in tracker
A93: User Profile | B93: Profile, Service Subscriptions, Feedback | C93: IBP | D93: Milestone 4 | E93: ✓ Found in tracker
A94: Whitelabelling | B94: Whitelabelling based on Org needs (IBP Admin) | C94: IBP/iWork | D94: Milestone 4 | E94: ✓ Found in tracker
A95: Contact Matrix | B95: Configure the Conact Info Matrix (IBP Admin) | C95: IBP/iWork | D95: Milestone 4 | E95: ✓ Found in tracker
A96: Contact Matrix View | B96: Contact Matrix View for end user | C96: IBP | D96: Milestone 4 | E96: ✓ Found in tracker
A97: Auth Config UI | B97: Config for Auth Rules setup | C97: IBP/iWork | D97: Milestone 4 | E97: ✓ Found in tracker
A98: Wellness Discount List Management | B98: Add/Remove/update Discount program benefits | C98: IBP/iWork | D98: Milestone 4 | E98: ✓ Found in tracker | F98: Map to line number 126 in Sheet-SOW, Feedbacks-Bug & CR_Items
A99: HR Portal View | B99: Employee Search, Resend Email, Update Employee Info, Delete Employees, Extend Enrollment Windows, Reports, Bulk Email | C99: IBP | D99: Milestone 4 | E99: ✓ Found in tracker
A100: Basic Landing Page Services | B100: Company provided plans only | C100: IBP | D100: Milestone 4 | E100: ✓ Found in tracker
...

Sheet Stablization Items
A1: List of Stabilization Items
A2: Sl. # | B2: Module | C2: Sub-Module | D2: Item | E2: Efforts (Hrs.) | F2: Assigned To | G2: Status | H2: Start Date | I2: End Date | J2: Requested Date
A3: 1 | B3: BizDone | D3: Offload Excel Generation: Disconnect report generation from HTTP requests to prevent timeout issues. Use an asynchronous thread or long polling for status updates and file downloading.
B4: BizDone | C4: 1-A | D4: API Tweaks for making data request | E4: 2 | F4: Sunil | G4: Yet to start | H4: 46237 | I4: 46237 | J4: 46234
B5: BizDone | D5: Implementing queue / query building | E5: 10 | F5: Sunil | G5: Yet to start | H5: 46237 | I5: 46238 | J5: 46234
B6: BizDone | D6: Tweaks / Update Procees the data onto file and store / upload to storage | E6: 8 | F6: Sunil | G6: Yet to start | H6: 46238 | I6: 46239 | J6: 46234
B7: BizDone | D7: Long Poling Implementation for Bizdone Download - Front End | E7: 4 | F7: Sunil | G7: Yet to start | H7: 46239 | I7: 46239 | J7: 46234
B8: BizDone | C8: 1-B | D8: Query Tuning for Binzdone Query, Dashboard Performances | E8: 16 | F8: Abhilash | G8: Yet to start | H8: 46237 | I8: 46238 | J8: 46234
B9: Dashboard | C9: 1-C | D9: Implementation of the dynamic fetching of the dashboard widgets data without depending on performance output cron job | E9: 8 | F9: Ravi | G9: DEV - WIP | H9: 46237 | I9: 46237 | J9: 46234
B10: Dashboard | D10: Centralised code or util function to fetch the KPIs in biz done report and dashboard data for re-usability | E10: 16 | F10: Ravi | G10: Yet to start | H10: 46238 | I10: 46239 | J10: 46234
B11: BizDone | C11: 1-D | D11: Migration Data load Should be always complete only Performances Job Execution - Continous acitivity | E11: 0 | F11: Rama | G11: Yet to start | H11: 46237 | I11: 46237 | J11: 46234
A12: 2 | B12: Dashboard | D12: Having individual component loaders on the landing page for each component and web-socket framework to avoid long-loading blank page issue. | G12: Yet to start | J12: 46234
A13: 3 | B13: Jobs | D13: Process Jobs - Review, Enhance and document
B14: Jobs | C14: 3-A | D14: Job - Expiry Opportunity - Review and Enhance
B15: Jobs | C15: 3-B | D15: Job - Opportunity Creation - Review and Enhance
B16: Jobs | C16: 3-C | D16: Job - Dashboard
B17: Jobs | C17: 3-D
B18: Jobs | C18: 3-E
B19: Jobs | C19: 3-F
B20: Jobs | C20: 3-G
B21: Jobs | C21: 3-H
A22: 4
A23: 5
A24: 6
A25: 7
A26: 8
A27: 9
A28: 10

Sheet Jira Report
A1: Sl. # | B1: Jira ID | C1: Issue Type | D1: Summary | E1: Status | F1: Reporter | G1: Product | H1: Parent
A2: 1 | B2: IIRM-4 | C2: Story | D2: ACL Establishment | E2: Done | F2: Sai Vamsee K | G2: Framework | H2: IIRM-18 — SOW#1 - ACL & RBAC Control
A3: 2 | B3: IIRM-6 | C3: Story | D3: Architecture - iWork | E3: Done | F3: Sai Vamsee K | H3: IIRM-64 — SOW#3 - Micro Service Framework
A4: 3 | B4: IIRM-7 | C4: Story | D4: Implement simple authentication | E4: Done | F4: Sai Vamsee K | G4: Framework | H4: IIRM-62 — SOW#2 - Authentication
A5: 4 | B5: IIRM-9 | C5: Story | D5: UX - Core System (Research & Documentation) | E5: Done | F5: Sai Vamsee K | G5: Framework | H5: IIRM-80 — SOW#4 - Core System
A6: 5 | B6: IIRM-11 | C6: Story | D6: Design System - UI | E6: Done | F6: Sai Vamsee K | G6: Framework | H6: IIRM-734 — SOW#7 - UI Design System
A7: 6 | B7: IIRM-13 | C7: Story | D7: Product Spec - iWork (Org Structure, RBAC, Contacts, TPA, Insurer and Broker) | E7: Done | F7: Sai Vamsee K | G7: Framework | H7: IIRM-80 — SOW#4 - Core System
A8: 7 | B8: IIRM-14 | C8: Story | D8: UX/UI - Create/List and View Company | E8: Done | F8: Sai Vamsee K | G8: iWork | H8: IIRM-736 — SOW#9 - Add/Manage Company (Prospects)
A9: 8 | B9: IIRM-15 | C9: Story | D9: Frontend - Micro Frontend Setup | E9: Done | F9: Sai Vamsee K | G9: Framework | H9: IIRM-64 — SOW#3 - Micro Service Framework
A10: 9 | B10: IIRM-16 | C10: Story | D10: Micro Service Framework Setup | E10: Done | F10: Sai Vamsee K | G10: Framework | H10: IIRM-64 — SOW#3 - Micro Service Framework
A11: 10 | B11: IIRM-17 | C11: Story | D11: Core System - Overall Project setup | E11: Done | F11: Sai Vamsee K | G11: Framework | H11: IIRM-80 — SOW#4 - Core System
A12: 11 | B12: IIRM-18 | C12: Epic | D12: SOW#1 - ACL & RBAC Control | E12: Maintenance | F12: Sai Vamsee K | G12: Framework
A13: 12 | B13: IIRM-19 | C13: Story | D13: Frontend - Service Workers Implementation | E13: Done | F13: Sai Vamsee K | G13: Framework | H13: IIRM-64 — SOW#3 - Micro Service Framework
A14: 13 | B14: IIRM-20 | C14: Story | D14: Core System - Tech Tool Decisions (TechStack & Integration Choices) | E14: Done | F14: Sai Vamsee K | G14: Framework | H14: IIRM-80 — SOW#4 - Core System
A15: 14 | B15: IIRM-23 | C15: Sub-task | D15: UX/UI - Manage Company | E15: Done | F15: Sai Vamsee K | G15: iWork | H15: IIRM-14 — UX/UI - Create/List and View Company
A16: 15 | B16: IIRM-30 | C16: Sub-task | D16: Setting up Repositories with Users and permissions | E16: Done | F16: Sai Vamsee K | H16: IIRM-6 — Architecture - iWork
A17: 16 | B17: IIRM-31 | C17: Sub-task | D17: Analyse the Design Patterns to be followed | E17: Done | F17: Sai Vamsee K | H17: IIRM-6 — Architecture - iWork
A18: 17 | B18: IIRM-32 | C18: Sub-task | D18: Analyse and Create the Architectural Flow | E18: Done | F18: Sai Vamsee K | H18: IIRM-6 — Architecture - iWork
A19: 18 | B19: IIRM-33 | C19: Sub-task | D19: Analyse the CommonLib Implemenetation and Functions to include | E19: Done | F19: Sai Vamsee K | H19: IIRM-6 — Architecture - iWork
A20: 19 | B20: IIRM-38 | C20: Sub-task | D20: Set Up API Gateway | E20: Done | F20: Sai Vamsee K | G20: Framework | H20: IIRM-16 — Micro Service Framework Setup
A21: 20 | B21: IIRM-39 | C21: Sub-task | D21: Setup Auth Service as Microservice | E21: Done | F21: Sai Vamsee K | G21: Framework | H21: IIRM-16 — Micro Service Framework Setup
A22: 21 | B22: IIRM-40 | C22: Sub-task | D22: Initialize Environment Configurations for Micro Services | E22: Done | F22: Sai Vamsee K | G22: Framework | H22: IIRM-16 — Micro Service Framework Setup
A23: 22 | B23: IIRM-41 | C23: Sub-task | D23: Setup the Service registry for Micro services | E23: Done | F23: Sai Vamsee K | H23: IIRM-1739 — Microservices Framework Setup - Service registry, Gateway Config, Service Discovery, Service Config
A24: 23 | B24: IIRM-42 | C24: Sub-task | D24: Analyse and Database Schema Design | E24: Done | F24: Sai Vamsee K | G24: Framework | H24: IIRM-7 — Implement simple authentication
A25: 24 | B25: IIRM-43 | C25: Sub-task | D25: API Development for Simple Auth Implementation | E25: Done | F25: Sai Vamsee K | G25: Framework | H25: IIRM-7 — Implement simple authentication
A26: 25 | B26: IIRM-44 | C26: Sub-task | D26: Tokenizing Simple Auth Authentication | E26: Done | F26: Sai Vamsee K | G26: Framework | H26: IIRM-7 — Implement simple authentication
A27: 26 | B27: IIRM-45 | C27: Sub-task | D27: Basic project / Development environment setup | E27: Done | F27: Sai Vamsee K | G27: Framework | H27: IIRM-17 — Core System - Overall Project setup
A28: 27 | B28: IIRM-46 | C28: Sub-task | D28: Structurise the Frontend Micro Frontends | E28: Done | F28: Sai Vamsee K | G28: Framework | H28: IIRM-17 — Core System - Overall Project setup
A29: 28 | B29: IIRM-47 | C29: Sub-task | D29: Setup the Environment Configurations | E29: Done | F29: Sai Vamsee K | G29: Framework | H29: IIRM-17 — Core System - Overall Project setup
A30: 29 | B30: IIRM-48 | C30: Sub-task | D30: Define Micro Frontend Architecture and Structure | E30: Done | F30: Sai Vamsee K | G30: Framework | H30: IIRM-15 — Frontend - Micro Frontend Setup
A31: 30 | B31: IIRM-49 | C31: Sub-task | D31: Set Up the Host Application | E31: Done | F31: Sai Vamsee K | G31: Framework | H31: IIRM-15 — Frontend - Micro Frontend Setup
A32: 31 | B32: IIRM-50 | C32: Sub-task | D32: Service Worker Setup & Registration | E32: Done | F32: Sai Vamsee K | G32: Framework | H32: IIRM-19 — Frontend - Service Workers Implementation
A33: 32 | B33: IIRM-51 | C33: Sub-task | D33: Caching Strategy & Static Asset Caching | E33: Done | F33: Sai Vamsee K | G33: Framework | H33: IIRM-19 — Frontend - Service Workers Implementation
A34: 33 | B34: IIRM-57 | C34: Sub-task | D34: Define access control reqiurement | E34: Done | F34: VedaVyas | G34: Framework | H34: IIRM-4 — ACL Establishment
A35: 34 | B35: IIRM-59 | C35: Sub-task | D35: Implementing Background Sync for Offline Actions | E35: Done | F35: tharun | G35: Framework | H35: IIRM-19 — Frontend - Service Workers Implementation
... A37: 36 | B37: IIRM-61 | C37: Sub-task | D37: Testing, Debugging, and Optimizing Service Worker and Push Functionality | E37: Done | F37: tharun | G37: Framework | H37: IIRM-19 — Frontend - Service Workers Implementation
A38: 37 | B38: IIRM-62 | C38: Epic | D38: SOW#2 - Authentication | E38: Maintenance | F38: VedaVyas | G38: Framework
A39: 38 | B39: IIRM-64 | C39: Epic | D39: SOW#3 - Micro Service Framework | E39: WORK IN PROGRESS | F39: VedaVyas | G39: Framework
A40: 39 | B40: IIRM-65 | C40: Sub-task | D40: Set Up User Roles and Permissions Model | E40: Done | F40: VedaVyas | G40: Framework | H40: IIRM-4 — ACL Establishment
A41: 40 | B41: IIRM-66 | C41: Sub-task | D41: Integrate ACL Logic into Authentication and Authorization Flow | E41: Done | F41: VedaVyas | G41: Framework | H41: IIRM-4 — ACL Establishment
A42: 41 | B42: IIRM-67 | C42: Sub-task | D42: Implement Role-Based Access Control UI | E42: Done | F42: VedaVyas | G42: Framework | H42: IIRM-4 — ACL Establishment
A43: 42 | B43: IIRM-71 | C43: Sub-task | D43: Configure Microfrontend Projects | E43: Done | F43: VedaVyas | G43: Framework | H43: IIRM-15 — Frontend - Micro Frontend Setup
A44: 43 | B44: IIRM-72 | C44: Sub-task | D44: Develop Microfrontend Components | E44: Done | F44: VedaVyas | G44: Framework | H44: IIRM-15 — Frontend - Micro Frontend Setup
A45: 44 | B45: IIRM-73 | C45: Sub-task | D45: Implement Communication Between Microfrontends | E45: Done | F45: VedaVyas | G45: Framework | H45: IIRM-15 — Frontend - Micro Frontend Setup
A46: 45 | B46: IIRM-74 | C46: Sub-task | D46: Set Up API Gateway configuration | E46: Done | F46: VedaVyas | H46: IIRM-1739 — Microservices Framework Setup - Service registry, Gateway Config, Service Discovery, Service Config
A47: 46 | B47: IIRM-75 | C47: Sub-task | D47: Set Up Service Discovery | E47: Done | F47: VedaVyas | H47: IIRM-1739 — Microservices Framework Setup - Service registry, Gateway Config, Service Discovery, Service Config
A48: 47 | B48: IIRM-76 | C48: Sub-task | D48: Implement Inter-Service Communication | E48: Done | F48: VedaVyas | H48: IIRM-1739 — Microservices Framework Setup - Service registry, Gateway Config, Service Discovery, Service Config
A49: 48 | B49: IIRM-77 | C49: Sub-task | D49: Define Microservice Architecture and Components and basic setup | E49: Done | F49: VedaVyas | G49: Framework | H49: IIRM-16 — Micro Service Framework Setup
A50: 49 | B50: IIRM-78 | C50: Sub-task | D50: Break Down and Detail Architectural Flow | E50: Done | F50: VedaVyas | H50: IIRM-6 — Architecture - iWork
A51: 50 | B51: IIRM-79 | C51: Sub-task | D51: Develop CommonLib Functions and Utilities | E51: Done | F51: VedaVyas | H51: IIRM-6 — Architecture - iWork
A52: 51 | B52: IIRM-80 | C52: Epic | D52: SOW#4 - Core System | E52: WORK IN PROGRESS | F52: tharun | G52: Framework
A53: 52 | B53: IIRM-83 | C53: Story | D53: Grid component | E53: Done | F53: tharun | G53: Framework | H53: IIRM-733 — SOW#6 - UI Components
A54: 53 | B54: IIRM-84 | C54: Story | D54: Form generation component and utils | E54: Done | F54: tharun | G54: Framework | H54: IIRM-733 — SOW#6 - UI Components
A55: 54 | B55: IIRM-85 | C55: Sub-task | D55: Set Up the Table Component Skeleton | E55: Done | F55: tharun | G55: Framework | H55: IIRM-83 — Grid component
A56: 55 | B56: IIRM-86 | C56: Sub-task | D56: Implement Sorting and Pagination Logic | E56: Done | F56: tharun | G56: Framework | H56: IIRM-83 — Grid component
A57: 56 | B57: IIRM-87 | C57: Sub-task | D57: Implement Filtering and Data Population | E57: Done | F57: tharun | G57: Framework | H57: IIRM-83 — Grid component
A58: 57 | B58: IIRM-88 | C58: Sub-task | D58: Add Custom Styling configuration and cell renderer templates | E58: Done | F58: tharun | G58: Framework | H58: IIRM-83 — Grid component
A59: 58 | B59: IIRM-89 | C59: Sub-task | D59: Define the Object Structure for Form Generation | E59: Done | F59: tharun | G59: Framework | H59: IIRM-84 — Form generation component and utils
A60: 59 | B60: IIRM-90 | C60: Sub-task | D60: Build Form Generation Logic | E60: Done | F60: tharun | G60: Framework | H60: IIRM-84 — Form generation component and utils
A61: 60 | B61: IIRM-91 | C61: Sub-task | D61: Implement Validation Logic | E61: Done | F61: tharun | G61: Framework | H61: IIRM-84 — Form generation component and utils
A62: 61 | B62: IIRM-92 | C62: Sub-task | D62: Create Utility Functions for Dynamic Form Handling | E62: Done | F62: tharun | G62: Framework | H62: IIRM-84 — Form generation component and utils
A63: 62 | B63: IIRM-732 | C63: Epic | D63: SOW#5 - Access Control | E63: WORK IN PROGRESS | F63: Sidhant Kumar Das | G63: Framework
A64: 63 | B64: IIRM-733 | C64: Epic | D64: SOW#6 - UI Components | E64: Draft | F64: Sidhant Kumar Das | G64: Framework
A65: 64 | B65: IIRM-734 | C65: Epic | D65: SOW#7 - UI Design System | E65: WORK IN PROGRESS | F65: Sidhant Kumar Das | G65: Framework
A66: 65 | B66: IIRM-735 | C66: Epic | D66: SOW#8 - 11 Components / Modules | E66: WORK IN PROGRESS | F66: Sidhant Kumar Das | G66: Framework
A67: 66 | B67: IIRM-736 | C67: Epic | D67: SOW#9 - Add/Manage Company (Prospects) | E67: Maintenance | F67: Sidhant Kumar Das | G67: iWork
A68: 67 | B68: IIRM-737 | C68: Epic | D68: SOW#10 - Add/Manage Contact | E68: Maintenance | F68: Sidhant Kumar Das | G68: iWork
A69: 68 | B69: IIRM-738 | C69: Epic | D69: SOW#11 - Manage Tasks, Meetings | E69: Maintenance | F69: Sidhant Kumar Das | G69: iWork
A70: 69 | B70: IIRM-739 | C70: Epic | D70: SOW#12 - Manage Employees | E70: Maintenance | F70: Sidhant Kumar Das | G70: iWork
A71: 70 | B71: IIRM-740 | C71: Epic | D71: SOW#13 - Add/Manage Opportunity | E71: Maintenance | F71: Sidhant Kumar Das | G71: iWork
A72: 71 | B72: IIRM-741 | C72: Epic | D72: SOW#14 - Add/Manage Insurer | E72: Maintenance | F72: Sidhant Kumar Das | G72: iWork
A73: 72 | B73: IIRM-742 | C73: Epic | D73: SOW#15 - Add/Manage TPA | E73: Maintenance | F73: Sidhant Kumar Das | G73: iWork
A74: 73 | B74: IIRM-743 | C74: Epic | D74: SOW#16 - Data Visualization Components | E74: WORK IN PROGRESS | F74: Sidhant Kumar Das | G74: Framework
... A87: 86 | B87: IIRM-756 | C87: Epic | D87: SOW#29 - Manage ISG Stages | E87: Maintenance | F87: Sidhant Kumar Das | G87: iWork
A88: 87 | B88: IIRM-757 | C88: Epic | D88: SOW#30 - Manage Policy Endorsements | E88: WORK IN PROGRESS | F88: Sidhant Kumar Das
A89: 88 | B89: IIRM-758 | C89: Epic | D89: SOW#31 - MIR Entry Mgmt. (Monthly Information Report) | E89: Draft | F89: Sidhant Kumar Das
A90: 89 | B90: IIRM-759 | C90: Epic | D90: SOW#32 - Asset/Member Data Mgmt | E90: RELEASED | F90: Sidhant Kumar Das
A91: 90 | B91: IIRM-760 | C91: Epic | D91: SOW#33 - Document Generation | E91: WORK IN PROGRESS | F91: Sidhant Kumar Das
A92: 91 | B92: IIRM-761 | C92: Epic | D92: SOW#34 - Notifications Management | E92: WORK IN PROGRESS | F92: Sidhant Kumar Das
A93: 92 | B93: IIRM-762 | C93: Epic | D93: SOW#35 - Configuration Management | E93: RELEASED | F93: Sidhant Kumar Das
A94: 93 | B94: IIRM-763 | C94: Epic | D94: SOW#36 - Accessibility | E94: Draft | F94: Sidhant Kumar Das
A95: 94 | B95: IIRM-764 | C95: Epic | D95: SOW#37 - Localisation | E95: WORK IN PROGRESS | F95: Sidhant Kumar Das
A96: 95 | B96: IIRM-765 | C96: Epic | D96: SOW#38 - Rule Definition Management | E96: Draft | F96: Sidhant Kumar Das
A97: 96 | B97: IIRM-766 | C97: Epic | D97: SOW#39 - Workflow Management | E97: Draft | F97: Sidhant Kumar Das
A98: 97 | B98: IIRM-767 | C98: Epic | D98: SOW#40 - Caching Localisation | E98: Draft | F98: Sidhant Kumar Das
A99: 98 | B99: IIRM-768 | C99: Epic | D99: SOW#41 - Knowledge Central | E99: Maintenance | F99: Sidhant Kumar Das
... A127: 126 | B127: IIRM-797 | C127: Epic | D127: SOW#69 - Manage Opportunities | E127: WORK IN PROGRESS | F127: Sidhant Kumar Das
A128: 127 | B128: IIRM-811 | C128: Story | D128: Opportunity Hub | E128: Done | F128: Sidhant Kumar Das | G128: iWork | H128: IIRM-740 — SOW#13 - Add/Manage Opportunity
A129: 128 | B129: IIRM-813 | C129: Story | D129: Manage TPA Contact | E129: Done | F129: Sidhant Kumar Das | G129: iWork | H129: IIRM-742 — SOW#15 - Add/Manage TPA
A130: 129 | B130: IIRM-834 | C130: Story | D130: Backend - Micro Service Framework Setup | E130: Done | F130: Sidhant Kumar Das | G130: Framework | H130: IIRM-64 — SOW#3 - Micro Service Framework
A131: 130 | B131: IIRM-836 | C131: Story | D131: Build UI components | E131: Done | F131: Sidhant Kumar Das | G131: Framework | H131: IIRM-733 — SOW#6 - UI Components
A132: 131 | B132: IIRM-838 | C132: Story | D132: UI - Approach Style Establishment | E132: Done | F132: Sidhant Kumar Das | G132: Framework | H132: IIRM-734 — SOW#7 - UI Design System
A133: 132 | B133: IIRM-1041 | C133: Sub-task | D133: UI Approach Style Establishment Option 1 | E133: Done | F133: Sidhant Kumar Das | G133: Framework | H133: IIRM-838 — UI - Approach Style Establishment
A134: 133 | B134: IIRM-1043 | C134: Sub-task | D134: UI Approach Style Establishment Option 2 | E134: Done | F134: Sidhant Kumar Das | G134: Framework | H134: IIRM-838 — UI - Approach Style Establishment
A135: 134 | B135: IIRM-1070 | C135: Sub-task | D135: Setup API Gate way | E135: Done | F135: Sidhant Kumar Das | G135: Framework | H135: IIRM-834 — Backend - Micro Service Framework Setup
A136: 135 | B136: IIRM-1071 | C136: Sub-task | D136: Setup Auth Service as Microservice | E136: Done | F136: Sidhant Kumar Das | G136: Framework | H136: IIRM-834 — Backend - Micro Service Framework Setup
A137: 136 | B137: IIRM-1072 | C137: Sub-task | D137: Initialize Environment Configurations for Micro Services | E137: Done | F137: Sidhant Kumar Das | G137: Framework | H137: IIRM-834 — Backend - Micro Service Framework Setup
A138: 137 | B138: IIRM-1073 | C138: Sub-task | D138: Setup the Service registry for Micro services | E138: Done | F138: Sidhant Kumar Das | G138: Framework | H138: IIRM-834 — Backend - Micro Service Framework Setup
A139: 138 | B139: IIRM-1104 | C139: Sub-task | D139: UI Components - Forms and Form Utils | E139: Done | F139: Sidhant Kumar Das | G139: Framework | H139: IIRM-836 — Build UI components
... A155: 154 | B155: IIRM-1493 | C155: QAlity Test | D155: TC_001: Admin: Login with Valid Credentials | E155: Draft | F155: SaikumarMahanthi | G155: Framework | H155: IIRM-18 — SOW#1 - ACL & RBAC Control
...

Sheet Helper
A1: Module | B1: Phase | C1: Status | D1: Category | E1: Bucket | F1: ReqDate
A2: ='SOW, Feedbacks-Bug & CR_Items'!D2 -> DPDP | B2: ='SOW, Feedbacks-Bug & CR_Items'!E2 -> Milestone 5 | C2: =TRIM('SOW, Feedbacks-Bug & CR_Items'!F2) -> Delivered | D2: =IFERROR(VLOOKUP(C2,Config!$A:$B,2,0),"Unknown") -> Delivered | E2: =IFERROR(VLOOKUP(C2,Config!$A:$C,3,0),"N/A") -> Delivered | F2: =IF('SOW, Feedbacks-Bug & CR_Items'!H2="","",'SOW, Feedbacks-Bug & CR_Items'!H2) -> 45869
A3: ='SOW, Feedbacks-Bug & CR_Items'!D3 -> DPDP | B3: ='SOW, Feedbacks-Bug & CR_Items'!E3 -> Milestone 5 | C3: =TRIM('SOW, Feedbacks-Bug & CR_Items'!F3) -> Delivered | D3: =IFERROR(VLOOKUP(C3,Config!$A:$B,2,0),"Unknown") -> Delivered | E3: =IFERROR(VLOOKUP(C3,Config!$A:$C,3,0),"N/A") -> Delivered | F3: =IF('SOW, Feedbacks-Bug & CR_Items'!H3="","",'SOW, Feedbacks-Bug & CR_Items'!H3) -> 45869
A4: ='SOW, Feedbacks-Bug & CR_Items'!D4 -> DPDP | B4: ='SOW, Feedbacks-Bug & CR_Items'!E4 -> Milestone 5 | C4: =TRIM('SOW, Feedbacks-Bug & CR_Items'!F4) -> Delivered | D4: =IFERROR(VLOOKUP(C4,Config!$A:$B,2,0),"Unknown") -> Delivered | E4: =IFERROR(VLOOKUP(C4,Config!$A:$C,3,0),"N/A") -> Delivered | F4: =IF('SOW, Feedbacks-Bug & CR_Items'!H4="","",'SOW, Feedbacks-Bug & CR_Items'!H4) -> 45869
A5: ='SOW, Feedbacks-Bug & CR_Items'!D5 -> DPDP | B5: ='SOW, Feedbacks-Bug & CR_Items'!E5 -> Milestone 5 | C5: =TRIM('SOW, Feedbacks-Bug & CR_Items'!F5) -> Delivered | D5: =IFERROR(VLOOKUP(C5,Config!$A:$B,2,0),"Unknown") -> Delivered | E5: =IFERROR(VLOOKUP(C5,Config!$A:$C,3,0),"N/A") -> Delivered | F5: =IF('SOW, Feedbacks-Bug & CR_Items'!H5="","",'SOW, Feedbacks-Bug & CR_Items'!H5) -> 45869
A6: ='SOW, Feedbacks-Bug & CR_Items'!D6 -> DPDP | B6: ='SOW, Feedbacks-Bug & CR_Items'!E6 -> Milestone 5 | C6: =TRIM('SOW, Feedbacks-Bug & CR_Items'!F6) -> Delivered | D6: =IFERROR(VLOOKUP(C6,Config!$A:$B,2,0),"Unknown") -> Delivered | E6: =IFERROR(VLOOKUP(C6,Config!$A:$C,3,0),"N/A") -> Delivered | F6: =IF('SOW, Feedbacks-Bug & CR_Items'!H6="","",'SOW, Feedbacks-Bug & CR_Items'!H6) -> 45869
A7: ='SOW, Feedbacks-Bug & CR_Items'!D7 -> DPDP | B7: ='SOW, Feedbacks-Bug & CR_Items'!E7 -> Milestone 5 | C7: =TRIM('SOW, Feedbacks-Bug & CR_Items'!F7) -> Delivered | D7: =IFERROR(VLOOKUP(C7,Config!$A:$B,2,0),"Unknown") -> Delivered | E7: =IFERROR(VLOOKUP(C7,Config!$A:$C,3,0),"N/A") -> Delivered | F7: =IF('SOW, Feedbacks-Bug & CR_Items'!H7="","",'SOW, Feedbacks-Bug & CR_Items'!H7) -> 45869
A8: ='SOW, Feedbacks-Bug & CR_Items'!D8 -> DPDP | B8: ='SOW, Feedbacks-Bug & CR_Items'!E8 -> Milestone 5 | C8: =TRIM('SOW, Feedbacks-Bug & CR_Items'!F8) -> DEV - WIP | D8: =IFERROR(VLOOKUP(C8,Config!$A:$B,2,0),"Unknown") -> In Development | E8: =IFERROR(VLOOKUP(C8,Config!$A:$C,3,0),"N/A") -> Pending | F8: =IF('SOW, Feedbacks-Bug & CR_Items'!H8="","",'SOW, Feedbacks-Bug & CR_Items'!H8) -> 45869
A9: ='SOW, Feedbacks-Bug & CR_Items'!D9 -> DPDP | B9: ='SOW, Feedbacks-Bug & CR_Items'!E9 -> Milestone 5 | C9: =TRIM('SOW, Feedbacks-Bug & CR_Items'!F9) -> DEV - WIP | D9: =IFERROR(VLOOKUP(C9,Config!$A:$B,2,0),"Unknown") -> In Development | E9: =IFERROR(VLOOKUP(C9,Config!$A:$C,3,0),"N/A") -> Pending | F9: =IF('SOW, Feedbacks-Bug & CR_Items'!H9="","",'SOW, Feedbacks-Bug & CR_Items'!H9) -> 45869
A10: ='SOW, Feedbacks-Bug & CR_Items'!D10 -> DPDP | B10: ='SOW, Feedbacks-Bug & CR_Items'!E10 -> Milestone 5 | C10: =TRIM('SOW, Feedbacks-Bug & CR_Items'!F10) -> DEV - WIP | D10: =IFERROR(VLOOKUP(C10,Config!$A:$B,2,0),"Unknown") -> In Development | E10: =IFERROR(VLOOKUP(C10,Config!$A:$C,3,0),"N/A") -> Pending | F10: =IF('SOW, Feedbacks-Bug & CR_Items'!H10="","",'SOW, Feedbacks-Bug & CR_Items'!H10) -> 45869
A11: ='SOW, Feedbacks-Bug & CR_Items'!D11 -> DPDP | B11: ='SOW, Feedbacks-Bug & CR_Items'!E11 -> Milestone 5 | C11: =TRIM('SOW, Feedbacks-Bug & CR_Items'!F11) -> DEV - Done | D11: =IFERROR(VLOOKUP(C11,Config!$A:$B,2,0),"Unknown") -> Dev Complete | E11: =IFERROR(VLOOKUP(C11,Config!$A:$C,3,0),"N/A") -> Delivered | F11: =IF('SOW, Feedbacks-Bug & CR_Items'!H11="","",'SOW, Feedbacks-Bug & CR_Items'!H11) -> 45869
A12: ='SOW, Feedbacks-Bug & CR_Items'!D12 -> DPDP | B12: ='SOW, Feedbacks-Bug & CR_Items'!E12 -> Milestone 5 | C12: =TRIM('SOW, Feedbacks-Bug & CR_Items'!F12) -> DEV - WIP | D12: =IFERROR(VLOOKUP(C12,Config!$A:$B,2,0),"Unknown") -> In Development | E12: =IFERROR(VLOOKUP(C12,Config!$A:$C,3,0),"N/A") -> Pending | F12: =IF('SOW, Feedbacks-Bug & CR_Items'!H12="","",'SOW, Feedbacks-Bug & CR_Items'!H12) -> 45869
A13: ='SOW, Feedbacks-Bug & CR_Items'!D13 -> DPDP | B13: ='SOW, Feedbacks-Bug & CR_Items'!E13 -> Milestone 5 | C13: =TRIM('SOW, Feedbacks-Bug & CR_Items'!F13) -> DEV - WIP | D13: =IFERROR(VLOOKUP(C13,Config!$A:$B,2,0),"Unknown") -> In Development | E13: =IFERROR(VLOOKUP(C13,Config!$A:$C,3,0),"N/A") -> Pending | F13: =IF('SOW, Feedbacks-Bug & CR_Items'!H13="","",'SOW, Feedbacks-Bug & CR_Items'!H13) -> 45869
... A427: ='SOW, Feedbacks-Bug & CR_Items'!D427 -> iWork | B427: ='SOW, Feedbacks-Bug & CR_Items'!E427 -> Milestone 6 | C427: =TRIM('SOW, Feedbacks-Bug & CR_Items'!F427) -> Yet to start | D427: =IFERROR(VLOOKUP(C427,Config!$A:$B,2,0),"Unknown") -> Not Started | E427: =IFERROR(VLOOKUP(C427,Config!$A:$C,3,0),"N/A") -> Pending | F427: =IF('SOW, Feedbacks-Bug & CR_Items'!H427="","",'SOW, Feedbacks-Bug & CR_Items'!H427) -> 46235

Sheet Config
A1: Status_Raw | B1: Category | C1: Bucket
A2: Delivered | B2: Delivered | C2: Delivered
A3: Dev - Done | B3: Dev Complete | C3: Delivered
A4: DEV - Done | B4: Dev Complete | C4: Delivered
A5: Dev - WIP | B5: In Development | C5: Pending
A6: DEV - WIP | B6: In Development | C6: Pending
A7: QA - WIP | B7: In QA | C7: Pending
A8: Pre-PROD | B8: Pre-PROD / UAT | C8: Pending
A9: UAT - WIP | B9: Pre-PROD / UAT | C9: Pending
A10: Yet to start | B10: Not Started | C10: Pending
A11: Delivered - Deficit | B11: Partial Delivery | C11: Pending
A12: Duplicate | B12: N/A | C12: N/A
... A14: Not in scope | B14: Delivered | C14: Delivered
